Workbook

Sheet Included
A1: First Author | B1: Publication Year | C1: PubMed link | D1: Study name | E1: Included in analysis | F1: Cohort size | G1: Age median | H1: Age min | I1: Age max | J1: Conditioning regimens: RIC | K1: Conditioning regimens: MAC | L1: Conditioning regimens: Unclear | M1: Antiviral PPX: AYC | N1: Antiviral PPX: GAN | O1: Antiviral PPX: FOS | P1: Antiviral PPX: Unclear | Q1: GVHD PPX: Cyclosporine | R1: GVHD PPX: CsA + MMF | S1: GVHD PPX: CsA + MMF + MTX | T1: GVHD PPX: CsA + MTX | U1: GVHD PPX: Cyclophos phamide | V1: GVHD PPX: Cy + CsA + MMF | W1: GVHD PPX: Cy + MMF + Tac or Siro | X1: GVHD PPX: MMF | Y1: GVHD PPX: TAC + MTX | Z1: GVHD PPX: CAMPATH-1 | AA1: GVHD PPX: Unclear | AB1: Tx type: BM | AC1: Tx type: PBSC | AD1: Tx type: CBT | AE1: Tx type: Unclear | AF1: N patients tested for HHV-6 | AG1: N patients with HHV-6 | AH1: N patients with HHV-6 detected after IR failure | AI1: N HHV-6 pos pts with delayed or failed engraftment (broadly) | AJ1: N HHV-6 pos pts with delayed or failed T cell engraftment | AK1: N HHV-6 pos pts with delayed or failed NK cell engraftment | AL1: N HHV-6 pos pts with delayed or failed neutrophil engraftment | AM1: N HHV-6 pos pts with delayed or failed platelet engraftment | AN1: HHV-6 pos min days to neutrophil engraftment | AO1: HHV-6 pos Q1 days to neutrophil engraftment | AP1: HHV-6 pos median days to neutrophil engraftment | AQ1: HHV-6 pos Q3 days to neutrophil engraftment | AR1: HHV-6 pos max days to neutrophil engraftment | AS1: HHV-6 pos min days to platelet engraftment | AT1: HHV-6 pos Q1 days to platelet engraftment | AU1: HHV-6 pos median days to platelet engraftment | AV1: HHV-6 pos Q3 days to platelet engraftment | AW1: HHV-6 pos max days to platelet engraftment | AX1: HHV-6 pos Q1 days to T cell engraftment | AY1: HHV-6 pos median days to T cell engraftment | AZ1: HHV-6 pos Q3 days to T cell engraftment | BA1: Combined HR/MHR neutrophil engraftment | BB1: Combined HR/MHR LB neutrophil engraftment | BC1: Combined HR/MHR UB neutrophil engraftment | BD1: Combined HR/MHR platelet engraftment | BE1: Combined HR/MHR LB platelet engraftment | BF1: Combined HR/MHR UB platelet engraftment | BG1: N patients with HHV-6 who engrafted neutrophils | BH1: N patients without HHV-6 who engrafted neutrophils | BI1: MHR HHV-6 neutrophil engraftment | BJ1: MHR LB HHV-6 neutrophil engraftment | BK1: MHR UB HHV-6 neutrophil engraftment | BL1: N patients with HHV-6 who engrafted platelets | BM1: N patients without HHV-6 who engrafted platelets | BN1: MHR HHV-6 platelets engraftment | BO1: MHR LB HHV-6 platelets engraftment | BP1: MHR UB HHV-6 platelets engraftment | BQ1: HR HHV-6 neutrophil engraftment | BR1: HR LB HHV-6 neutrophil engraftment | BS1: HR UB HHV-6 neutrophil engraftment | BT1: HR HHV-6 platelet engraftment | BU1: HR LB HHV-6 platelet engraftment | BV1: HR UB HHV-6 platelet engraftment | BW1: HR HHV-6 CD4 T cell engraftment | BX1: HR LB HHV-6 CD4 T cell engraftment | BY1: HR UB HHV-6 CD4 T cell engraftment | BZ1: HR HHV-6 CD8 T cell engraftment | CA1: HR LB HHV-6 CD8 T cell engraftment | CB1: HR UB HHV-6 CD8 T cell engraftment | CC1: N patients without HHV-6 | CD1: N HHV-6 neg pts with delayed or failed engraftment (broadly) | CE1: N HHV-6 neg pts with delayed or failed T cell engraftment | CF1: N HHV-6 neg pts with delayed or failed NK cell engraftment | CG1: N HHV-6 neg pts with delayed or failed neutrophil engraftment | CH1: N HHV-6 neg pts with delayed or failed platelet engraftment | CI1: HHV-6 neg min days to neutrophil engraftment | CJ1: HHV-6 neg Q1 days to neutrophil engraftment | CK1: HHV-6 neg median days to neutrophil engraftment | CL1: HHV-6 neg Q3 days to neutrophil engraftment | CM1: HHV-6 neg max days to neutrophil engraftment | CN1: HHV-6 neg min days to platelet engraftment | CO1: HHV-6 neg Q1 days to platelet engraftment | CP1: HHV-6 neg median days to platelet engraftment | CQ1: HHV-6 neg Q3 days to platelet engraftment | CR1: HHV-6 neg max days to platelet engraftment | CS1: HHV-6 neg Q1 days to T cell engraftment | CT1: HHV-6 neg median days to T cell engraftment | CU1: HHV-6 neg Q3 days to T cell engraftment | CV1: Definition of neutrophil reconstitution / engraftment | CW1: Definition of platelet reconstitution / engraftment | CX1: Notes
A2: Betts BC | B2: 2011 | C2: https://pubmed.ncbi.nlm.nih.gov/21549850 | D2: =A2&" "&B2 -> Betts BC 2011 | E2: =IF(OR(AND(ISNUMBER(AG2),ISNUMBER(AL2),ISNUMBER(CC2),ISNUMBER(CG2)),AND(ISNUMBER(AG2),ISNUMBER(AM2),ISNUMBER(CC2),ISNUMBER(CH2))),"Yes","No") -> Yes | F2: 82 | G2: 26 | H2: 1 | I2: 66 | J2: Given for HHV-6 pos but not whole cohort | K2: Given for HHV-6 pos but not whole cohort | P2: 82 | AA2: 82 | AD2: 37 | AE2: =82-37 -> 45 | AF2: 82 | AG2: 46 | AH2: Timing of IR failure relative to HHV-6 detection is unclear, but systemic testing was performed | AI2: 7 | AL2: 7 | BA2: =IF(ISNUMBER(BQ2),BQ2,IF(AND(ISNUMBER($BJ2),ISNUMBER($BK2)),BI2,"")) | BB2: =IF(ISNUMBER(BR2),BR2,IF(AND(ISNUMBER($BJ2),ISNUMBER($BK2)),BJ2,"")) | BC2: =IF(ISNUMBER(BS2),BS2,IF(AND(ISNUMBER($BJ2),ISNUMBER($BK2)),BK2,"")) | BD2: =IF(ISNUMBER(BT2),BT2,IF(AND(ISNUMBER($BO2),ISNUMBER($BP2)),BN2,"")) | BE2: =IF(ISNUMBER(BU2),BU2,IF(AND(ISNUMBER($BO2),ISNUMBER($BP2)),BO2,"")) | BF2: =IF(ISNUMBER(BV2),BV2,IF(AND(ISNUMBER($BO2),ISNUMBER($BP2)),BP2,"")) | BJ2: =IF(AND(ISNUMBER(BG2),ISNUMBER(BH2),ISNUMBER(BI2)),EXP(LOG(BI2)-1.96*SQRT((1/BG2)+(1/BH2))),"") | BK2: =IF(AND(ISNUMBER(BG2),ISNUMBER(BH2),ISNUMBER(BI2)),EXP(LOG(BI2)+1.96*SQRT((1/BG2)+(1/BH2))),"") | BO2: =IF(AND(ISNUMBER(BL2),ISNUMBER(BM2),ISNUMBER(BN2)),EXP(LOG(BN2)-1.96*SQRT((1/BL2)+(1/BM2))),"") | BP2: =IF(AND(ISNUMBER(BL2),ISNUMBER(BM2),ISNUMBER(BN2)),EXP(LOG(BN2)+1.96*SQRT((1/BL2)+(1/BM2))),"") | CC2: 36 | CD2: 4 | CG2: 4 | CV2: Data given as "Bone marrow suppression/delayed engraftment". Bone marrow suppression was defined as recovery of HHV6 from marrow aspirates by PCR, accompanying worsening leukopenia, thrombocytopenia, and a hypoplastic marrow. | CX2: marked broad engraftment as neutrophil
A3: Chan PK | B3: 1997 | C3: https://pubmed.ncbi.nlm.nih.gov/9365899 | D3: =A3&" "&B3 -> Chan PK 1997 | E3: =IF(OR(AND(ISNUMBER(AG3),ISNUMBER(AL3),ISNUMBER(CC3),ISNUMBER(CG3)),AND(ISNUMBER(AG3),ISNUMBER(AM3),ISNUMBER(CC3),ISNUMBER(CH3))),"Yes","No") -> Yes | F3: 61 | G3: Unclear | H3: Unclear | I3: Unclear | K3: 33 | L3: =61-33 -> 28 | P3: 61 | AA3: 61 | AB3: 61 | AF3: 61 | AG3: 17 | AH3: Timing of IR failure relative to HHV-6 detection is unclear, but systemic testing was performed | AL3: 1 | BA3: =IF(ISNUMBER(BQ3),BQ3,IF(AND(ISNUMBER($BJ3),ISNUMBER($BK3)),BI3,"")) | BB3: =IF(ISNUMBER(BR3),BR3,IF(AND(ISNUMBER($BJ3),ISNUMBER($BK3)),BJ3,"")) | BC3: =IF(ISNUMBER(BS3),BS3,IF(AND(ISNUMBER($BJ3),ISNUMBER($BK3)),BK3,"")) | BD3: =IF(ISNUMBER(BT3),BT3,IF(AND(ISNUMBER($BO3),ISNUMBER($BP3)),BN3,"")) | BE3: =IF(ISNUMBER(BU3),BU3,IF(AND(ISNUMBER($BO3),ISNUMBER($BP3)),BO3,"")) | BF3: =IF(ISNUMBER(BV3),BV3,IF(AND(ISNUMBER($BO3),ISNUMBER($BP3)),BP3,"")) | BJ3: =IF(AND(ISNUMBER(BG3),ISNUMBER(BH3),ISNUMBER(BI3)),EXP(LOG(BI3)-1.96*SQRT((1/BG3)+(1/BH3))),"") | BK3: =IF(AND(ISNUMBER(BG3),ISNUMBER(BH3),ISNUMBER(BI3)),EXP(LOG(BI3)+1.96*SQRT((1/BG3)+(1/BH3))),"") | BO3: =IF(AND(ISNUMBER(BL3),ISNUMBER(BM3),ISNUMBER(BN3)),EXP(LOG(BN3)-1.96*SQRT((1/BL3)+(1/BM3))),"") | BP3: =IF(AND(ISNUMBER(BL3),ISNUMBER(BM3),ISNUMBER(BN3)),EXP(LOG(BN3)+1.96*SQRT((1/BL3)+(1/BM3))),"") | CC3: 44 | CG3: 1 | CV3: The date of engraftment of the transplanted marrow was defined as the first day post-transplantation when the absolute neutrophil count was >500 cells/ml of blood.
A4: Drobyski WR | B4: 1993 | C4: https://pubmed.ncbi.nlm.nih.gov/8382723 | D4: =A4&" "&B4 -> Drobyski WR 1993 | E4: =IF(OR(AND(ISNUMBER(AG4),ISNUMBER(AL4),ISNUMBER(CC4),ISNUMBER(CG4)),AND(ISNUMBER(AG4),ISNUMBER(AM4),ISNUMBER(CC4),ISNUMBER(CH4))),"Yes","No") -> Yes | F4: 16 | G4: ND | H4: ND | I4: ND | K4: 16 | M4: 16 | Q4: 16 | AB4: 16 | AF4: 16 | AG4: 6 | AH4: Timing of IR failure relative to HHV-6 detection is unclear | AL4: 1 | BA4: =IF(ISNUMBER(BQ4),BQ4,IF(AND(ISNUMBER($BJ4),ISNUMBER($BK4)),BI4,"")) | BB4: =IF(ISNUMBER(BR4),BR4,IF(AND(ISNUMBER($BJ4),ISNUMBER($BK4)),BJ4,"")) | BC4: =IF(ISNUMBER(BS4),BS4,IF(AND(ISNUMBER($BJ4),ISNUMBER($BK4)),BK4,"")) | BD4: =IF(ISNUMBER(BT4),BT4,IF(AND(ISNUMBER($BO4),ISNUMBER($BP4)),BN4,"")) | BE4: =IF(ISNUMBER(BU4),BU4,IF(AND(ISNUMBER($BO4),ISNUMBER($BP4)),BO4,"")) | BF4: =IF(ISNUMBER(BV4),BV4,IF(AND(ISNUMBER($BO4),ISNUMBER($BP4)),BP4,"")) | BJ4: =IF(AND(ISNUMBER(BG4),ISNUMBER(BH4),ISNUMBER(BI4)),EXP(LOG(BI4)-1.96*SQRT((1/BG4)+(1/BH4))),"") | BK4: =IF(AND(ISNUMBER(BG4),ISNUMBER(BH4),ISNUMBER(BI4)),EXP(LOG(BI4)+1.96*SQRT((1/BG4)+(1/BH4))),"") | BO4: =IF(AND(ISNUMBER(BL4),ISNUMBER(BM4),ISNUMBER(BN4)),EXP(LOG(BN4)-1.96*SQRT((1/BL4)+(1/BM4))),"") | BP4: =IF(AND(ISNUMBER(BL4),ISNUMBER(BM4),ISNUMBER(BN4)),EXP(LOG(BN4)+1.96*SQRT((1/BL4)+(1/BM4))),"") | CC4: =16-6 -> 10 | CG4: 0 | CV4: Engraftment in this patient population was considered to have occurred when there were 3 consecutive days with an absolute neutrophil count (ANC) ~500/mm3.
A5: Düver F | B5: 2020 | C5: https://pubmed.ncbi.nlm.nih.gov/32017805 | D5: =A5&" "&B5 -> Düver F 2020 | E5: =IF(OR(AND(ISNUMBER(AG5),ISNUMBER(AL5),ISNUMBER(CC5),ISNUMBER(CG5)),AND(ISNUMBER(AG5),ISNUMBER(AM5),ISNUMBER(CC5),ISNUMBER(CH5))),"Yes","No") -> Yes | F5: 107 | G5: 9 | H5: Unclear | I5: Unclear | K5: 107 | M5: =F5 -> 107 | Q5: =ROUND(F5*0.822,0) -> 88 | AB5: 20 | AC5: =F5-AB5 -> 87 | AG5: 36 | AH5: 0 | AI5: 1 | AL5: 1 | BA5: =IF(ISNUMBER(BQ5),BQ5,IF(AND(ISNUMBER($BJ5),ISNUMBER($BK5)),BI5,"")) | BB5: =IF(ISNUMBER(BR5),BR5,IF(AND(ISNUMBER($BJ5),ISNUMBER($BK5)),BJ5,"")) | BC5: =IF(ISNUMBER(BS5),BS5,IF(AND(ISNUMBER($BJ5),ISNUMBER($BK5)),BK5,"")) | BD5: =IF(ISNUMBER(BT5),BT5,IF(AND(ISNUMBER($BO5),ISNUMBER($BP5)),BN5,"")) | BE5: =IF(ISNUMBER(BU5),BU5,IF(AND(ISNUMBER($BO5),ISNUMBER($BP5)),BO5,"")) | BF5: =IF(ISNUMBER(BV5),BV5,IF(AND(ISNUMBER($BO5),ISNUMBER($BP5)),BP5,"")) | BJ5: =IF(AND(ISNUMBER(BG5),ISNUMBER(BH5),ISNUMBER(BI5)),EXP(LOG(BI5)-1.96*SQRT((1/BG5)+(1/BH5))),"") | BK5: =IF(AND(ISNUMBER(BG5),ISNUMBER(BH5),ISNUMBER(BI5)),EXP(LOG(BI5)+1.96*SQRT((1/BG5)+(1/BH5))),"") | BO5: =IF(AND(ISNUMBER(BL5),ISNUMBER(BM5),ISNUMBER(BN5)),EXP(LOG(BN5)-1.96*SQRT((1/BL5)+(1/BM5))),"") | BP5: =IF(AND(ISNUMBER(BL5),ISNUMBER(BM5),ISNUMBER(BN5)),EXP(LOG(BN5)+1.96*SQRT((1/BL5)+(1/BM5))),"") | CC5: =107-36 -> 71 | CD5: 2 | CG5: 2 | CV5: Engraftment was defined as the first of three consecutive days with a leukocyte count above 1000/μl in peripheral blood samples. | CX5: marked broad engraftment as neutrophil
A6: Dzieciątkowski T | B6: 2010 | C6: https://pubmed.ncbi.nlm.nih.gov/20872080 | D6: =A6&" "&B6 -> Dzieciątkowski T 2010 | E6: =IF(OR(AND(ISNUMBER(AG6),ISNUMBER(AL6),ISNUMBER(CC6),ISNUMBER(CG6)),AND(ISNUMBER(AG6),ISNUMBER(AM6),ISNUMBER(CC6),ISNUMBER(CH6))),"Yes","No") -> Yes | F6: 7 | G6: =MEDIAN(18,27,22,20,32,27,44) -> 27 | H6: =MIN(18,27,22,20,32,27,44) -> 18 | I6: =MAX(18,27,22,20,32,27,44) -> 44 | L6: 7 | M6: 7 | AA6: 7 | AD6: 7 | AG6: 1 | AH6: 0 | AI6: 0 | AL6: 0 | BA6: =IF(ISNUMBER(BQ6),BQ6,IF(AND(ISNUMBER($BJ6),ISNUMBER($BK6)),BI6,"")) | BB6: =IF(ISNUMBER(BR6),BR6,IF(AND(ISNUMBER($BJ6),ISNUMBER($BK6)),BJ6,"")) | BC6: =IF(ISNUMBER(BS6),BS6,IF(AND(ISNUMBER($BJ6),ISNUMBER($BK6)),BK6,"")) | BD6: =IF(ISNUMBER(BT6),BT6,IF(AND(ISNUMBER($BO6),ISNUMBER($BP6)),BN6,"")) | BE6: =IF(ISNUMBER(BU6),BU6,IF(AND(ISNUMBER($BO6),ISNUMBER($BP6)),BO6,"")) | BF6: =IF(ISNUMBER(BV6),BV6,IF(AND(ISNUMBER($BO6),ISNUMBER($BP6)),BP6,"")) | BJ6: =IF(AND(ISNUMBER(BG6),ISNUMBER(BH6),ISNUMBER(BI6)),EXP(LOG(BI6)-1.96*SQRT((1/BG6)+(1/BH6))),"") | BK6: =IF(AND(ISNUMBER(BG6),ISNUMBER(BH6),ISNUMBER(BI6)),EXP(LOG(BI6)+1.96*SQRT((1/BG6)+(1/BH6))),"") | BO6: =IF(AND(ISNUMBER(BL6),ISNUMBER(BM6),ISNUMBER(BN6)),EXP(LOG(BN6)-1.96*SQRT((1/BL6)+(1/BM6))),"") | BP6: =IF(AND(ISNUMBER(BL6),ISNUMBER(BM6),ISNUMBER(BN6)),EXP(LOG(BN6)+1.96*SQRT((1/BL6)+(1/BM6))),"") | CC6: 6 | CD6: 1 | CG6: 1 | CV6: Not discussed. "acceptable engraftment" only mention | CX6: marked broad engraftment as neutrophil
A7: El Jurdi N | B7: 2021 | C7: https://pubmed.ncbi.nlm.nih.gov/33053448 | D7: =A7&" "&B7 -> El Jurdi N 2021 | E7: =IF(OR(AND(ISNUMBER(AG7),ISNUMBER(AL7),ISNUMBER(CC7),ISNUMBER(CG7)),AND(ISNUMBER(AG7),ISNUMBER(AM7),ISNUMBER(CC7),ISNUMBER(CH7))),"Yes","No") -> Yes | F7: 86 | G7: Unclear | H7: Unclear | I7: Unclear | J7: =16+9+31+30 -> 86 | M7: 86 | X7: =25+61 -> 86 | AD7: =4+11+10+1+5+55 -> 86 | AG7: =ROUND(F7*0.63,0) -> 54 | AH7: 0 | AL7: 11 | AM7: 13 | BA7: =IF(ISNUMBER(BQ7),BQ7,IF(AND(ISNUMBER($BJ7),ISNUMBER($BK7)),BI7,"")) | BB7: =IF(ISNUMBER(BR7),BR7,IF(AND(ISNUMBER($BJ7),ISNUMBER($BK7)),BJ7,"")) | BC7: =IF(ISNUMBER(BS7),BS7,IF(AND(ISNUMBER($BJ7),ISNUMBER($BK7)),BK7,"")) | BD7: =IF(ISNUMBER(BT7),BT7,IF(AND(ISNUMBER($BO7),ISNUMBER($BP7)),BN7,"")) | BE7: =IF(ISNUMBER(BU7),BU7,IF(AND(ISNUMBER($BO7),ISNUMBER($BP7)),BO7,"")) | BF7: =IF(ISNUMBER(BV7),BV7,IF(AND(ISNUMBER($BO7),ISNUMBER($BP7)),BP7,"")) | BJ7: =IF(AND(ISNUMBER(BG7),ISNUMBER(BH7),ISNUMBER(BI7)),EXP(LOG(BI7)-1.96*SQRT((1/BG7)+(1/BH7))),"") | BK7: =IF(AND(ISNUMBER(BG7),ISNUMBER(BH7),ISNUMBER(BI7)),EXP(LOG(BI7)+1.96*SQRT((1/BG7)+(1/BH7))),"") | BO7: =IF(AND(ISNUMBER(BL7),ISNUMBER(BM7),ISNUMBER(BN7)),EXP(LOG(BN7)-1.96*SQRT((1/BL7)+(1/BM7))),"") | BP7: =IF(AND(ISNUMBER(BL7),ISNUMBER(BM7),ISNUMBER(BN7)),EXP(LOG(BN7)+1.96*SQRT((1/BL7)+(1/BM7))),"") | CC7: =F7-AG7 -> 32 | CG7: 5 | CH7: =17-13 -> 4 | CV7: "Neutrophil engraftment was defined as absolute neutrophil count >=5 x 10^8/L on the first of 3 consecutive measurements." | CW7: "Platelet engraftment was defined as the first of 7 consecutive days with a nontransfused count of >=20 x 10^9/L."
A8: Gomes de Oliveira PG | B8: 2016 | C8: https://pubmed.ncbi.nlm.nih.gov/26555946 | D8: =A8&" "&B8 -> Gomes de Oliveira PG 2016 | E8: =IF(OR(AND(ISNUMBER(AG8),ISNUMBER(AL8),ISNUMBER(CC8),ISNUMBER(CG8)),AND(ISNUMBER(AG8),ISNUMBER(AM8),ISNUMBER(CC8),ISNUMBER(CH8))),"Yes","No") -> Yes | F8: 98 | G8: 16 | H8: 2 | I8: 73 | J8: 27 | L8: =F8-J8 -> 71 | M8: 98 | Q8: 17 | R8: 36 | T8: 24 | U8: 9 | AA8: 47 | AD8: 24 | AE8: 74 | AF8: 98 | AG8: 18 | AH8: 0 | AL8: =ROUND(AG8*(1-0.82),0) -> 3 | AM8: =ROUND(AG8*(1-0.71),0) -> 5 | AP8: 19 | AU8: 38 | BA8: =IF(ISNUMBER(BQ8),BQ8,IF(AND(ISNUMBER($BJ8),ISNUMBER($BK8)),BI8,"")) -> 0.84210526 | BB8: =IF(ISNUMBER(BR8),BR8,IF(AND(ISNUMBER($BJ8),ISNUMBER($BK8)),BJ8,"")) -> 0.53376261 | BC8: =IF(ISNUMBER(BS8),BS8,IF(AND(ISNUMBER($BJ8),ISNUMBER($BK8)),BK8,"")) -> 1.6137116 | BD8: =IF(ISNUMBER(BT8),BT8,IF(AND(ISNUMBER($BO8),ISNUMBER($BP8)),BN8,"")) -> 0.47368421 | BE8: =IF(ISNUMBER(BU8),BU8,IF(AND(ISNUMBER($BO8),ISNUMBER($BP8)),BO8,"")) -> 0.4007015 | BF8: =IF(ISNUMBER(BV8),BV8,IF(AND(ISNUMBER($BO8),ISNUMBER($BP8)),BP8,"")) -> 1.3041041 | BG8: =ROUND(AG8*0.82,0) -> 15 | BH8: =ROUND(CC8*0.96,0) -> 77 | BI8: =CK8/AP8 -> 0.84210526 | BJ8: =IF(AND(ISNUMBER(BG8),ISNUMBER(BH8),ISNUMBER(BI8)),EXP(LOG(BI8)-1.96*SQRT((1/BG8)+(1/BH8))),"") -> 0.53376261 | BK8: =IF(AND(ISNUMBER(BG8),ISNUMBER(BH8),ISNUMBER(BI8)),EXP(LOG(BI8)+1.96*SQRT((1/BG8)+(1/BH8))),"") -> 1.6137116 | BL8: =ROUND(AG8*0.71,0) -> 13 | BM8: =ROUND(CC8*0.91,0) -> 73 | BN8: =CP8/AU8 -> 0.47368421 | BO8: =IF(AND(ISNUMBER(BL8),ISNUMBER(BM8),ISNUMBER(BN8)),EXP(LOG(BN8)-1.96*SQRT((1/BL8)+(1/BM8))),"") -> 0.4007015 | BP8: =IF(AND(ISNUMBER(BL8),ISNUMBER(BM8),ISNUMBER(BN8)),EXP(LOG(BN8)+1.96*SQRT((1/BL8)+(1/BM8))),"") -> 1.3041041 | CC8: =F8-AG8 -> 80 | CG8: =ROUND(CC8*(1-0.96),0) -> 3 | CH8: =ROUND(CC8*(1-0.91),0) -> 7 | CK8: 16 | CP8: 18 | CV8: "... first of 3 consecutive days with a neutrophil count of at least 0.5 x 10^9/L" | CW8: "... first of 7 consecutive days of an unsupported platelet count of at least 20 x 10^9/L"
A9: Han TT | B9: 2021 | C9: https://pubmed.ncbi.nlm.nih.gov/33326670 | D9: =A9&" "&B9 -> Han TT 2021 | E9: =IF(OR(AND(ISNUMBER(AG9),ISNUMBER(AL9),ISNUMBER(CC9),ISNUMBER(CG9)),AND(ISNUMBER(AG9),ISNUMBER(AM9),ISNUMBER(CC9),ISNUMBER(CH9))),"Yes","No") -> Yes | F9: 102 | G9: 25 | H9: 2 | I9: 58 | M9: =F9 -> 102 | S9: =F9 -> 102 | AE9: =F9 -> 102 | AF9: 102 | AG9: 25 | AH9: Timing of IR failure relative to HHV-6 detection is unclear, but systemic testing was performed | AM9: 4 | AN9: 9 | AP9: 13 | AR9: 21 | AS9: 9 | AU9: 16 | AW9: 29 | BA9: =IF(ISNUMBER(BQ9),BQ9,IF(AND(ISNUMBER($BJ9),ISNUMBER($BK9)),BI9,"")) | BB9: =IF(ISNUMBER(BR9),BR9,IF(AND(ISNUMBER($BJ9),ISNUMBER($BK9)),BJ9,"")) | BC9: =IF(ISNUMBER(BS9),BS9,IF(AND(ISNUMBER($BJ9),ISNUMBER($BK9)),BK9,"")) | BD9: =IF(ISNUMBER(BT9),BT9,IF(AND(ISNUMBER($BO9),ISNUMBER($BP9)),BN9,"")) -> 1 | BE9: =IF(ISNUMBER(BU9),BU9,IF(AND(ISNUMBER($BO9),ISNUMBER($BP9)),BO9,"")) -> 0.61454819 | BF9: =IF(ISNUMBER(BV9),BV9,IF(AND(ISNUMBER($BO9),ISNUMBER($BP9)),BP9,"")) -> 1.6272117 | BG9: Unclear | BH9: Unclear | BI9: =CK9/AP9 -> 1 | BJ9: =IF(AND(ISNUMBER(BG9),ISNUMBER(BH9),ISNUMBER(BI9)),EXP(LOG(BI9)-1.96*SQRT((1/BG9)+(1/BH9))),"") | BK9: =IF(AND(ISNUMBER(BG9),ISNUMBER(BH9),ISNUMBER(BI9)),EXP(LOG(BI9)+1.96*SQRT((1/BG9)+(1/BH9))),"") | BL9: =AG9-4 -> 21 | BM9: =CC9-6 -> 71 | BN9: =CP9/AU9 -> 1 | BO9: =IF(AND(ISNUMBER(BL9),ISNUMBER(BM9),ISNUMBER(BN9)),EXP(LOG(BN9)-1.96*SQRT((1/BL9)+(1/BM9))),"") -> 0.61454819 | BP9: =IF(AND(ISNUMBER(BL9),ISNUMBER(BM9),ISNUMBER(BN9)),EXP(LOG(BN9)+1.96*SQRT((1/BL9)+(1/BM9))),"") -> 1.6272117 | CC9: 77 | CH9: 6 | CI9: 11 | CK9: 13 | CM9: 20 | CN9: 10 | CP9: 16 | CR9: 84 | CV9: "The date of white blood cell (WBC) and platelet engraftment were defined as accepted standards" | CW9: "The date of white blood cell (WBC) and platelet engraftment were defined as accepted standards."
A10: Hentrich M | B10: 2005 | C10: https://pubmed.ncbi.nlm.nih.gov/15606551 | D10: =A10&" "&B10 -> Hentrich M 2005 | E10: =IF(OR(AND(ISNUMBER(AG10),ISNUMBER(AL10),ISNUMBER(CC10),ISNUMBER(CG10)),AND(ISNUMBER(AG10),ISNUMBER(AM10),ISNUMBER(CC10),ISNUMBER(CH10))),"Yes","No") -> Yes | F10: =129+99 -> 228 | G10: Unclear | H10: Unclear | I10: Unclear | K10: =F10 -> 228 | M10: =F10 -> 228 | AA10: =F10 -> 228 | AB10: =100+63 -> 163 | AC10: =21+13 -> 34 | AF10: =129+99 -> 228 | AG10: 129 | AH10: 0 | AL10: 8 | AP10: 19 | BA10: =IF(ISNUMBER(BQ10),BQ10,IF(AND(ISNUMBER($BJ10),ISNUMBER($BK10)),BI10,"")) | BB10: =IF(ISNUMBER(BR10),BR10,IF(AND(ISNUMBER($BJ10),ISNUMBER($BK10)),BJ10,"")) | BC10: =IF(ISNUMBER(BS10),BS10,IF(AND(ISNUMBER($BJ10),ISNUMBER($BK10)),BK10,"")) | BD10: =IF(ISNUMBER(BT10),BT10,IF(AND(ISNUMBER($BO10),ISNUMBER($BP10)),BN10,"")) | BE10: =IF(ISNUMBER(BU10),BU10,IF(AND(ISNUMBER($BO10),ISNUMBER($BP10)),BO10,"")) | BF10: =IF(ISNUMBER(BV10),BV10,IF(AND(ISNUMBER($BO10),ISNUMBER($BP10)),BP10,"")) | BG10: Unclear | BH10: Unclear | BI10: =CK10/AP10 -> 0.94736842 | BJ10: =IF(AND(ISNUMBER(BG10),ISNUMBER(BH10),ISNUMBER(BI10)),EXP(LOG(BI10)-1.96*SQRT((1/BG10)+(1/BH10))),"") | BK10: =IF(AND(ISNUMBER(BG10),ISNUMBER(BH10),ISNUMBER(BI10)),EXP(LOG(BI10)+1.96*SQRT((1/BG10)+(1/BH10))),"") | BO10: =IF(AND(ISNUMBER(BL10),ISNUMBER(BM10),ISNUMBER(BN10)),EXP(LOG(BN10)-1.96*SQRT((1/BL10)+(1/BM10))),"") | BP10: =IF(AND(ISNUMBER(BL10),ISNUMBER(BM10),ISNUMBER(BN10)),EXP(LOG(BN10)+1.96*SQRT((1/BL10)+(1/BM10))),"") | CC10: 99 | CG10: 11 | CK10: 18 | CV10: "Delayed engraftment was defined as an ANC of 0.5 x10^9/L first occurring on or after day +25 after HSCT." | CX10: Median is inferred here. Engraftment is not explicilty given as the median, but in context I think this is a reasonable assumption (no averages are given in the paper, only medians)
A11: Le Bourgeois A | B11: 2014 | C11: https://pubmed.ncbi.nlm.nih.gov/25072620 | D11: =A11&" "&B11 -> Le Bourgeois A 2014 | E11: =IF(OR(AND(ISNUMBER(AG11),ISNUMBER(AL11),ISNUMBER(CC11),ISNUMBER(CG11)),AND(ISNUMBER(AG11),ISNUMBER(AM11),ISNUMBER(CC11),ISNUMBER(CH11))),"Yes","No") -> Yes | F11: 73 | G11: Unclear | H11: Unclear | I11: Unclear | J11: 69 | K11: 8 | P11: =F11 -> 73 | R11: =F11 -> 73 | AD11: =F11 -> 73 | AG11: 27 | AH11: 0 | AL11: 9 | BA11: =IF(ISNUMBER(BQ11),BQ11,IF(AND(ISNUMBER($BJ11),ISNUMBER($BK11)),BI11,"")) | BB11: =IF(ISNUMBER(BR11),BR11,IF(AND(ISNUMBER($BJ11),ISNUMBER($BK11)),BJ11,"")) | BC11: =IF(ISNUMBER(BS11),BS11,IF(AND(ISNUMBER($BJ11),ISNUMBER($BK11)),BK11,"")) | BD11: =IF(ISNUMBER(BT11),BT11,IF(AND(ISNUMBER($BO11),ISNUMBER($BP11)),BN11,"")) | BE11: =IF(ISNUMBER(BU11),BU11,IF(AND(ISNUMBER($BO11),ISNUMBER($BP11)),BO11,"")) | BF11: =IF(ISNUMBER(BV11),BV11,IF(AND(ISNUMBER($BO11),ISNUMBER($BP11)),BP11,"")) | BJ11: =IF(AND(ISNUMBER(BG11),ISNUMBER(BH11),ISNUMBER(BI11)),EXP(LOG(BI11)-1.96*SQRT((1/BG11)+(1/BH11))),"") | BK11: =IF(AND(ISNUMBER(BG11),ISNUMBER(BH11),ISNUMBER(BI11)),EXP(LOG(BI11)+1.96*SQRT((1/BG11)+(1/BH11))),"") | BO11: =IF(AND(ISNUMBER(BL11),ISNUMBER(BM11),ISNUMBER(BN11)),EXP(LOG(BN11)-1.96*SQRT((1/BL11)+(1/BM11))),"") | BP11: =IF(AND(ISNUMBER(BL11),ISNUMBER(BM11),ISNUMBER(BN11)),EXP(LOG(BN11)+1.96*SQRT((1/BL11)+(1/BM11))),"") | CC11: 44 | CG11: 6 | CV11: "Neutrophil recovery was defined as the first of three consecutive days during which the absolute neutrophil count in the blood was >0.5 x 10^9/L. " | CW11: "Platelet recovery was defined as the first of three consecutive days when the platelet count was >20 x 10^9/L without transfusion support."
A12: Mata JR | B12: 2024 | C12: https://pubmed.ncbi.nlm.nih.gov/38521411 | D12: =A12&" "&B12 -> Mata JR 2024 | E12: =IF(OR(AND(ISNUMBER(AG12),ISNUMBER(AL12),ISNUMBER(CC12),ISNUMBER(CG12)),AND(ISNUMBER(AG12),ISNUMBER(AM12),ISNUMBER(CC12),ISNUMBER(CH12))),"Yes","No") -> Yes | F12: 958 | G12: Unclear | H12: 18 | I12: Unclear | J12: Unclear | K12: Unclear | L12: Unclear | P12: =F12 -> 958 | W12: =F12 -> 958 | AB12: 455 | AC12: 503 | AF12: 958 | AG12: =193+17 -> 210 | AI12: 17 | AL12: 17 | BA12: =IF(ISNUMBER(BQ12),BQ12,IF(AND(ISNUMBER($BJ12),ISNUMBER($BK12)),BI12,"")) | BB12: =IF(ISNUMBER(BR12),BR12,IF(AND(ISNUMBER($BJ12),ISNUMBER($BK12)),BJ12,"")) | BC12: =IF(ISNUMBER(BS12),BS12,IF(AND(ISNUMBER($BJ12),ISNUMBER($BK12)),BK12,"")) | BD12: =IF(ISNUMBER(BT12),BT12,IF(AND(ISNUMBER($BO12),ISNUMBER($BP12)),BN12,"")) | BE12: =IF(ISNUMBER(BU12),BU12,IF(AND(ISNUMBER($BO12),ISNUMBER($BP12)),BO12,"")) | BF12: =IF(ISNUMBER(BV12),BV12,IF(AND(ISNUMBER($BO12),ISNUMBER($BP12)),BP12,"")) | CC12: =921-193 -> 728 | CD12: =37-17 -> 20 | CG12: =37-17 -> 20 | CV12: "Normal engraftment was defined as the achievement of an ANC of 500 cells/m3 or greater by day 30" | CX12: Added 7/8/24
A13: Miranda-Silva W | B13: 2023 | C13: https://pubmed.ncbi.nlm.nih.gov/34523191 | D13: =A13&" "&B13 -> Miranda-Silva W 2023 | E13: =IF(OR(AND(ISNUMBER(AG13),ISNUMBER(AL13),ISNUMBER(CC13),ISNUMBER(CG13)),AND(ISNUMBER(AG13),ISNUMBER(AM13),ISNUMBER(CC13),ISNUMBER(CH13))),"Yes","No") -> Yes | F13: 31 | G13: 50 | H13: 19 | I13: 72 | J13: 19 | K13: 12 | M13: =F13 -> 31 | R13: 11 | T13: 10 | V13: 10 | AB13: 10 | AC13: 21 | AF13: 31 | AG13: 2 | AH13: 0 | AL13: 1 | BA13: =IF(ISNUMBER(BQ13),BQ13,IF(AND(ISNUMBER($BJ13),ISNUMBER($BK13)),BI13,"")) | BB13: =IF(ISNUMBER(BR13),BR13,IF(AND(ISNUMBER($BJ13),ISNUMBER($BK13)),BJ13,"")) | BC13: =IF(ISNUMBER(BS13),BS13,IF(AND(ISNUMBER($BJ13),ISNUMBER($BK13)),BK13,"")) | BD13: =IF(ISNUMBER(BT13),BT13,IF(AND(ISNUMBER($BO13),ISNUMBER($BP13)),BN13,"")) | BE13: =IF(ISNUMBER(BU13),BU13,IF(AND(ISNUMBER($BO13),ISNUMBER($BP13)),BO13,"")) | BF13: =IF(ISNUMBER(BV13),BV13,IF(AND(ISNUMBER($BO13),ISNUMBER($BP13)),BP13,"")) | BJ13: =IF(AND(ISNUMBER(BG13),ISNUMBER(BH13),ISNUMBER(BI13)),EXP(LOG(BI13)-1.96*SQRT((1/BG13)+(1/BH13))),"") | BK13: =IF(AND(ISNUMBER(BG13),ISNUMBER(BH13),ISNUMBER(BI13)),EXP(LOG(BI13)+1.96*SQRT((1/BG13)+(1/BH13))),"") | BO13: =IF(AND(ISNUMBER(BL13),ISNUMBER(BM13),ISNUMBER(BN13)),EXP(LOG(BN13)-1.96*SQRT((1/BL13)+(1/BM13))),"") | BP13: =IF(AND(ISNUMBER(BL13),ISNUMBER(BM13),ISNUMBER(BN13)),EXP(LOG(BN13)+1.96*SQRT((1/BL13)+(1/BM13))),"") | CC13: =AF13-AG13 -> 29 | CG13: =ROUND(CC13*(1-0.97),0) -> 1 | CV13: "Neutrophil engraftment was considered as the first day of 3 consecutive days with a neutrophil count of at least 0.5 × 10^9/L" | CW13: "... platelet engraftment was considered as the first day of 7 consecutive days of an unsupported platelet count of at least 20.0 × 10^9/L"
A14: Ogata M | B14: 2006 | C14: https://pubmed.ncbi.nlm.nih.gov/16323134 | D14: =A14&" "&B14 -> Ogata M 2006 | E14: =IF(OR(AND(ISNUMBER(AG14),ISNUMBER(AL14),ISNUMBER(CC14),ISNUMBER(CG14)),AND(ISNUMBER(AG14),ISNUMBER(AM14),ISNUMBER(CC14),ISNUMBER(CH14))),"Yes","No") -> Yes | F14: =24+26 -> 50 | G14: 40.5 | H14: 12 | I14: 59 | J14: 4 | K14: 46 | M14: 50 | Q14: 1 | T14: 46 | Y14: 3 | AB14: =11+31 -> 42 | AC14: 8 | AF14: =24+26 -> 50 | AG14: 24 | AH14: Timing of IR failure relative to HHV-6 detection is unclear, but systemic testing was performed | AM14: 11 | AN14: 11 | AP14: 14 | AR14: 27 | BA14: =IF(ISNUMBER(BQ14),BQ14,IF(AND(ISNUMBER($BJ14),ISNUMBER($BK14)),BI14,"")) -> 1.0357143 | BB14: =IF(ISNUMBER(BR14),BR14,IF(AND(ISNUMBER($BJ14),ISNUMBER($BK14)),BJ14,"")) -> 0.58299552 | BC14: =IF(ISNUMBER(BS14),BS14,IF(AND(ISNUMBER($BJ14),ISNUMBER($BK14)),BK14,"")) -> 1.7683656 | BD14: =IF(ISNUMBER(BT14),BT14,IF(AND(ISNUMBER($BO14),ISNUMBER($BP14)),BN14,"")) | BE14: =IF(ISNUMBER(BU14),BU14,IF(AND(ISNUMBER($BO14),ISNUMBER($BP14)),BO14,"")) | BF14: =IF(ISNUMBER(BV14),BV14,IF(AND(ISNUMBER($BO14),ISNUMBER($BP14)),BP14,"")) | BG14: =AG14 -> 24 | BH14: =CC14 -> 26 | BI14: =CK14/AP14 -> 1.0357143 | BJ14: =IF(AND(ISNUMBER(BG14),ISNUMBER(BH14),ISNUMBER(BI14)),EXP(LOG(BI14)-1.96*SQRT((1/BG14)+(1/BH14))),"") -> 0.58299552 | BK14: =IF(AND(ISNUMBER(BG14),ISNUMBER(BH14),ISNUMBER(BI14)),EXP(LOG(BI14)+1.96*SQRT((1/BG14)+(1/BH14))),"") -> 1.7683656 | BO14: =IF(AND(ISNUMBER(BL14),ISNUMBER(BM14),ISNUMBER(BN14)),EXP(LOG(BN14)-1.96*SQRT((1/BL14)+(1/BM14))),"") | BP14: =IF(AND(ISNUMBER(BL14),ISNUMBER(BM14),ISNUMBER(BN14)),EXP(LOG(BN14)+1.96*SQRT((1/BL14)+(1/BM14))),"") | CC14: 26 | CH14: 8 | CI14: 11 | CK14: 14.5 | CM14: 25 | CV14: "Neutrophil engraftment was defined as an absolute neutrophil count of > 0.5 x 10^9 neutrophils/L" | CW14: "... platelet engraftment was considered present with a self-sustained platelet count of 20_x0001_x 10^9 platelets/L."
A15: Ohyashiki JH | B15: 2000 | C15: https://pubmed.ncbi.nlm.nih.gov/10998432 | D15: =A15&" "&B15 -> Ohyashiki JH 2000 | E15: =IF(OR(AND(ISNUMBER(AG15),ISNUMBER(AL15),ISNUMBER(CC15),ISNUMBER(CG15)),AND(ISNUMBER(AG15),ISNUMBER(AM15),ISNUMBER(CC15),ISNUMBER(CH15))),"Yes","No") -> Yes | F15: 5 | G15: =MEDIAN(18,45,26,22,28) -> 26 | H15: =MIN(18,45,26,22,28) -> 18 | I15: =MAX(18,45,26,22,28) -> 45 | L15: =F15 -> 5 | P15: =F15 -> 5 | AA15: =F15 -> 5 | AB15: 5 | AF15: 5 | AG15: 3 | AH15: 0 | AM15: 1 | BA15: =IF(ISNUMBER(BQ15),BQ15,IF(AND(ISNUMBER($BJ15),ISNUMBER($BK15)),BI15,"")) | BB15: =IF(ISNUMBER(BR15),BR15,IF(AND(ISNUMBER($BJ15),ISNUMBER($BK15)),BJ15,"")) | BC15: =IF(ISNUMBER(BS15),BS15,IF(AND(ISNUMBER($BJ15),ISNUMBER($BK15)),BK15,"")) | BD15: =IF(ISNUMBER(BT15),BT15,IF(AND(ISNUMBER($BO15),ISNUMBER($BP15)),BN15,"")) | BE15: =IF(ISNUMBER(BU15),BU15,IF(AND(ISNUMBER($BO15),ISNUMBER($BP15)),BO15,"")) | BF15: =IF(ISNUMBER(BV15),BV15,IF(AND(ISNUMBER($BO15),ISNUMBER($BP15)),BP15,"")) | BJ15: =IF(AND(ISNUMBER(BG15),ISNUMBER(BH15),ISNUMBER(BI15)),EXP(LOG(BI15)-1.96*SQRT((1/BG15)+(1/BH15))),"") | BK15: =IF(AND(ISNUMBER(BG15),ISNUMBER(BH15),ISNUMBER(BI15)),EXP(LOG(BI15)+1.96*SQRT((1/BG15)+(1/BH15))),"") | BO15: =IF(AND(ISNUMBER(BL15),ISNUMBER(BM15),ISNUMBER(BN15)),EXP(LOG(BN15)-1.96*SQRT((1/BL15)+(1/BM15))),"") | BP15: =IF(AND(ISNUMBER(BL15),ISNUMBER(BM15),ISNUMBER(BN15)),EXP(LOG(BN15)+1.96*SQRT((1/BL15)+(1/BM15))),"") | CC15: 2 | CH15: 0 | CV15: Not defined
A16: Paviglianiti A | B16: 2024 | C16: https://pubmed.ncbi.nlm.nih.gov/38817703 | D16: =A16&" "&B16 -> Paviglianiti A 2024 | E16: =IF(OR(AND(ISNUMBER(AG16),ISNUMBER(AL16),ISNUMBER(CC16),ISNUMBER(CG16)),AND(ISNUMBER(AG16),ISNUMBER(AM16),ISNUMBER(CC16),ISNUMBER(CH16))),"Yes","No") -> Yes | F16: =31+25+19+25 -> 100 | G16: Unclear | H16: Unclear | I16: Unclear | J16: =16+14 -> 30 | K16: =17+10 -> 27 | L16: =23+20 -> 43 | M16: =F16 -> 100 | V16: =F16 -> 100 | AB16: =16+8 -> 24 | AC16: =40+36 -> 76 | AF16: =31+25+19+25 -> 100 | AG16: =31+25 -> 56 | AL16: =ROUND(AG16*(1-0.91),0) -> 5 | AM16: =ROUND(AG16*(1-0.73),0) -> 15 | BA16: =IF(ISNUMBER(BQ16),BQ16,IF(AND(ISNUMBER($BJ16),ISNUMBER($BK16)),BI16,"")) -> 1.08 | BB16: =IF(ISNUMBER(BR16),BR16,IF(AND(ISNUMBER($BJ16),ISNUMBER($BK16)),BJ16,"")) -> 0.6 | BC16: =IF(ISNUMBER(BS16),BS16,IF(AND(ISNUMBER($BJ16),ISNUMBER($BK16)),BK16,"")) -> 1.94 | BD16: =IF(ISNUMBER(BT16),BT16,IF(AND(ISNUMBER($BO16),ISNUMBER($BP16)),BN16,"")) -> 1.81 | BE16: =IF(ISNUMBER(BU16),BU16,IF(AND(ISNUMBER($BO16),ISNUMBER($BP16)),BO16,"")) -> 1.07 | BF16: =IF(ISNUMBER(BV16),BV16,IF(AND(ISNUMBER($BO16),ISNUMBER($BP16)),BP16,"")) -> 3.05 | BQ16: 1.08 | BR16: 0.6 | BS16: 1.94 | BT16: 1.81 | BU16: 1.07 | BV16: 3.05 | CC16: =19+25 -> 44 | CG16: =ROUND(CC16*(1-0.96),0) -> 2 | CH16: =ROUND(CC16*(1-0.82),0) -> 8 | CV16: "Neutrophil engraftment was defined as an absolute neutrophil count > 0.5 x 10^9/L for three consecutive days (the first of which was considered the engraftment day)" | CW16: "... platelet engraftment as a platelet count > 50 x 10^9/L for seven consecutive days (the first of which was considered engraftment day)" | CX16: Added 7/9/24
A17: Raouf MME | B17: 2023 | C17: https://pubmed.ncbi.nlm.nih.gov/36739398 | D17: =A17&" "&B17 -> Raouf MME 2023 | E17: =IF(OR(AND(ISNUMBER(AG17),ISNUMBER(AL17),ISNUMBER(CC17),ISNUMBER(CG17)),AND(ISNUMBER(AG17),ISNUMBER(AM17),ISNUMBER(CC17),ISNUMBER(CH17))),"Yes","No") -> Yes | F17: =25+15 -> 40 | G17: Unclear for whole cohort | H17: 19 | I17: 72 | J17: =1+11+17 -> 29 | K17: =11 -> 11 | M17: =12+28 -> 40 | T17: =12 -> 12 | AC17: =12+28 -> 40 | AF17: =25+15 -> 40 | AG17: 15 | AH17: Timing of IR failure relative to HHV-6 detection is unclear, but systemic testing was performed | AI17: 6 | AL17: 6 | AN17: 9 | AO17: 10 | AP17: 12 | AQ17: 15.5 | AR17: 28 | AS17: 8 | AT17: 10 | AU17: 11 | AV17: 12 | AW17: 13 | BA17: =IF(ISNUMBER(BQ17),BQ17,IF(AND(ISNUMBER($BJ17),ISNUMBER($BK17)),BI17,"")) | BB17: =IF(ISNUMBER(BR17),BR17,IF(AND(ISNUMBER($BJ17),ISNUMBER($BK17)),BJ17,"")) | BC17: =IF(ISNUMBER(BS17),BS17,IF(AND(ISNUMBER($BJ17),ISNUMBER($BK17)),BK17,"")) | BD17: =IF(ISNUMBER(BT17),BT17,IF(AND(ISNUMBER($BO17),ISNUMBER($BP17)),BN17,"")) | BE17: =IF(ISNUMBER(BU17),BU17,IF(AND(ISNUMBER($BO17),ISNUMBER($BP17)),BO17,"")) | BF17: =IF(ISNUMBER(BV17),BV17,IF(AND(ISNUMBER($BO17),ISNUMBER($BP17)),BP17,"")) | BG17: Unclear | BH17: Unclear | BI17: =CK17/AP17 -> 1 | BJ17: =IF(AND(ISNUMBER(BG17),ISNUMBER(BH17),ISNUMBER(BI17)),EXP(LOG(BI17)-1.96*SQRT((1/BG17)+(1/BH17))),"") | BK17: =IF(AND(ISNUMBER(BG17),ISNUMBER(BH17),ISNUMBER(BI17)),EXP(LOG(BI17)+1.96*SQRT((1/BG17)+(1/BH17))),"") | BL17: Unclear | BM17: Unclear | BN17: =CP17/AU17 -> 1.0909091 | BO17: =IF(AND(ISNUMBER(BL17),ISNUMBER(BM17),ISNUMBER(BN17)),EXP(LOG(BN17)-1.96*SQRT((1/BL17)+(1/BM17))),"") | BP17: =IF(AND(ISNUMBER(BL17),ISNUMBER(BM17),ISNUMBER(BN17)),EXP(LOG(BN17)+1.96*SQRT((1/BL17)+(1/BM17))),"") | BQ17: See note | BR17: See note | BS17: See note | CC17: 25 | CD17: 4 | CG17: 4 | CI17: 7 | CJ17: 11 | CK17: 12 | CL17: 13 | CM17: 24 | CN17: 5 | CO17: 11 | CP17: 12 | CQ17: 14 | CR17: 22 | CV17: Not defined | CX17: marked broad engraftment as neutrophil. Combines delayed engraftment and bone marrow suppression into one category. Odds given for delayed engraftment, which invert the interpretation
A18: Rapaport D | B18: 2002 | C18: https://pubmed.ncbi.nlm.nih.gov/12123421 | D18: =A18&" "&B18 -> Rapaport D 2002 | E18: =IF(OR(AND(ISNUMBER(AG18),ISNUMBER(AL18),ISNUMBER(CC18),ISNUMBER(CG18)),AND(ISNUMBER(AG18),ISNUMBER(AM18),ISNUMBER(CC18),ISNUMBER(CH18))),"Yes","No") -> Yes | F18: 14 | G18: =MEDIAN(21,17,36,40,12,35,40,21,11,48,36,18,29,23) -> 26 | H18: =MIN(21,17,36,40,12,35,40,21,11,48,36,18,29,23) -> 11 | I18: =MAX(21,17,36,40,12,35,40,21,11,48,36,18,29,23) -> 48 | L18: =F18 -> 14 | M18: =F18 -> 14 | T18: 5 | Z18: 8 | AG18: 3 | AH18: 0 | AI18: 1 | AL18: 1 | BA18: =IF(ISNUMBER(BQ18),BQ18,IF(AND(ISNUMBER($BJ18),ISNUMBER($BK18)),BI18,"")) | BB18: =IF(ISNUMBER(BR18),BR18,IF(AND(ISNUMBER($BJ18),ISNUMBER($BK18)),BJ18,"")) | BC18: =IF(ISNUMBER(BS18),BS18,IF(AND(ISNUMBER($BJ18),ISNUMBER($BK18)),BK18,"")) | BD18: =IF(ISNUMBER(BT18),BT18,IF(AND(ISNUMBER($BO18),ISNUMBER($BP18)),BN18,"")) | BE18: =IF(ISNUMBER(BU18),BU18,IF(AND(ISNUMBER($BO18),ISNUMBER($BP18)),BO18,"")) | BF18: =IF(ISNUMBER(BV18),BV18,IF(AND(ISNUMBER($BO18),ISNUMBER($BP18)),BP18,"")) | BJ18: =IF(AND(ISNUMBER(BG18),ISNUMBER(BH18),ISNUMBER(BI18)),EXP(LOG(BI18)-1.96*SQRT((1/BG18)+(1/BH18))),"") | BK18: =IF(AND(ISNUMBER(BG18),ISNUMBER(BH18),ISNUMBER(BI18)),EXP(LOG(BI18)+1.96*SQRT((1/BG18)+(1/BH18))),"") | BO18: =IF(AND(ISNUMBER(BL18),ISNUMBER(BM18),ISNUMBER(BN18)),EXP(LOG(BN18)-1.96*SQRT((1/BL18)+(1/BM18))),"") | BP18: =IF(AND(ISNUMBER(BL18),ISNUMBER(BM18),ISNUMBER(BN18)),EXP(LOG(BN18)+1.96*SQRT((1/BL18)+(1/BM18))),"") | CC18: =14-3 -> 11 | CD18: 5 | CG18: 5 | CV18: Cell level not defined. "... defining late engraftment as that occurring 18 days post-BMT" | CX18: marked broad engraftment as neutrophil
A19: Savolainen H | B19: 2005 | C19: https://pubmed.ncbi.nlm.nih.gov/15700258 | D19: =A19&" "&B19 -> Savolainen H 2005 | E19: =IF(OR(AND(ISNUMBER(AG19),ISNUMBER(AL19),ISNUMBER(CC19),ISNUMBER(CG19)),AND(ISNUMBER(AG19),ISNUMBER(AM19),ISNUMBER(CC19),ISNUMBER(CH19))),"Yes","No") -> Yes | F19: 60 | G19: Unclear for whole cohort | H19: 2 | I19: 20 | J19: =16+3 -> 19 | K19: =5+34+2+3 -> 44 | P19: =F19 -> 60 | AA19: =F19 -> 60 | AB19: =7+37 -> 44 | AC19: =14+2 -> 16 | AG19: 45 | AH19: 0 | AI19: 1 | AL19: 1 | AP19: 20 | AU19: 44 | BA19: =IF(ISNUMBER(BQ19),BQ19,IF(AND(ISNUMBER($BJ19),ISNUMBER($BK19)),BI19,"")) -> 0.7 | BB19: =IF(ISNUMBER(BR19),BR19,IF(AND(ISNUMBER($BJ19),ISNUMBER($BK19)),BJ19,"")) -> 0.47667574 | BC19: =IF(ISNUMBER(BS19),BS19,IF(AND(ISNUMBER($BJ19),ISNUMBER($BK19)),BK19,"")) -> 1.5389724 | BD19: =IF(ISNUMBER(BT19),BT19,IF(AND(ISNUMBER($BO19),ISNUMBER($BP19)),BN19,"")) -> 0.5 | BE19: =IF(ISNUMBER(BU19),BU19,IF(AND(ISNUMBER($BO19),ISNUMBER($BP19)),BO19,"")) -> 0.41187027 | BF19: =IF(ISNUMBER(BV19),BV19,IF(AND(ISNUMBER($BO19),ISNUMBER($BP19)),BP19,"")) -> 1.3297446 | BG19: =AG19-1 -> 44 | BH19: =CC19 -> 15 | BI19: =CK19/AP19 -> 0.7 | BJ19: =IF(AND(ISNUMBER(BG19),ISNUMBER(BH19),ISNUMBER(BI19)),EXP(LOG(BI19)-1.96*SQRT((1/BG19)+(1/BH19))),"") -> 0.47667574 | BK19: =IF(AND(ISNUMBER(BG19),ISNUMBER(BH19),ISNUMBER(BI19)),EXP(LOG(BI19)+1.96*SQRT((1/BG19)+(1/BH19))),"") -> 1.5389724 | BL19: =AG19-1 -> 44 | BM19: =CC19 -> 15 | BN19: =CP19/AU19 -> 0.5 | BO19: =IF(AND(ISNUMBER(BL19),ISNUMBER(BM19),ISNUMBER(BN19)),EXP(LOG(BN19)-1.96*SQRT((1/BL19)+(1/BM19))),"") -> 0.41187027 | BP19: =IF(AND(ISNUMBER(BL19),ISNUMBER(BM19),ISNUMBER(BN19)),EXP(LOG(BN19)+1.96*SQRT((1/BL19)+(1/BM19))),"") -> 1.3297446 | CC19: =F19-AG19 -> 15 | CD19: 0 | CG19: 0 | CK19: 14 | CP19: 22 | CX19: marked broad engraftment as neutrophil
A20: Violago L | B20: 2015 | C20: https://pubmed.ncbi.nlm.nih.gov/26329541 | D20: =A20&" "&B20 -> Violago L 2015 | E20: =IF(OR(AND(ISNUMBER(AG20),ISNUMBER(AL20),ISNUMBER(CC20),ISNUMBER(CG20)),AND(ISNUMBER(AG20),ISNUMBER(AM20),ISNUMBER(CC20),ISNUMBER(CH20))),"Yes","No") -> Yes | F20: 100 | G20: 9 | H20: 0.25 | I20: 22 | J20: =35+22 -> 57 | K20: 43 | M20: =F20 -> 100 | AA20: =F20 -> 100 | AB20: 49 | AC20: 30 | AD20: 21 | AF20: 100 | AG20: 19 | AH20: Timing of IR failure relative to HHV-6 detection is unclear, but systemic testing was performed | AL20: =ROUND(AG20*(1-0.85),0) -> 3 | AM20: =ROUND(AG20*(1-0.58),0) -> 8 | BA20: =IF(ISNUMBER(BQ20),BQ20,IF(AND(ISNUMBER($BJ20),ISNUMBER($BK20)),BI20,"")) | BB20: =IF(ISNUMBER(BR20),BR20,IF(AND(ISNUMBER($BJ20),ISNUMBER($BK20)),BJ20,"")) | BC20: =IF(ISNUMBER(BS20),BS20,IF(AND(ISNUMBER($BJ20),ISNUMBER($BK20)),BK20,"")) | BD20: =IF(ISNUMBER(BT20),BT20,IF(AND(ISNUMBER($BO20),ISNUMBER($BP20)),BN20,"")) -> 0.91 | BE20: =IF(ISNUMBER(BU20),BU20,IF(AND(ISNUMBER($BO20),ISNUMBER($BP20)),BO20,"")) -> 0.447 | BF20: =IF(ISNUMBER(BV20),BV20,IF(AND(ISNUMBER($BO20),ISNUMBER($BP20)),BP20,"")) -> 1.852 | BJ20: =IF(AND(ISNUMBER(BG20),ISNUMBER(BH20),ISNUMBER(BI20)),EXP(LOG(BI20)-1.96*SQRT((1/BG20)+(1/BH20))),"") | BK20: =IF(AND(ISNUMBER(BG20),ISNUMBER(BH20),ISNUMBER(BI20)),EXP(LOG(BI20)+1.96*SQRT((1/BG20)+(1/BH20))),"") | BO20: =IF(AND(ISNUMBER(BL20),ISNUMBER(BM20),ISNUMBER(BN20)),EXP(LOG(BN20)-1.96*SQRT((1/BL20)+(1/BM20))),"") | BP20: =IF(AND(ISNUMBER(BL20),ISNUMBER(BM20),ISNUMBER(BN20)),EXP(LOG(BN20)+1.96*SQRT((1/BL20)+(1/BM20))),"") | BT20: 0.91 | BU20: 0.447 | BV20: 1.852 | CC20: 81 | CG20: =ROUND(CC20*(1-0.74),0) -> 21 | CH20: =ROUND(CC20*(1-0.82),0) -> 15
A21: Wang FZ | B21: 1996 | C21: https://pubmed.ncbi.nlm.nih.gov/8896431 | D21: =A21&" "&B21 -> Wang FZ 1996 | E21: =IF(OR(AND(ISNUMBER(AG21),ISNUMBER(AL21),ISNUMBER(CC21),ISNUMBER(CG21)),AND(ISNUMBER(AG21),ISNUMBER(AM21),ISNUMBER(CC21),ISNUMBER(CH21))),"Yes","No") -> Yes | AG21: 8 | AH21: Timing of IR failure relative to HHV-6 detection is unclear, but systemic testing was performed | AL21: =1+2+1+1 -> 5 | BA21: =IF(ISNUMBER(BQ21),BQ21,IF(AND(ISNUMBER($BJ21),ISNUMBER($BK21)),BI21,"")) | BB21: =IF(ISNUMBER(BR21),BR21,IF(AND(ISNUMBER($BJ21),ISNUMBER($BK21)),BJ21,"")) | BC21: =IF(ISNUMBER(BS21),BS21,IF(AND(ISNUMBER($BJ21),ISNUMBER($BK21)),BK21,"")) | BD21: =IF(ISNUMBER(BT21),BT21,IF(AND(ISNUMBER($BO21),ISNUMBER($BP21)),BN21,"")) | BE21: =IF(ISNUMBER(BU21),BU21,IF(AND(ISNUMBER($BO21),ISNUMBER($BP21)),BO21,"")) | BF21: =IF(ISNUMBER(BV21),BV21,IF(AND(ISNUMBER($BO21),ISNUMBER($BP21)),BP21,"")) | BJ21: =IF(AND(ISNUMBER(BG21),ISNUMBER(BH21),ISNUMBER(BI21)),EXP(LOG(BI21)-1.96*SQRT((1/BG21)+(1/BH21))),"") | BK21: =IF(AND(ISNUMBER(BG21),ISNUMBER(BH21),ISNUMBER(BI21)),EXP(LOG(BI21)+1.96*SQRT((1/BG21)+(1/BH21))),"") | BO21: =IF(AND(ISNUMBER(BL21),ISNUMBER(BM21),ISNUMBER(BN21)),EXP(LOG(BN21)-1.96*SQRT((1/BL21)+(1/BM21))),"") | BP21: =IF(AND(ISNUMBER(BL21),ISNUMBER(BM21),ISNUMBER(BN21)),EXP(LOG(BN21)+1.96*SQRT((1/BL21)+(1/BM21))),"") | CC21: =37-8 -> 29 | CG21: 3
A22: Wang LR | B22: 2006 | C22: https://pubmed.ncbi.nlm.nih.gov/17067909 | D22: =A22&" "&B22 -> Wang LR 2006 | E22: =IF(OR(AND(ISNUMBER(AG22),ISNUMBER(AL22),ISNUMBER(CC22),ISNUMBER(CG22)),AND(ISNUMBER(AG22),ISNUMBER(AM22),ISNUMBER(CC22),ISNUMBER(CH22))),"Yes","No") -> Yes | F22: 72 | G22: 28 | H22: 8 | I22: 58 | J22: 25 | K22: 47 | M22: =F22 -> 72 | S22: =F22 -> 72 | AB22: =F22 -> 72 | AF22: 72 | AG22: 27 | AH22: Timing of IR failure relative to HHV-6 detection is unclear, but systemic testing was performed | AL22: 0 | AM22: 4 | BA22: =IF(ISNUMBER(BQ22),BQ22,IF(AND(ISNUMBER($BJ22),ISNUMBER($BK22)),BI22,"")) -> 2.28 | BB22: =IF(ISNUMBER(BR22),BR22,IF(AND(ISNUMBER($BJ22),ISNUMBER($BK22)),BJ22,"")) -> 0.86 | BC22: =IF(ISNUMBER(BS22),BS22,IF(AND(ISNUMBER($BJ22),ISNUMBER($BK22)),BK22,"")) -> 6.06 | BD22: =IF(ISNUMBER(BT22),BT22,IF(AND(ISNUMBER($BO22),ISNUMBER($BP22)),BN22,"")) -> 1.02 | BE22: =IF(ISNUMBER(BU22),BU22,IF(AND(ISNUMBER($BO22),ISNUMBER($BP22)),BO22,"")) -> 0.47 | BF22: =IF(ISNUMBER(BV22),BV22,IF(AND(ISNUMBER($BO22),ISNUMBER($BP22)),BP22,"")) -> 2.19 | BJ22: =IF(AND(ISNUMBER(BG22),ISNUMBER(BH22),ISNUMBER(BI22)),EXP(LOG(BI22)-1.96*SQRT((1/BG22)+(1/BH22))),"") | BK22: =IF(AND(ISNUMBER(BG22),ISNUMBER(BH22),ISNUMBER(BI22)),EXP(LOG(BI22)+1.96*SQRT((1/BG22)+(1/BH22))),"") | BO22: =IF(AND(ISNUMBER(BL22),ISNUMBER(BM22),ISNUMBER(BN22)),EXP(LOG(BN22)-1.96*SQRT((1/BL22)+(1/BM22))),"") | BP22: =IF(AND(ISNUMBER(BL22),ISNUMBER(BM22),ISNUMBER(BN22)),EXP(LOG(BN22)+1.96*SQRT((1/BL22)+(1/BM22))),"") | BQ22: 2.28 | BR22: 0.86 | BS22: 6.06 | BT22: 1.02 | BU22: 0.47 | BV22: 2.19 | CC22: =AF22-AG22 -> 45 | CG22: 1 | CH22: =45-31 -> 14 | CX22: Labeled 2006a in FTR. Day 50 HR's chosen
A23: Balsat M | B23: 2019 | C23: https://pubmed.ncbi.nlm.nih.gov/31075291 | D23: =A23&" "&B23 -> Balsat M 2019 | E23: =IF(OR(AND(ISNUMBER(AG23),ISNUMBER(AL23),ISNUMBER(CC23),ISNUMBER(CG23)),AND(ISNUMBER(AG23),ISNUMBER(AM23),ISNUMBER(CC23),ISNUMBER(CH23))),"Yes","No") -> No | AG23: 22 | AH23: Timing of IR failure relative to HHV-6 detection is unclear, but systemic testing was performed | AO23: 8 | AP23: 10 | AQ23: 14 | BA23: =IF(ISNUMBER(BQ23),BQ23,IF(AND(ISNUMBER($BJ23),ISNUMBER($BK23)),BI23,"")) -> 0.8 | BB23: =IF(ISNUMBER(BR23),BR23,IF(AND(ISNUMBER($BJ23),ISNUMBER($BK23)),BJ23,"")) -> 0.58250668 | BC23: =IF(ISNUMBER(BS23),BS23,IF(AND(ISNUMBER($BJ23),ISNUMBER($BK23)),BK23,"")) -> 1.4142433 | BD23: =IF(ISNUMBER(BT23),BT23,IF(AND(ISNUMBER($BO23),ISNUMBER($BP23)),BN23,"")) | BE23: =IF(ISNUMBER(BU23),BU23,IF(AND(ISNUMBER($BO23),ISNUMBER($BP23)),BO23,"")) | BF23: =IF(ISNUMBER(BV23),BV23,IF(AND(ISNUMBER($BO23),ISNUMBER($BP23)),BP23,"")) | BG23: =AG23*1 -> 22 | BH23: =CC23*1 -> 174 | BI23: =CK23/AP23 -> 0.8 | BJ23: =IF(AND(ISNUMBER(BG23),ISNUMBER(BH23),ISNUMBER(BI23)),EXP(LOG(BI23)-1.96*SQRT((1/BG23)+(1/BH23))),"") -> 0.58250668 | BK23: =IF(AND(ISNUMBER(BG23),ISNUMBER(BH23),ISNUMBER(BI23)),EXP(LOG(BI23)+1.96*SQRT((1/BG23)+(1/BH23))),"") -> 1.4142433 | BO23: =IF(AND(ISNUMBER(BL23),ISNUMBER(BM23),ISNUMBER(BN23)),EXP(LOG(BN23)-1.96*SQRT((1/BL23)+(1/BM23))),"") | BP23: =IF(AND(ISNUMBER(BL23),ISNUMBER(BM23),ISNUMBER(BN23)),EXP(LOG(BN23)+1.96*SQRT((1/BL23)+(1/BM23))),"") | CC23: 174 | CJ23: 6 | CK23: 8 | CL23: 11 | CV23: Neutropenia recovery was defined as absolute neutrophil count (ANC) > 0.5× 10^9/L for two consecutive days. | CW23: Platelets recovery was defined as platelets count > 20× 109/L without transfusion support.
A24: Inazawa N | B24: 2017 | C24: https://pubmed.ncbi.nlm.nih.gov/27364410 | D24: =A24&" "&B24 -> Inazawa N 2017 | E24: =IF(OR(AND(ISNUMBER(AG24),ISNUMBER(AL24),ISNUMBER(CC24),ISNUMBER(CG24)),AND(ISNUMBER(AG24),ISNUMBER(AM24),ISNUMBER(CC24),ISNUMBER(CH24))),"Yes","No") -> No | AG24: 9 | AH24: Timing of IR failure relative to HHV-6 detection is unclear, but systemic testing was performed | AN24: 8 | AP24: 11 | AR24: 15 | BA24: =IF(ISNUMBER(BQ24),BQ24,IF(AND(ISNUMBER($BJ24),ISNUMBER($BK24)),BI24,"")) -> 1.0909091 | BB24: =IF(ISNUMBER(BR24),BR24,IF(AND(ISNUMBER($BJ24),ISNUMBER($BK24)),BJ24,"")) -> 0.44391399 | BC24: =IF(ISNUMBER(BS24),BS24,IF(AND(ISNUMBER($BJ24),ISNUMBER($BK24)),BK24,"")) -> 2.4295391 | BD24: =IF(ISNUMBER(BT24),BT24,IF(AND(ISNUMBER($BO24),ISNUMBER($BP24)),BN24,"")) | BE24: =IF(ISNUMBER(BU24),BU24,IF(AND(ISNUMBER($BO24),ISNUMBER($BP24)),BO24,"")) | BF24: =IF(ISNUMBER(BV24),BV24,IF(AND(ISNUMBER($BO24),ISNUMBER($BP24)),BP24,"")) | BG24: 9 | BH24: 13 | BI24: =CK24/AP24 -> 1.0909091 | BJ24: =IF(AND(ISNUMBER(BG24),ISNUMBER(BH24),ISNUMBER(BI24)),EXP(LOG(BI24)-1.96*SQRT((1/BG24)+(1/BH24))),"") -> 0.44391399 | BK24: =IF(AND(ISNUMBER(BG24),ISNUMBER(BH24),ISNUMBER(BI24)),EXP(LOG(BI24)+1.96*SQRT((1/BG24)+(1/BH24))),"") -> 2.4295391 | BO24: =IF(AND(ISNUMBER(BL24),ISNUMBER(BM24),ISNUMBER(BN24)),EXP(LOG(BN24)-1.96*SQRT((1/BL24)+(1/BM24))),"") | BP24: =IF(AND(ISNUMBER(BL24),ISNUMBER(BM24),ISNUMBER(BN24)),EXP(LOG(BN24)+1.96*SQRT((1/BL24)+(1/BM24))),"") | CC24: 13 | CI24: 5 | CK24: 12 | CM24: 20 | CV24: Not defined
A25: Ishiyama K | B25: 2011 | C25: https://pubmed.ncbi.nlm.nih.gov/20838386 | D25: =A25&" "&B25 -> Ishiyama K 2011 | E25: =IF(OR(AND(ISNUMBER(AG25),ISNUMBER(AL25),ISNUMBER(CC25),ISNUMBER(CG25)),AND(ISNUMBER(AG25),ISNUMBER(AM25),ISNUMBER(CC25),ISNUMBER(CH25))),"Yes","No") -> No | AG25: 12 | AH25: Timing of IR failure relative to HHV-6 detection is unclear, but systemic testing was performed | AP25: 27 | BA25: =IF(ISNUMBER(BQ25),BQ25,IF(AND(ISNUMBER($BJ25),ISNUMBER($BK25)),BI25,"")) -> 0.92592593 | BB25: =IF(ISNUMBER(BR25),BR25,IF(AND(ISNUMBER($BJ25),ISNUMBER($BK25)),BJ25,"")) -> 0.27291406 | BC25: =IF(ISNUMBER(BS25),BS25,IF(AND(ISNUMBER($BJ25),ISNUMBER($BK25)),BK25,"")) -> 3.4272247 | BD25: =IF(ISNUMBER(BT25),BT25,IF(AND(ISNUMBER($BO25),ISNUMBER($BP25)),BN25,"")) | BE25: =IF(ISNUMBER(BU25),BU25,IF(AND(ISNUMBER($BO25),ISNUMBER($BP25)),BO25,"")) | BF25: =IF(ISNUMBER(BV25),BV25,IF(AND(ISNUMBER($BO25),ISNUMBER($BP25)),BP25,"")) | BG25: 12 | BH25: 3 | BI25: =CK25/AP25 -> 0.92592593 | BJ25: =IF(AND(ISNUMBER(BG25),ISNUMBER(BH25),ISNUMBER(BI25)),EXP(LOG(BI25)-1.96*SQRT((1/BG25)+(1/BH25))),"") -> 0.27291406 | BK25: =IF(AND(ISNUMBER(BG25),ISNUMBER(BH25),ISNUMBER(BI25)),EXP(LOG(BI25)+1.96*SQRT((1/BG25)+(1/BH25))),"") -> 3.4272247 | BO25: =IF(AND(ISNUMBER(BL25),ISNUMBER(BM25),ISNUMBER(BN25)),EXP(LOG(BN25)-1.96*SQRT((1/BL25)+(1/BM25))),"") | BP25: =IF(AND(ISNUMBER(BL25),ISNUMBER(BM25),ISNUMBER(BN25)),EXP(LOG(BN25)+1.96*SQRT((1/BL25)+(1/BM25))),"") | CC25: 3 | CK25: 25 | CV25: "... neutrophils >0.5 x 10^9/L"
A26: Olson AL | B26: 2014 | C26: https://pubmed.ncbi.nlm.nih.gov/24548875 | D26: =A26&" "&B26 -> Olson AL 2014 | E26: =IF(OR(AND(ISNUMBER(AG26),ISNUMBER(AL26),ISNUMBER(CC26),ISNUMBER(CG26)),AND(ISNUMBER(AG26),ISNUMBER(AM26),ISNUMBER(CC26),ISNUMBER(CH26))),"Yes","No") -> No | AG26: 51 | AH26: Timing of IR failure relative to HHV-6 detection is unclear, but systemic testing was performed | AN26: 7 | AP26: 22 | AR26: 38 | AS26: 32 | AU26: 48 | AW26: 99 | BA26: =IF(ISNUMBER(BQ26),BQ26,IF(AND(ISNUMBER($BJ26),ISNUMBER($BK26)),BI26,"")) -> 0.98 | BB26: =IF(ISNUMBER(BR26),BR26,IF(AND(ISNUMBER($BJ26),ISNUMBER($BK26)),BJ26,"")) -> 0.68 | BC26: =IF(ISNUMBER(BS26),BS26,IF(AND(ISNUMBER($BJ26),ISNUMBER($BK26)),BK26,"")) -> 1.41 | BD26: =IF(ISNUMBER(BT26),BT26,IF(AND(ISNUMBER($BO26),ISNUMBER($BP26)),BN26,"")) -> 1.01 | BE26: =IF(ISNUMBER(BU26),BU26,IF(AND(ISNUMBER($BO26),ISNUMBER($BP26)),BO26,"")) -> 0.68 | BF26: =IF(ISNUMBER(BV26),BV26,IF(AND(ISNUMBER($BO26),ISNUMBER($BP26)),BP26,"")) -> 1.5 | BG26: Unclear | BH26: Unclear | BI26: =CK26/AP26 -> 0.95454545 | BJ26: =IF(AND(ISNUMBER(BG26),ISNUMBER(BH26),ISNUMBER(BI26)),EXP(LOG(BI26)-1.96*SQRT((1/BG26)+(1/BH26))),"") | BK26: =IF(AND(ISNUMBER(BG26),ISNUMBER(BH26),ISNUMBER(BI26)),EXP(LOG(BI26)+1.96*SQRT((1/BG26)+(1/BH26))),"") | BL26: Unclear | BM26: Unclear | BN26: =CP26/AU26 -> 0.95833333 | BO26: =IF(AND(ISNUMBER(BL26),ISNUMBER(BM26),ISNUMBER(BN26)),EXP(LOG(BN26)-1.96*SQRT((1/BL26)+(1/BM26))),"") | BP26: =IF(AND(ISNUMBER(BL26),ISNUMBER(BM26),ISNUMBER(BN26)),EXP(LOG(BN26)+1.96*SQRT((1/BL26)+(1/BM26))),"") | BQ26: 0.98 | BR26: 0.68 | BS26: 1.41 | BT26: 1.01 | BU26: 0.68 | BV26: 1.5 | CC26: 74 | CI26: 7 | CK26: 21 | CM26: 43 | CN26: 21 | CP26: 46 | CR26: 90 | CV26: Not defined
A27: Quintela A | B27: 2016 | C27: https://pubmed.ncbi.nlm.nih.gov/26518057 | D27: =A27&" "&B27 -> Quintela A 2016 | E27: =IF(OR(AND(ISNUMBER(AG27),ISNUMBER(AL27),ISNUMBER(CC27),ISNUMBER(CG27)),AND(ISNUMBER(AG27),ISNUMBER(AM27),ISNUMBER(CC27),ISNUMBER(CH27))),"Yes","No") -> No | AG27: 75 | AH27: Timing of IR failure relative to HHV-6 detection is unclear | AN27: 8 | AP27: 24 | AR27: 43 | BA27: =IF(ISNUMBER(BQ27),BQ27,IF(AND(ISNUMBER($BJ27),ISNUMBER($BK27)),BI27,"")) | BB27: =IF(ISNUMBER(BR27),BR27,IF(AND(ISNUMBER($BJ27),ISNUMBER($BK27)),BJ27,"")) | BC27: =IF(ISNUMBER(BS27),BS27,IF(AND(ISNUMBER($BJ27),ISNUMBER($BK27)),BK27,"")) | BD27: =IF(ISNUMBER(BT27),BT27,IF(AND(ISNUMBER($BO27),ISNUMBER($BP27)),BN27,"")) | BE27: =IF(ISNUMBER(BU27),BU27,IF(AND(ISNUMBER($BO27),ISNUMBER($BP27)),BO27,"")) | BF27: =IF(ISNUMBER(BV27),BV27,IF(AND(ISNUMBER($BO27),ISNUMBER($BP27)),BP27,"")) | BG27: Unclear | BH27: Unclear | BI27: =CK27/AP27 -> 0.83333333 | BJ27: =IF(AND(ISNUMBER(BG27),ISNUMBER(BH27),ISNUMBER(BI27)),EXP(LOG(BI27)-1.96*SQRT((1/BG27)+(1/BH27))),"") | BK27: =IF(AND(ISNUMBER(BG27),ISNUMBER(BH27),ISNUMBER(BI27)),EXP(LOG(BI27)+1.96*SQRT((1/BG27)+(1/BH27))),"") | BO27: =IF(AND(ISNUMBER(BL27),ISNUMBER(BM27),ISNUMBER(BN27)),EXP(LOG(BN27)-1.96*SQRT((1/BL27)+(1/BM27))),"") | BP27: =IF(AND(ISNUMBER(BL27),ISNUMBER(BM27),ISNUMBER(BN27)),EXP(LOG(BN27)+1.96*SQRT((1/BL27)+(1/BM27))),"") | CC27: 291 | CI27: 2 | CK27: 20 | CM27: 48 | CV27: Not defined
A28: Tormo N | B28: 2010 | C28: https://pubmed.ncbi.nlm.nih.gov/20005968 | D28: =A28&" "&B28 -> Tormo N 2010 | E28: =IF(OR(AND(ISNUMBER(AG28),ISNUMBER(AL28),ISNUMBER(CC28),ISNUMBER(CG28)),AND(ISNUMBER(AG28),ISNUMBER(AM28),ISNUMBER(CC28),ISNUMBER(CH28))),"Yes","No") -> No | AH28: Timing of IR failure relative to HHV-6 detection is unclear | BA28: =IF(ISNUMBER(BQ28),BQ28,IF(AND(ISNUMBER($BJ28),ISNUMBER($BK28)),BI28,"")) -> 1 | BB28: =IF(ISNUMBER(BR28),BR28,IF(AND(ISNUMBER($BJ28),ISNUMBER($BK28)),BJ28,"")) -> 0.8 | BC28: =IF(ISNUMBER(BS28),BS28,IF(AND(ISNUMBER($BJ28),ISNUMBER($BK28)),BK28,"")) -> 1.7 | BD28: =IF(ISNUMBER(BT28),BT28,IF(AND(ISNUMBER($BO28),ISNUMBER($BP28)),BN28,"")) -> 0.9 | BE28: =IF(ISNUMBER(BU28),BU28,IF(AND(ISNUMBER($BO28),ISNUMBER($BP28)),BO28,"")) -> 0.7 | BF28: =IF(ISNUMBER(BV28),BV28,IF(AND(ISNUMBER($BO28),ISNUMBER($BP28)),BP28,"")) -> 2.1 | BJ28: =IF(AND(ISNUMBER(BG28),ISNUMBER(BH28),ISNUMBER(BI28)),EXP(LOG(BI28)-1.96*SQRT((1/BG28)+(1/BH28))),"") | BK28: =IF(AND(ISNUMBER(BG28),ISNUMBER(BH28),ISNUMBER(BI28)),EXP(LOG(BI28)+1.96*SQRT((1/BG28)+(1/BH28))),"") | BO28: =IF(AND(ISNUMBER(BL28),ISNUMBER(BM28),ISNUMBER(BN28)),EXP(LOG(BN28)-1.96*SQRT((1/BL28)+(1/BM28))),"") | BP28: =IF(AND(ISNUMBER(BL28),ISNUMBER(BM28),ISNUMBER(BN28)),EXP(LOG(BN28)+1.96*SQRT((1/BL28)+(1/BM28))),"") | BQ28: 1 | BR28: 0.8 | BS28: 1.7 | BT28: 0.9 | BU28: 0.7 | BV28: 2.1
A29: Yoshikawa T | B29: 2002 | C29: https://pubmed.ncbi.nlm.nih.gov/11920307 | D29: =A29&" "&B29 -> Yoshikawa T 2002 | E29: =IF(OR(AND(ISNUMBER(AG29),ISNUMBER(AL29),ISNUMBER(CC29),ISNUMBER(CG29)),AND(ISNUMBER(AG29),ISNUMBER(AM29),ISNUMBER(CC29),ISNUMBER(CH29))),"Yes","No") -> No | AG29: 31 | AH29: Timing of IR failure relative to HHV-6 detection is unclear, but systemic testing was performed | AN29: 10 | AP29: 17.3 | AR29: 38 | AS29: 16 | AU29: 31 | AW29: 60 | BA29: =IF(ISNUMBER(BQ29),BQ29,IF(AND(ISNUMBER($BJ29),ISNUMBER($BK29)),BI29,"")) | BB29: =IF(ISNUMBER(BR29),BR29,IF(AND(ISNUMBER($BJ29),ISNUMBER($BK29)),BJ29,"")) | BC29: =IF(ISNUMBER(BS29),BS29,IF(AND(ISNUMBER($BJ29),ISNUMBER($BK29)),BK29,"")) | BD29: =IF(ISNUMBER(BT29),BT29,IF(AND(ISNUMBER($BO29),ISNUMBER($BP29)),BN29,"")) | BE29: =IF(ISNUMBER(BU29),BU29,IF(AND(ISNUMBER($BO29),ISNUMBER($BP29)),BO29,"")) | BF29: =IF(ISNUMBER(BV29),BV29,IF(AND(ISNUMBER($BO29),ISNUMBER($BP29)),BP29,"")) | BG29: Unclear | BH29: Unclear | BI29: =CK29/AP29 -> 1.0115607 | BJ29: =IF(AND(ISNUMBER(BG29),ISNUMBER(BH29),ISNUMBER(BI29)),EXP(LOG(BI29)-1.96*SQRT((1/BG29)+(1/BH29))),"") | BK29: =IF(AND(ISNUMBER(BG29),ISNUMBER(BH29),ISNUMBER(BI29)),EXP(LOG(BI29)+1.96*SQRT((1/BG29)+(1/BH29))),"") | BL29: Unclear | BM29: Unclear | BN29: =CP29/AU29 -> 0.83870968 | BO29: =IF(AND(ISNUMBER(BL29),ISNUMBER(BM29),ISNUMBER(BN29)),EXP(LOG(BN29)-1.96*SQRT((1/BL29)+(1/BM29))),"") | BP29: =IF(AND(ISNUMBER(BL29),ISNUMBER(BM29),ISNUMBER(BN29)),EXP(LOG(BN29)+1.96*SQRT((1/BL29)+(1/BM29))),"") | CC29: 51 | CI29: 12 | CK29: 17.5 | CM29: 60 | CN29: 8 | CP29: 26 | CR29: 60
A30: Zerr DM | B30: 2005 | C30: https://pubmed.ncbi.nlm.nih.gov/15824982 | D30: =A30&" "&B30 -> Zerr DM 2005 | E30: =IF(OR(AND(ISNUMBER(AG30),ISNUMBER(AL30),ISNUMBER(CC30),ISNUMBER(CG30)),AND(ISNUMBER(AG30),ISNUMBER(AM30),ISNUMBER(CC30),ISNUMBER(CH30))),"Yes","No") -> No | AH30: Timing of IR failure relative to HHV-6 detection is unclear, but systemic testing was performed | BA30: =IF(ISNUMBER(BQ30),BQ30,IF(AND(ISNUMBER($BJ30),ISNUMBER($BK30)),BI30,"")) -> 1 | BB30: =IF(ISNUMBER(BR30),BR30,IF(AND(ISNUMBER($BJ30),ISNUMBER($BK30)),BJ30,"")) -> 0.46 | BC30: =IF(ISNUMBER(BS30),BS30,IF(AND(ISNUMBER($BJ30),ISNUMBER($BK30)),BK30,"")) -> 1.7 | BD30: =IF(ISNUMBER(BT30),BT30,IF(AND(ISNUMBER($BO30),ISNUMBER($BP30)),BN30,"")) -> 0.43 | BE30: =IF(ISNUMBER(BU30),BU30,IF(AND(ISNUMBER($BO30),ISNUMBER($BP30)),BO30,"")) -> 0.19 | BF30: =IF(ISNUMBER(BV30),BV30,IF(AND(ISNUMBER($BO30),ISNUMBER($BP30)),BP30,"")) -> 0.97 | BJ30: =IF(AND(ISNUMBER(BG30),ISNUMBER(BH30),ISNUMBER(BI30)),EXP(LOG(BI30)-1.96*SQRT((1/BG30)+(1/BH30))),"") | BK30: =IF(AND(ISNUMBER(BG30),ISNUMBER(BH30),ISNUMBER(BI30)),EXP(LOG(BI30)+1.96*SQRT((1/BG30)+(1/BH30))),"") | BO30: =IF(AND(ISNUMBER(BL30),ISNUMBER(BM30),ISNUMBER(BN30)),EXP(LOG(BN30)-1.96*SQRT((1/BL30)+(1/BM30))),"") | BP30: =IF(AND(ISNUMBER(BL30),ISNUMBER(BM30),ISNUMBER(BN30)),EXP(LOG(BN30)+1.96*SQRT((1/BL30)+(1/BM30))),"") | BQ30: 1 | BR30: 0.46 | BS30: 1.7 | BT30: 0.43 | BU30: 0.19 | BV30: 0.97 | CX30: Day 30 used for HR
A31: Chevallier P | B31: 2010 | C31: https://pubmed.ncbi.nlm.nih.gov/19935727 | D31: =A31&" "&B31 -> Chevallier P 2010 | E31: =IF(OR(AND(ISNUMBER(AL31),ISNUMBER(CG31)),AND(ISNUMBER(AM31),ISNUMBER(CH31)),AND(ISNUMBER(AP31),ISNUMBER(AN31),ISNUMBER(AR31),ISNUMBER(CK31),ISNUMBER(CI31),ISNUMBER(CM31)),AND(ISNUMBER(AU31),ISNUMBER(AS31),ISNUMBER(AW31),ISNUMBER(CP31),ISNUMBER(CN31),ISNUMBER(CR31)),AND(ISNUMBER(BB31),ISNUMBER(BC31))),"Yes","No") -> No | AG31: =12+17 -> 29 | AP31: 37.5 | AU31: 98.5 | BA31: =IF(ISNUMBER(BQ31),BQ31,IF(AND(ISNUMBER($BJ31),ISNUMBER($BK31)),BI31,"")) | BB31: =IF(ISNUMBER(BR31),BR31,IF(AND(ISNUMBER($BJ31),ISNUMBER($BK31)),BJ31,"")) | BC31: =IF(ISNUMBER(BS31),BS31,IF(AND(ISNUMBER($BJ31),ISNUMBER($BK31)),BK31,"")) | BD31: =IF(ISNUMBER(BT31),BT31,IF(AND(ISNUMBER($BO31),ISNUMBER($BP31)),BN31,"")) | BE31: =IF(ISNUMBER(BU31),BU31,IF(AND(ISNUMBER($BO31),ISNUMBER($BP31)),BO31,"")) | BF31: =IF(ISNUMBER(BV31),BV31,IF(AND(ISNUMBER($BO31),ISNUMBER($BP31)),BP31,"")) | BG31: Unclear | BH31: Unclear | BI31: =CK31/AP31 -> 0.44 | BJ31: =IF(AND(ISNUMBER(BG31),ISNUMBER(BH31),ISNUMBER(BI31)),EXP(LOG(BI31)-1.96*SQRT((1/BG31)+(1/BH31))),"") | BK31: =IF(AND(ISNUMBER(BG31),ISNUMBER(BH31),ISNUMBER(BI31)),EXP(LOG(BI31)+1.96*SQRT((1/BG31)+(1/BH31))),"") | BL31: Unclear | BM31: Unclear | BN31: =CP31/AU31 -> 0.12690355 | BO31: =IF(AND(ISNUMBER(BL31),ISNUMBER(BM31),ISNUMBER(BN31)),EXP(LOG(BN31)-1.96*SQRT((1/BL31)+(1/BM31))),"") | BP31: =IF(AND(ISNUMBER(BL31),ISNUMBER(BM31),ISNUMBER(BN31)),EXP(LOG(BN31)+1.96*SQRT((1/BL31)+(1/BM31))),"") | CC31: =15+40 -> 55 | CK31: 16.5 | CP31: 12.5
A32: Cirrone F | B32: 2016 | C32: https://pubmed.ncbi.nlm.nih.gov/26984480 | D32: =A32&" "&B32 -> Cirrone F 2016 | E32: =IF(OR(AND(ISNUMBER(AL32),ISNUMBER(CG32)),AND(ISNUMBER(AM32),ISNUMBER(CH32)),AND(ISNUMBER(AP32),ISNUMBER(AN32),ISNUMBER(AR32),ISNUMBER(CK32),ISNUMBER(CI32),ISNUMBER(CM32)),AND(ISNUMBER(AU32),ISNUMBER(AS32),ISNUMBER(AW32),ISNUMBER(CP32),ISNUMBER(CN32),ISNUMBER(CR32)),AND(ISNUMBER(BB32),ISNUMBER(BC32))),"Yes","No") -> No | AG32: 60 | AP32: 14 | AU32: 20 | BA32: =IF(ISNUMBER(BQ32),BQ32,IF(AND(ISNUMBER($BJ32),ISNUMBER($BK32)),BI32,"")) | BB32: =IF(ISNUMBER(BR32),BR32,IF(AND(ISNUMBER($BJ32),ISNUMBER($BK32)),BJ32,"")) | BC32: =IF(ISNUMBER(BS32),BS32,IF(AND(ISNUMBER($BJ32),ISNUMBER($BK32)),BK32,"")) | BD32: =IF(ISNUMBER(BT32),BT32,IF(AND(ISNUMBER($BO32),ISNUMBER($BP32)),BN32,"")) | BE32: =IF(ISNUMBER(BU32),BU32,IF(AND(ISNUMBER($BO32),ISNUMBER($BP32)),BO32,"")) | BF32: =IF(ISNUMBER(BV32),BV32,IF(AND(ISNUMBER($BO32),ISNUMBER($BP32)),BP32,"")) | BG32: Unclear | BH32: Unclear | BI32: =CK32/AP32 -> 1 | BJ32: =IF(AND(ISNUMBER(BG32),ISNUMBER(BH32),ISNUMBER(BI32)),EXP(LOG(BI32)-1.96*SQRT((1/BG32)+(1/BH32))),"") | BK32: =IF(AND(ISNUMBER(BG32),ISNUMBER(BH32),ISNUMBER(BI32)),EXP(LOG(BI32)+1.96*SQRT((1/BG32)+(1/BH32))),"") | BL32: Unclear | BM32: Unclear | BN32: =CP32/AU32 -> 1.15 | BO32: =IF(AND(ISNUMBER(BL32),ISNUMBER(BM32),ISNUMBER(BN32)),EXP(LOG(BN32)-1.96*SQRT((1/BL32)+(1/BM32))),"") | BP32: =IF(AND(ISNUMBER(BL32),ISNUMBER(BM32),ISNUMBER(BN32)),EXP(LOG(BN32)+1.96*SQRT((1/BL32)+(1/BM32))),"") | CC32: =92-60 -> 32 | CK32: 14 | CP32: 23
A33: de Koning C | B33: 2018 | C33: https://pubmed.ncbi.nlm.nih.gov/29487057 | D33: =A33&" "&B33 -> de Koning C 2018 | E33: =IF(OR(AND(ISNUMBER(AL33),ISNUMBER(CG33)),AND(ISNUMBER(AM33),ISNUMBER(CH33)),AND(ISNUMBER(AP33),ISNUMBER(AN33),ISNUMBER(AR33),ISNUMBER(CK33),ISNUMBER(CI33),ISNUMBER(CM33)),AND(ISNUMBER(AU33),ISNUMBER(AS33),ISNUMBER(AW33),ISNUMBER(CP33),ISNUMBER(CN33),ISNUMBER(CR33)),AND(ISNUMBER(BB33),ISNUMBER(BC33))),"Yes","No") -> No | AG33: 79 | AY33: 84 | BA33: =IF(ISNUMBER(BQ33),BQ33,IF(AND(ISNUMBER($BJ33),ISNUMBER($BK33)),BI33,"")) | BB33: =IF(ISNUMBER(BR33),BR33,IF(AND(ISNUMBER($BJ33),ISNUMBER($BK33)),BJ33,"")) | BC33: =IF(ISNUMBER(BS33),BS33,IF(AND(ISNUMBER($BJ33),ISNUMBER($BK33)),BK33,"")) | BD33: =IF(ISNUMBER(BT33),BT33,IF(AND(ISNUMBER($BO33),ISNUMBER($BP33)),BN33,"")) | BE33: =IF(ISNUMBER(BU33),BU33,IF(AND(ISNUMBER($BO33),ISNUMBER($BP33)),BO33,"")) | BF33: =IF(ISNUMBER(BV33),BV33,IF(AND(ISNUMBER($BO33),ISNUMBER($BP33)),BP33,"")) | BJ33: =IF(AND(ISNUMBER(BG33),ISNUMBER(BH33),ISNUMBER(BI33)),EXP(LOG(BI33)-1.96*SQRT((1/BG33)+(1/BH33))),"") | BK33: =IF(AND(ISNUMBER(BG33),ISNUMBER(BH33),ISNUMBER(BI33)),EXP(LOG(BI33)+1.96*SQRT((1/BG33)+(1/BH33))),"") | BO33: =IF(AND(ISNUMBER(BL33),ISNUMBER(BM33),ISNUMBER(BN33)),EXP(LOG(BN33)-1.96*SQRT((1/BL33)+(1/BM33))),"") | BP33: =IF(AND(ISNUMBER(BL33),ISNUMBER(BM33),ISNUMBER(BN33)),EXP(LOG(BN33)+1.96*SQRT((1/BL33)+(1/BM33))),"") | BW33: 0.913 | BX33: 0.892 | BY33: 0.934 | BZ33: 0.912 | CA33: 0.891 | CB33: 0.933 | CC33: =273-AG33 -> 194 | CT33: 78
A34: de Pagter AP | B34: 2012 | C34: https://pubmed.ncbi.nlm.nih.gov/22820131 | D34: =A34&" "&B34 -> de Pagter AP 2012 | E34: =IF(OR(AND(ISNUMBER(AL34),ISNUMBER(CG34)),AND(ISNUMBER(AM34),ISNUMBER(CH34)),AND(ISNUMBER(AP34),ISNUMBER(AN34),ISNUMBER(AR34),ISNUMBER(CK34),ISNUMBER(CI34),ISNUMBER(CM34)),AND(ISNUMBER(AU34),ISNUMBER(AS34),ISNUMBER(AW34),ISNUMBER(CP34),ISNUMBER(CN34),ISNUMBER(CR34)),AND(ISNUMBER(BB34),ISNUMBER(BC34))),"Yes","No") -> No | BA34: =IF(ISNUMBER(BQ34),BQ34,IF(AND(ISNUMBER($BJ34),ISNUMBER($BK34)),BI34,"")) | BB34: =IF(ISNUMBER(BR34),BR34,IF(AND(ISNUMBER($BJ34),ISNUMBER($BK34)),BJ34,"")) | BC34: =IF(ISNUMBER(BS34),BS34,IF(AND(ISNUMBER($BJ34),ISNUMBER($BK34)),BK34,"")) | BD34: =IF(ISNUMBER(BT34),BT34,IF(AND(ISNUMBER($BO34),ISNUMBER($BP34)),BN34,"")) | BE34: =IF(ISNUMBER(BU34),BU34,IF(AND(ISNUMBER($BO34),ISNUMBER($BP34)),BO34,"")) | BF34: =IF(ISNUMBER(BV34),BV34,IF(AND(ISNUMBER($BO34),ISNUMBER($BP34)),BP34,"")) | BJ34: =IF(AND(ISNUMBER(BG34),ISNUMBER(BH34),ISNUMBER(BI34)),EXP(LOG(BI34)-1.96*SQRT((1/BG34)+(1/BH34))),"") | BK34: =IF(AND(ISNUMBER(BG34),ISNUMBER(BH34),ISNUMBER(BI34)),EXP(LOG(BI34)+1.96*SQRT((1/BG34)+(1/BH34))),"") | BO34: =IF(AND(ISNUMBER(BL34),ISNUMBER(BM34),ISNUMBER(BN34)),EXP(LOG(BN34)-1.96*SQRT((1/BL34)+(1/BM34))),"") | BP34: =IF(AND(ISNUMBER(BL34),ISNUMBER(BM34),ISNUMBER(BN34)),EXP(LOG(BN34)+1.96*SQRT((1/BL34)+(1/BM34))),"")
A35: Dulery R | B35: 2012 | C35: https://pubmed.ncbi.nlm.nih.gov/22212513 | D35: =A35&" "&B35 -> Dulery R 2012 | E35: =IF(OR(AND(ISNUMBER(AL35),ISNUMBER(CG35)),AND(ISNUMBER(AM35),ISNUMBER(CH35)),AND(ISNUMBER(AP35),ISNUMBER(AN35),ISNUMBER(AR35),ISNUMBER(CK35),ISNUMBER(CI35),ISNUMBER(CM35)),AND(ISNUMBER(AU35),ISNUMBER(AS35),ISNUMBER(AW35),ISNUMBER(CP35),ISNUMBER(CN35),ISNUMBER(CR35)),AND(ISNUMBER(BB35),ISNUMBER(BC35))),"Yes","No") -> No | AG35: 112 | AU35: 29 | BA35: =IF(ISNUMBER(BQ35),BQ35,IF(AND(ISNUMBER($BJ35),ISNUMBER($BK35)),BI35,"")) | BB35: =IF(ISNUMBER(BR35),BR35,IF(AND(ISNUMBER($BJ35),ISNUMBER($BK35)),BJ35,"")) | BC35: =IF(ISNUMBER(BS35),BS35,IF(AND(ISNUMBER($BJ35),ISNUMBER($BK35)),BK35,"")) | BD35: =IF(ISNUMBER(BT35),BT35,IF(AND(ISNUMBER($BO35),ISNUMBER($BP35)),BN35,"")) | BE35: =IF(ISNUMBER(BU35),BU35,IF(AND(ISNUMBER($BO35),ISNUMBER($BP35)),BO35,"")) | BF35: =IF(ISNUMBER(BV35),BV35,IF(AND(ISNUMBER($BO35),ISNUMBER($BP35)),BP35,"")) | BJ35: =IF(AND(ISNUMBER(BG35),ISNUMBER(BH35),ISNUMBER(BI35)),EXP(LOG(BI35)-1.96*SQRT((1/BG35)+(1/BH35))),"") | BK35: =IF(AND(ISNUMBER(BG35),ISNUMBER(BH35),ISNUMBER(BI35)),EXP(LOG(BI35)+1.96*SQRT((1/BG35)+(1/BH35))),"") | BL35: Unclear | BM35: Unclear | BN35: =CP35/AU35 -> 0.75862069 | BO35: =IF(AND(ISNUMBER(BL35),ISNUMBER(BM35),ISNUMBER(BN35)),EXP(LOG(BN35)-1.96*SQRT((1/BL35)+(1/BM35))),"") | BP35: =IF(AND(ISNUMBER(BL35),ISNUMBER(BM35),ISNUMBER(BN35)),EXP(LOG(BN35)+1.96*SQRT((1/BL35)+(1/BM35))),"") | BT35: See note | BU35: see note | BV35: see note | CC35: 123 | CP35: 22 | CX35: Has HR for platelet, but inverts the conventional direction so that >1 corresponds to delay
A36: Fule Robles JD | B36: 2014 | C36: https://pubmed.ncbi.nlm.nih.gov/24881673 | D36: =A36&" "&B36 -> Fule Robles JD 2014 | E36: =IF(OR(AND(ISNUMBER(AL36),ISNUMBER(CG36)),AND(ISNUMBER(AM36),ISNUMBER(CH36)),AND(ISNUMBER(AP36),ISNUMBER(AN36),ISNUMBER(AR36),ISNUMBER(CK36),ISNUMBER(CI36),ISNUMBER(CM36)),AND(ISNUMBER(AU36),ISNUMBER(AS36),ISNUMBER(AW36),ISNUMBER(CP36),ISNUMBER(CN36),ISNUMBER(CR36)),AND(ISNUMBER(BB36),ISNUMBER(BC36))),"Yes","No") -> No | BA36: =IF(ISNUMBER(BQ36),BQ36,IF(AND(ISNUMBER($BJ36),ISNUMBER($BK36)),BI36,"")) | BB36: =IF(ISNUMBER(BR36),BR36,IF(AND(ISNUMBER($BJ36),ISNUMBER($BK36)),BJ36,"")) | BC36: =IF(ISNUMBER(BS36),BS36,IF(AND(ISNUMBER($BJ36),ISNUMBER($BK36)),BK36,"")) | BD36: =IF(ISNUMBER(BT36),BT36,IF(AND(ISNUMBER($BO36),ISNUMBER($BP36)),BN36,"")) | BE36: =IF(ISNUMBER(BU36),BU36,IF(AND(ISNUMBER($BO36),ISNUMBER($BP36)),BO36,"")) | BF36: =IF(ISNUMBER(BV36),BV36,IF(AND(ISNUMBER($BO36),ISNUMBER($BP36)),BP36,"")) | BJ36: =IF(AND(ISNUMBER(BG36),ISNUMBER(BH36),ISNUMBER(BI36)),EXP(LOG(BI36)-1.96*SQRT((1/BG36)+(1/BH36))),"") | BK36: =IF(AND(ISNUMBER(BG36),ISNUMBER(BH36),ISNUMBER(BI36)),EXP(LOG(BI36)+1.96*SQRT((1/BG36)+(1/BH36))),"") | BO36: =IF(AND(ISNUMBER(BL36),ISNUMBER(BM36),ISNUMBER(BN36)),EXP(LOG(BN36)-1.96*SQRT((1/BL36)+(1/BM36))),"") | BP36: =IF(AND(ISNUMBER(BL36),ISNUMBER(BM36),ISNUMBER(BN36)),EXP(LOG(BN36)+1.96*SQRT((1/BL36)+(1/BM36))),"")
A37: Gasior M | B37: 2021 | C37: https://pubmed.ncbi.nlm.nih.gov/33713461 | D37: =A37&" "&B37 -> Gasior M 2021 | E37: =IF(OR(AND(ISNUMBER(AL37),ISNUMBER(CG37)),AND(ISNUMBER(AM37),ISNUMBER(CH37)),AND(ISNUMBER(AP37),ISNUMBER(AN37),ISNUMBER(AR37),ISNUMBER(CK37),ISNUMBER(CI37),ISNUMBER(CM37)),AND(ISNUMBER(AU37),ISNUMBER(AS37),ISNUMBER(AW37),ISNUMBER(CP37),ISNUMBER(CN37),ISNUMBER(CR37)),AND(ISNUMBER(BB37),ISNUMBER(BC37))),"Yes","No") -> No | BA37: =IF(ISNUMBER(BQ37),BQ37,IF(AND(ISNUMBER($BJ37),ISNUMBER($BK37)),BI37,"")) | BB37: =IF(ISNUMBER(BR37),BR37,IF(AND(ISNUMBER($BJ37),ISNUMBER($BK37)),BJ37,"")) | BC37: =IF(ISNUMBER(BS37),BS37,IF(AND(ISNUMBER($BJ37),ISNUMBER($BK37)),BK37,"")) | BD37: =IF(ISNUMBER(BT37),BT37,IF(AND(ISNUMBER($BO37),ISNUMBER($BP37)),BN37,"")) | BE37: =IF(ISNUMBER(BU37),BU37,IF(AND(ISNUMBER($BO37),ISNUMBER($BP37)),BO37,"")) | BF37: =IF(ISNUMBER(BV37),BV37,IF(AND(ISNUMBER($BO37),ISNUMBER($BP37)),BP37,"")) | BJ37: =IF(AND(ISNUMBER(BG37),ISNUMBER(BH37),ISNUMBER(BI37)),EXP(LOG(BI37)-1.96*SQRT((1/BG37)+(1/BH37))),"") | BK37: =IF(AND(ISNUMBER(BG37),ISNUMBER(BH37),ISNUMBER(BI37)),EXP(LOG(BI37)+1.96*SQRT((1/BG37)+(1/BH37))),"") | BO37: =IF(AND(ISNUMBER(BL37),ISNUMBER(BM37),ISNUMBER(BN37)),EXP(LOG(BN37)-1.96*SQRT((1/BL37)+(1/BM37))),"") | BP37: =IF(AND(ISNUMBER(BL37),ISNUMBER(BM37),ISNUMBER(BN37)),EXP(LOG(BN37)+1.96*SQRT((1/BL37)+(1/BM37))),"")
A38: Gotoh M | B38: 2014 | C38: https://pubmed.ncbi.nlm.nih.gov/24810656 | D38: =A38&" "&B38 -> Gotoh M 2014 | E38: =IF(OR(AND(ISNUMBER(AL38),ISNUMBER(CG38)),AND(ISNUMBER(AM38),ISNUMBER(CH38)),AND(ISNUMBER(AP38),ISNUMBER(AN38),ISNUMBER(AR38),ISNUMBER(CK38),ISNUMBER(CI38),ISNUMBER(CM38)),AND(ISNUMBER(AU38),ISNUMBER(AS38),ISNUMBER(AW38),ISNUMBER(CP38),ISNUMBER(CN38),ISNUMBER(CR38)),AND(ISNUMBER(BB38),ISNUMBER(BC38))),"Yes","No") -> No | F38: 49 | M38: 31 | N38: 10 | O38: 8 | AF38: 49 | AG38: 26 | AL38: Zero in both groups, precluding analysis | BA38: =IF(ISNUMBER(BQ38),BQ38,IF(AND(ISNUMBER($BJ38),ISNUMBER($BK38)),BI38,"")) | BB38: =IF(ISNUMBER(BR38),BR38,IF(AND(ISNUMBER($BJ38),ISNUMBER($BK38)),BJ38,"")) | BC38: =IF(ISNUMBER(BS38),BS38,IF(AND(ISNUMBER($BJ38),ISNUMBER($BK38)),BK38,"")) | BD38: =IF(ISNUMBER(BT38),BT38,IF(AND(ISNUMBER($BO38),ISNUMBER($BP38)),BN38,"")) | BE38: =IF(ISNUMBER(BU38),BU38,IF(AND(ISNUMBER($BO38),ISNUMBER($BP38)),BO38,"")) | BF38: =IF(ISNUMBER(BV38),BV38,IF(AND(ISNUMBER($BO38),ISNUMBER($BP38)),BP38,"")) | BJ38: =IF(AND(ISNUMBER(BG38),ISNUMBER(BH38),ISNUMBER(BI38)),EXP(LOG(BI38)-1.96*SQRT((1/BG38)+(1/BH38))),"") | BK38: =IF(AND(ISNUMBER(BG38),ISNUMBER(BH38),ISNUMBER(BI38)),EXP(LOG(BI38)+1.96*SQRT((1/BG38)+(1/BH38))),"") | BO38: =IF(AND(ISNUMBER(BL38),ISNUMBER(BM38),ISNUMBER(BN38)),EXP(LOG(BN38)-1.96*SQRT((1/BL38)+(1/BM38))),"") | BP38: =IF(AND(ISNUMBER(BL38),ISNUMBER(BM38),ISNUMBER(BN38)),EXP(LOG(BN38)+1.96*SQRT((1/BL38)+(1/BM38))),"") | CC38: =AF38-AG38 -> 23 | CG38: Zero in both groups, precluding analysis
A39: Greco R | B39: 2016 | C39: https://pubmed.ncbi.nlm.nih.gov/27697585 | D39: =A39&" "&B39 -> Greco R 2016 | E39: =IF(OR(AND(ISNUMBER(AL39),ISNUMBER(CG39)),AND(ISNUMBER(AM39),ISNUMBER(CH39)),AND(ISNUMBER(AP39),ISNUMBER(AN39),ISNUMBER(AR39),ISNUMBER(CK39),ISNUMBER(CI39),ISNUMBER(CM39)),AND(ISNUMBER(AU39),ISNUMBER(AS39),ISNUMBER(AW39),ISNUMBER(CP39),ISNUMBER(CN39),ISNUMBER(CR39)),AND(ISNUMBER(BB39),ISNUMBER(BC39))),"Yes","No") -> No | BA39: =IF(ISNUMBER(BQ39),BQ39,IF(AND(ISNUMBER($BJ39),ISNUMBER($BK39)),BI39,"")) | BB39: =IF(ISNUMBER(BR39),BR39,IF(AND(ISNUMBER($BJ39),ISNUMBER($BK39)),BJ39,"")) | BC39: =IF(ISNUMBER(BS39),BS39,IF(AND(ISNUMBER($BJ39),ISNUMBER($BK39)),BK39,"")) | BD39: =IF(ISNUMBER(BT39),BT39,IF(AND(ISNUMBER($BO39),ISNUMBER($BP39)),BN39,"")) | BE39: =IF(ISNUMBER(BU39),BU39,IF(AND(ISNUMBER($BO39),ISNUMBER($BP39)),BO39,"")) | BF39: =IF(ISNUMBER(BV39),BV39,IF(AND(ISNUMBER($BO39),ISNUMBER($BP39)),BP39,"")) | BJ39: =IF(AND(ISNUMBER(BG39),ISNUMBER(BH39),ISNUMBER(BI39)),EXP(LOG(BI39)-1.96*SQRT((1/BG39)+(1/BH39))),"") | BK39: =IF(AND(ISNUMBER(BG39),ISNUMBER(BH39),ISNUMBER(BI39)),EXP(LOG(BI39)+1.96*SQRT((1/BG39)+(1/BH39))),"") | BO39: =IF(AND(ISNUMBER(BL39),ISNUMBER(BM39),ISNUMBER(BN39)),EXP(LOG(BN39)-1.96*SQRT((1/BL39)+(1/BM39))),"") | BP39: =IF(AND(ISNUMBER(BL39),ISNUMBER(BM39),ISNUMBER(BN39)),EXP(LOG(BN39)+1.96*SQRT((1/BL39)+(1/BM39))),"")
A40: Hill JA | B40: 2024 | C40: https://pubmed.ncbi.nlm.nih.gov/38228644 | D40: =A40&" "&B40 -> Hill JA 2024 | E40: =IF(OR(AND(ISNUMBER(AL40),ISNUMBER(CG40)),AND(ISNUMBER(AM40),ISNUMBER(CH40)),AND(ISNUMBER(AP40),ISNUMBER(AN40),ISNUMBER(AR40),ISNUMBER(CK40),ISNUMBER(CI40),ISNUMBER(CM40)),AND(ISNUMBER(AU40),ISNUMBER(AS40),ISNUMBER(AW40),ISNUMBER(CP40),ISNUMBER(CN40),ISNUMBER(CR40)),AND(ISNUMBER(BB40),ISNUMBER(BC40))),"Yes","No") -> No | BA40: =IF(ISNUMBER(BQ40),BQ40,IF(AND(ISNUMBER($BJ40),ISNUMBER($BK40)),BI40,"")) | BB40: =IF(ISNUMBER(BR40),BR40,IF(AND(ISNUMBER($BJ40),ISNUMBER($BK40)),BJ40,"")) | BC40: =IF(ISNUMBER(BS40),BS40,IF(AND(ISNUMBER($BJ40),ISNUMBER($BK40)),BK40,"")) | BD40: =IF(ISNUMBER(BT40),BT40,IF(AND(ISNUMBER($BO40),ISNUMBER($BP40)),BN40,"")) | BE40: =IF(ISNUMBER(BU40),BU40,IF(AND(ISNUMBER($BO40),ISNUMBER($BP40)),BO40,"")) | BF40: =IF(ISNUMBER(BV40),BV40,IF(AND(ISNUMBER($BO40),ISNUMBER($BP40)),BP40,"")) | BJ40: =IF(AND(ISNUMBER(BG40),ISNUMBER(BH40),ISNUMBER(BI40)),EXP(LOG(BI40)-1.96*SQRT((1/BG40)+(1/BH40))),"") | BK40: =IF(AND(ISNUMBER(BG40),ISNUMBER(BH40),ISNUMBER(BI40)),EXP(LOG(BI40)+1.96*SQRT((1/BG40)+(1/BH40))),"") | BO40: =IF(AND(ISNUMBER(BL40),ISNUMBER(BM40),ISNUMBER(BN40)),EXP(LOG(BN40)-1.96*SQRT((1/BL40)+(1/BM40))),"") | BP40: =IF(AND(ISNUMBER(BL40),ISNUMBER(BM40),ISNUMBER(BN40)),EXP(LOG(BN40)+1.96*SQRT((1/BL40)+(1/BM40))),"")
A41: Hill JA | B41: 2018 | C41: https://pubmed.ncbi.nlm.nih.gov/29020348 | D41: =A41&" "&B41 -> Hill JA 2018 | E41: =IF(OR(AND(ISNUMBER(AL41),ISNUMBER(CG41)),AND(ISNUMBER(AM41),ISNUMBER(CH41)),AND(ISNUMBER(AP41),ISNUMBER(AN41),ISNUMBER(AR41),ISNUMBER(CK41),ISNUMBER(CI41),ISNUMBER(CM41)),AND(ISNUMBER(AU41),ISNUMBER(AS41),ISNUMBER(AW41),ISNUMBER(CP41),ISNUMBER(CN41),ISNUMBER(CR41)),AND(ISNUMBER(BB41),ISNUMBER(BC41))),"Yes","No") -> No | BA41: =IF(ISNUMBER(BQ41),BQ41,IF(AND(ISNUMBER($BJ41),ISNUMBER($BK41)),BI41,"")) | BB41: =IF(ISNUMBER(BR41),BR41,IF(AND(ISNUMBER($BJ41),ISNUMBER($BK41)),BJ41,"")) | BC41: =IF(ISNUMBER(BS41),BS41,IF(AND(ISNUMBER($BJ41),ISNUMBER($BK41)),BK41,"")) | BD41: =IF(ISNUMBER(BT41),BT41,IF(AND(ISNUMBER($BO41),ISNUMBER($BP41)),BN41,"")) | BE41: =IF(ISNUMBER(BU41),BU41,IF(AND(ISNUMBER($BO41),ISNUMBER($BP41)),BO41,"")) | BF41: =IF(ISNUMBER(BV41),BV41,IF(AND(ISNUMBER($BO41),ISNUMBER($BP41)),BP41,"")) | BJ41: =IF(AND(ISNUMBER(BG41),ISNUMBER(BH41),ISNUMBER(BI41)),EXP(LOG(BI41)-1.96*SQRT((1/BG41)+(1/BH41))),"") | BK41: =IF(AND(ISNUMBER(BG41),ISNUMBER(BH41),ISNUMBER(BI41)),EXP(LOG(BI41)+1.96*SQRT((1/BG41)+(1/BH41))),"") | BO41: =IF(AND(ISNUMBER(BL41),ISNUMBER(BM41),ISNUMBER(BN41)),EXP(LOG(BN41)-1.96*SQRT((1/BL41)+(1/BM41))),"") | BP41: =IF(AND(ISNUMBER(BL41),ISNUMBER(BM41),ISNUMBER(BN41)),EXP(LOG(BN41)+1.96*SQRT((1/BL41)+(1/BM41))),"")
A42: Iesato K | B42: 2018 | C42: https://pubmed.ncbi.nlm.nih.gov/29542206 | D42: =A42&" "&B42 -> Iesato K 2018 | E42: =IF(OR(AND(ISNUMBER(AL42),ISNUMBER(CG42)),AND(ISNUMBER(AM42),ISNUMBER(CH42)),AND(ISNUMBER(AP42),ISNUMBER(AN42),ISNUMBER(AR42),ISNUMBER(CK42),ISNUMBER(CI42),ISNUMBER(CM42)),AND(ISNUMBER(AU42),ISNUMBER(AS42),ISNUMBER(AW42),ISNUMBER(CP42),ISNUMBER(CN42),ISNUMBER(CR42)),AND(ISNUMBER(BB42),ISNUMBER(BC42))),"Yes","No") -> No | AG42: 63 | AP42: 18 | AU42: 41 | BA42: =IF(ISNUMBER(BQ42),BQ42,IF(AND(ISNUMBER($BJ42),ISNUMBER($BK42)),BI42,"")) | BB42: =IF(ISNUMBER(BR42),BR42,IF(AND(ISNUMBER($BJ42),ISNUMBER($BK42)),BJ42,"")) | BC42: =IF(ISNUMBER(BS42),BS42,IF(AND(ISNUMBER($BJ42),ISNUMBER($BK42)),BK42,"")) | BD42: =IF(ISNUMBER(BT42),BT42,IF(AND(ISNUMBER($BO42),ISNUMBER($BP42)),BN42,"")) | BE42: =IF(ISNUMBER(BU42),BU42,IF(AND(ISNUMBER($BO42),ISNUMBER($BP42)),BO42,"")) | BF42: =IF(ISNUMBER(BV42),BV42,IF(AND(ISNUMBER($BO42),ISNUMBER($BP42)),BP42,"")) | BG42: Unclear | BH42: Unclear | BI42: =CK42/AP42 -> 0.88888889 | BJ42: =IF(AND(ISNUMBER(BG42),ISNUMBER(BH42),ISNUMBER(BI42)),EXP(LOG(BI42)-1.96*SQRT((1/BG42)+(1/BH42))),"") | BK42: =IF(AND(ISNUMBER(BG42),ISNUMBER(BH42),ISNUMBER(BI42)),EXP(LOG(BI42)+1.96*SQRT((1/BG42)+(1/BH42))),"") | BL42: Unclear | BM42: Unclear | BN42: =CP42/AU42 -> 0.87804878 | BO42: =IF(AND(ISNUMBER(BL42),ISNUMBER(BM42),ISNUMBER(BN42)),EXP(LOG(BN42)-1.96*SQRT((1/BL42)+(1/BM42))),"") | BP42: =IF(AND(ISNUMBER(BL42),ISNUMBER(BM42),ISNUMBER(BN42)),EXP(LOG(BN42)+1.96*SQRT((1/BL42)+(1/BM42))),"") | CC42: =105-AG42 -> 42 | CK42: 16 | CP42: 36 | CX42: Median is inferred here. Engraftment is not explicilty given as the median, but in context I think this is a reasonable assumption (no averages are given in the paper, only medians)
A43: Iino M | B43: 2021 | C43: https://pubmed.ncbi.nlm.nih.gov/33308840 | D43: =A43&" "&B43 -> Iino M 2021 | E43: =IF(OR(AND(ISNUMBER(AL43),ISNUMBER(CG43)),AND(ISNUMBER(AM43),ISNUMBER(CH43)),AND(ISNUMBER(AP43),ISNUMBER(AN43),ISNUMBER(AR43),ISNUMBER(CK43),ISNUMBER(CI43),ISNUMBER(CM43)),AND(ISNUMBER(AU43),ISNUMBER(AS43),ISNUMBER(AW43),ISNUMBER(CP43),ISNUMBER(CN43),ISNUMBER(CR43)),AND(ISNUMBER(BB43),ISNUMBER(BC43))),"Yes","No") -> No | BA43: =IF(ISNUMBER(BQ43),BQ43,IF(AND(ISNUMBER($BJ43),ISNUMBER($BK43)),BI43,"")) | BB43: =IF(ISNUMBER(BR43),BR43,IF(AND(ISNUMBER($BJ43),ISNUMBER($BK43)),BJ43,"")) | BC43: =IF(ISNUMBER(BS43),BS43,IF(AND(ISNUMBER($BJ43),ISNUMBER($BK43)),BK43,"")) | BD43: =IF(ISNUMBER(BT43),BT43,IF(AND(ISNUMBER($BO43),ISNUMBER($BP43)),BN43,"")) | BE43: =IF(ISNUMBER(BU43),BU43,IF(AND(ISNUMBER($BO43),ISNUMBER($BP43)),BO43,"")) | BF43: =IF(ISNUMBER(BV43),BV43,IF(AND(ISNUMBER($BO43),ISNUMBER($BP43)),BP43,"")) | BJ43: =IF(AND(ISNUMBER(BG43),ISNUMBER(BH43),ISNUMBER(BI43)),EXP(LOG(BI43)-1.96*SQRT((1/BG43)+(1/BH43))),"") | BK43: =IF(AND(ISNUMBER(BG43),ISNUMBER(BH43),ISNUMBER(BI43)),EXP(LOG(BI43)+1.96*SQRT((1/BG43)+(1/BH43))),"") | BO43: =IF(AND(ISNUMBER(BL43),ISNUMBER(BM43),ISNUMBER(BN43)),EXP(LOG(BN43)-1.96*SQRT((1/BL43)+(1/BM43))),"") | BP43: =IF(AND(ISNUMBER(BL43),ISNUMBER(BM43),ISNUMBER(BN43)),EXP(LOG(BN43)+1.96*SQRT((1/BL43)+(1/BM43))),"")
A44: Illiaquer M | B44: 2014 | C44: https://pubmed.ncbi.nlm.nih.gov/24596281 | D44: =A44&" "&B44 -> Illiaquer M 2014 | E44: =IF(OR(AND(ISNUMBER(AL44),ISNUMBER(CG44)),AND(ISNUMBER(AM44),ISNUMBER(CH44)),AND(ISNUMBER(AP44),ISNUMBER(AN44),ISNUMBER(AR44),ISNUMBER(CK44),ISNUMBER(CI44),ISNUMBER(CM44)),AND(ISNUMBER(AU44),ISNUMBER(AS44),ISNUMBER(AW44),ISNUMBER(CP44),ISNUMBER(CN44),ISNUMBER(CR44)),AND(ISNUMBER(BB44),ISNUMBER(BC44))),"Yes","No") -> No | BA44: =IF(ISNUMBER(BQ44),BQ44,IF(AND(ISNUMBER($BJ44),ISNUMBER($BK44)),BI44,"")) | BB44: =IF(ISNUMBER(BR44),BR44,IF(AND(ISNUMBER($BJ44),ISNUMBER($BK44)),BJ44,"")) | BC44: =IF(ISNUMBER(BS44),BS44,IF(AND(ISNUMBER($BJ44),ISNUMBER($BK44)),BK44,"")) | BD44: =IF(ISNUMBER(BT44),BT44,IF(AND(ISNUMBER($BO44),ISNUMBER($BP44)),BN44,"")) | BE44: =IF(ISNUMBER(BU44),BU44,IF(AND(ISNUMBER($BO44),ISNUMBER($BP44)),BO44,"")) | BF44: =IF(ISNUMBER(BV44),BV44,IF(AND(ISNUMBER($BO44),ISNUMBER($BP44)),BP44,"")) | BJ44: =IF(AND(ISNUMBER(BG44),ISNUMBER(BH44),ISNUMBER(BI44)),EXP(LOG(BI44)-1.96*SQRT((1/BG44)+(1/BH44))),"") | BK44: =IF(AND(ISNUMBER(BG44),ISNUMBER(BH44),ISNUMBER(BI44)),EXP(LOG(BI44)+1.96*SQRT((1/BG44)+(1/BH44))),"") | BO44: =IF(AND(ISNUMBER(BL44),ISNUMBER(BM44),ISNUMBER(BN44)),EXP(LOG(BN44)-1.96*SQRT((1/BL44)+(1/BM44))),"") | BP44: =IF(AND(ISNUMBER(BL44),ISNUMBER(BM44),ISNUMBER(BN44)),EXP(LOG(BN44)+1.96*SQRT((1/BL44)+(1/BM44))),"")
A45: Illiaquer M | B45: 2017 | C45: https://pubmed.ncbi.nlm.nih.gov/28601677 | D45: =A45&" "&B45 -> Illiaquer M 2017 | E45: =IF(OR(AND(ISNUMBER(AL45),ISNUMBER(CG45)),AND(ISNUMBER(AM45),ISNUMBER(CH45)),AND(ISNUMBER(AP45),ISNUMBER(AN45),ISNUMBER(AR45),ISNUMBER(CK45),ISNUMBER(CI45),ISNUMBER(CM45)),AND(ISNUMBER(AU45),ISNUMBER(AS45),ISNUMBER(AW45),ISNUMBER(CP45),ISNUMBER(CN45),ISNUMBER(CR45)),AND(ISNUMBER(BB45),ISNUMBER(BC45))),"Yes","No") -> No | BA45: =IF(ISNUMBER(BQ45),BQ45,IF(AND(ISNUMBER($BJ45),ISNUMBER($BK45)),BI45,"")) | BB45: =IF(ISNUMBER(BR45),BR45,IF(AND(ISNUMBER($BJ45),ISNUMBER($BK45)),BJ45,"")) | BC45: =IF(ISNUMBER(BS45),BS45,IF(AND(ISNUMBER($BJ45),ISNUMBER($BK45)),BK45,"")) | BD45: =IF(ISNUMBER(BT45),BT45,IF(AND(ISNUMBER($BO45),ISNUMBER($BP45)),BN45,"")) | BE45: =IF(ISNUMBER(BU45),BU45,IF(AND(ISNUMBER($BO45),ISNUMBER($BP45)),BO45,"")) | BF45: =IF(ISNUMBER(BV45),BV45,IF(AND(ISNUMBER($BO45),ISNUMBER($BP45)),BP45,"")) | BJ45: =IF(AND(ISNUMBER(BG45),ISNUMBER(BH45),ISNUMBER(BI45)),EXP(LOG(BI45)-1.96*SQRT((1/BG45)+(1/BH45))),"") | BK45: =IF(AND(ISNUMBER(BG45),ISNUMBER(BH45),ISNUMBER(BI45)),EXP(LOG(BI45)+1.96*SQRT((1/BG45)+(1/BH45))),"") | BO45: =IF(AND(ISNUMBER(BL45),ISNUMBER(BM45),ISNUMBER(BN45)),EXP(LOG(BN45)-1.96*SQRT((1/BL45)+(1/BM45))),"") | BP45: =IF(AND(ISNUMBER(BL45),ISNUMBER(BM45),ISNUMBER(BN45)),EXP(LOG(BN45)+1.96*SQRT((1/BL45)+(1/BM45))),"")
A46: Imbert-Marcille BM | B46: 2000 | C46: https://pubmed.ncbi.nlm.nih.gov/11049765 | D46: =A46&" "&B46 -> Imbert-Marcille BM 2000 | E46: =IF(OR(AND(ISNUMBER(AL46),ISNUMBER(CG46)),AND(ISNUMBER(AM46),ISNUMBER(CH46)),AND(ISNUMBER(AP46),ISNUMBER(AN46),ISNUMBER(AR46),ISNUMBER(CK46),ISNUMBER(CI46),ISNUMBER(CM46)),AND(ISNUMBER(AU46),ISNUMBER(AS46),ISNUMBER(AW46),ISNUMBER(CP46),ISNUMBER(CN46),ISNUMBER(CR46)),AND(ISNUMBER(BB46),ISNUMBER(BC46))),"Yes","No") -> No | AG46: 39 | BA46: =IF(ISNUMBER(BQ46),BQ46,IF(AND(ISNUMBER($BJ46),ISNUMBER($BK46)),BI46,"")) | BB46: =IF(ISNUMBER(BR46),BR46,IF(AND(ISNUMBER($BJ46),ISNUMBER($BK46)),BJ46,"")) | BC46: =IF(ISNUMBER(BS46),BS46,IF(AND(ISNUMBER($BJ46),ISNUMBER($BK46)),BK46,"")) | BD46: =IF(ISNUMBER(BT46),BT46,IF(AND(ISNUMBER($BO46),ISNUMBER($BP46)),BN46,"")) | BE46: =IF(ISNUMBER(BU46),BU46,IF(AND(ISNUMBER($BO46),ISNUMBER($BP46)),BO46,"")) | BF46: =IF(ISNUMBER(BV46),BV46,IF(AND(ISNUMBER($BO46),ISNUMBER($BP46)),BP46,"")) | BJ46: =IF(AND(ISNUMBER(BG46),ISNUMBER(BH46),ISNUMBER(BI46)),EXP(LOG(BI46)-1.96*SQRT((1/BG46)+(1/BH46))),"") | BK46: =IF(AND(ISNUMBER(BG46),ISNUMBER(BH46),ISNUMBER(BI46)),EXP(LOG(BI46)+1.96*SQRT((1/BG46)+(1/BH46))),"") | BO46: =IF(AND(ISNUMBER(BL46),ISNUMBER(BM46),ISNUMBER(BN46)),EXP(LOG(BN46)-1.96*SQRT((1/BL46)+(1/BM46))),"") | BP46: =IF(AND(ISNUMBER(BL46),ISNUMBER(BM46),ISNUMBER(BN46)),EXP(LOG(BN46)+1.96*SQRT((1/BL46)+(1/BM46))),"") | CC46: 53
A47: Jeulin H | B47: 2013 | C47: https://pubmed.ncbi.nlm.nih.gov/23514960 | D47: =A47&" "&B47 -> Jeulin H 2013 | E47: =IF(OR(AND(ISNUMBER(AL47),ISNUMBER(CG47)),AND(ISNUMBER(AM47),ISNUMBER(CH47)),AND(ISNUMBER(AP47),ISNUMBER(AN47),ISNUMBER(AR47),ISNUMBER(CK47),ISNUMBER(CI47),ISNUMBER(CM47)),AND(ISNUMBER(AU47),ISNUMBER(AS47),ISNUMBER(AW47),ISNUMBER(CP47),ISNUMBER(CN47),ISNUMBER(CR47)),AND(ISNUMBER(BB47),ISNUMBER(BC47))),"Yes","No") -> No | BA47: =IF(ISNUMBER(BQ47),BQ47,IF(AND(ISNUMBER($BJ47),ISNUMBER($BK47)),BI47,"")) | BB47: =IF(ISNUMBER(BR47),BR47,IF(AND(ISNUMBER($BJ47),ISNUMBER($BK47)),BJ47,"")) | BC47: =IF(ISNUMBER(BS47),BS47,IF(AND(ISNUMBER($BJ47),ISNUMBER($BK47)),BK47,"")) | BD47: =IF(ISNUMBER(BT47),BT47,IF(AND(ISNUMBER($BO47),ISNUMBER($BP47)),BN47,"")) | BE47: =IF(ISNUMBER(BU47),BU47,IF(AND(ISNUMBER($BO47),ISNUMBER($BP47)),BO47,"")) | BF47: =IF(ISNUMBER(BV47),BV47,IF(AND(ISNUMBER($BO47),ISNUMBER($BP47)),BP47,"")) | BJ47: =IF(AND(ISNUMBER(BG47),ISNUMBER(BH47),ISNUMBER(BI47)),EXP(LOG(BI47)-1.96*SQRT((1/BG47)+(1/BH47))),"") | BK47: =IF(AND(ISNUMBER(BG47),ISNUMBER(BH47),ISNUMBER(BI47)),EXP(LOG(BI47)+1.96*SQRT((1/BG47)+(1/BH47))),"") | BO47: =IF(AND(ISNUMBER(BL47),ISNUMBER(BM47),ISNUMBER(BN47)),EXP(LOG(BN47)-1.96*SQRT((1/BL47)+(1/BM47))),"") | BP47: =IF(AND(ISNUMBER(BL47),ISNUMBER(BM47),ISNUMBER(BN47)),EXP(LOG(BN47)+1.96*SQRT((1/BL47)+(1/BM47))),"")
A48: Kadakia MP | B48: 1996 | C48: https://pubmed.ncbi.nlm.nih.gov/8652850 | D48: =A48&" "&B48 -> Kadakia MP 1996 | E48: =IF(OR(AND(ISNUMBER(AL48),ISNUMBER(CG48)),AND(ISNUMBER(AM48),ISNUMBER(CH48)),AND(ISNUMBER(AP48),ISNUMBER(AN48),ISNUMBER(AR48),ISNUMBER(CK48),ISNUMBER(CI48),ISNUMBER(CM48)),AND(ISNUMBER(AU48),ISNUMBER(AS48),ISNUMBER(AW48),ISNUMBER(CP48),ISNUMBER(CN48),ISNUMBER(CR48)),AND(ISNUMBER(BB48),ISNUMBER(BC48))),"Yes","No") -> No | AG48: 12 | AP48: 17 | AU48: 58 | BA48: =IF(ISNUMBER(BQ48),BQ48,IF(AND(ISNUMBER($BJ48),ISNUMBER($BK48)),BI48,"")) | BB48: =IF(ISNUMBER(BR48),BR48,IF(AND(ISNUMBER($BJ48),ISNUMBER($BK48)),BJ48,"")) | BC48: =IF(ISNUMBER(BS48),BS48,IF(AND(ISNUMBER($BJ48),ISNUMBER($BK48)),BK48,"")) | BD48: =IF(ISNUMBER(BT48),BT48,IF(AND(ISNUMBER($BO48),ISNUMBER($BP48)),BN48,"")) | BE48: =IF(ISNUMBER(BU48),BU48,IF(AND(ISNUMBER($BO48),ISNUMBER($BP48)),BO48,"")) | BF48: =IF(ISNUMBER(BV48),BV48,IF(AND(ISNUMBER($BO48),ISNUMBER($BP48)),BP48,"")) | BG48: Unclear | BH48: Unclear | BI48: =CK48/AP48 -> 0.94117647 | BJ48: =IF(AND(ISNUMBER(BG48),ISNUMBER(BH48),ISNUMBER(BI48)),EXP(LOG(BI48)-1.96*SQRT((1/BG48)+(1/BH48))),"") | BK48: =IF(AND(ISNUMBER(BG48),ISNUMBER(BH48),ISNUMBER(BI48)),EXP(LOG(BI48)+1.96*SQRT((1/BG48)+(1/BH48))),"") | BL48: Unclear | BM48: Unclear | BN48: =CP48/AU48 -> 0.51724138 | BO48: =IF(AND(ISNUMBER(BL48),ISNUMBER(BM48),ISNUMBER(BN48)),EXP(LOG(BN48)-1.96*SQRT((1/BL48)+(1/BM48))),"") | BP48: =IF(AND(ISNUMBER(BL48),ISNUMBER(BM48),ISNUMBER(BN48)),EXP(LOG(BN48)+1.96*SQRT((1/BL48)+(1/BM48))),"") | CC48: =26-AG48 -> 14 | CK48: 16 | CP48: 30
A49: Kageyama K | B49: 2021 | C49: https://pubmed.ncbi.nlm.nih.gov/32782352 | D49: =A49&" "&B49 -> Kageyama K 2021 | E49: =IF(OR(AND(ISNUMBER(AL49),ISNUMBER(CG49)),AND(ISNUMBER(AM49),ISNUMBER(CH49)),AND(ISNUMBER(AP49),ISNUMBER(AN49),ISNUMBER(AR49),ISNUMBER(CK49),ISNUMBER(CI49),ISNUMBER(CM49)),AND(ISNUMBER(AU49),ISNUMBER(AS49),ISNUMBER(AW49),ISNUMBER(CP49),ISNUMBER(CN49),ISNUMBER(CR49)),AND(ISNUMBER(BB49),ISNUMBER(BC49))),"Yes","No") -> No | BA49: =IF(ISNUMBER(BQ49),BQ49,IF(AND(ISNUMBER($BJ49),ISNUMBER($BK49)),BI49,"")) | BB49: =IF(ISNUMBER(BR49),BR49,IF(AND(ISNUMBER($BJ49),ISNUMBER($BK49)),BJ49,"")) | BC49: =IF(ISNUMBER(BS49),BS49,IF(AND(ISNUMBER($BJ49),ISNUMBER($BK49)),BK49,"")) | BD49: =IF(ISNUMBER(BT49),BT49,IF(AND(ISNUMBER($BO49),ISNUMBER($BP49)),BN49,"")) | BE49: =IF(ISNUMBER(BU49),BU49,IF(AND(ISNUMBER($BO49),ISNUMBER($BP49)),BO49,"")) | BF49: =IF(ISNUMBER(BV49),BV49,IF(AND(ISNUMBER($BO49),ISNUMBER($BP49)),BP49,"")) | BJ49: =IF(AND(ISNUMBER(BG49),ISNUMBER(BH49),ISNUMBER(BI49)),EXP(LOG(BI49)-1.96*SQRT((1/BG49)+(1/BH49))),"") | BK49: =IF(AND(ISNUMBER(BG49),ISNUMBER(BH49),ISNUMBER(BI49)),EXP(LOG(BI49)+1.96*SQRT((1/BG49)+(1/BH49))),"") | BO49: =IF(AND(ISNUMBER(BL49),ISNUMBER(BM49),ISNUMBER(BN49)),EXP(LOG(BN49)-1.96*SQRT((1/BL49)+(1/BM49))),"") | BP49: =IF(AND(ISNUMBER(BL49),ISNUMBER(BM49),ISNUMBER(BN49)),EXP(LOG(BN49)+1.96*SQRT((1/BL49)+(1/BM49))),"")
A50: Khimani F | B50: 2021 | C50: https://pubmed.ncbi.nlm.nih.gov/34329754 | D50: =A50&" "&B50 -> Khimani F 2021 | E50: =IF(OR(AND(ISNUMBER(AL50),ISNUMBER(CG50)),AND(ISNUMBER(AM50),ISNUMBER(CH50)),AND(ISNUMBER(AP50),ISNUMBER(AN50),ISNUMBER(AR50),ISNUMBER(CK50),ISNUMBER(CI50),ISNUMBER(CM50)),AND(ISNUMBER(AU50),ISNUMBER(AS50),ISNUMBER(AW50),ISNUMBER(CP50),ISNUMBER(CN50),ISNUMBER(CR50)),AND(ISNUMBER(BB50),ISNUMBER(BC50))),"Yes","No") -> No | BA50: =IF(ISNUMBER(BQ50),BQ50,IF(AND(ISNUMBER($BJ50),ISNUMBER($BK50)),BI50,"")) | BB50: =IF(ISNUMBER(BR50),BR50,IF(AND(ISNUMBER($BJ50),ISNUMBER($BK50)),BJ50,"")) | BC50: =IF(ISNUMBER(BS50),BS50,IF(AND(ISNUMBER($BJ50),ISNUMBER($BK50)),BK50,"")) | BD50: =IF(ISNUMBER(BT50),BT50,IF(AND(ISNUMBER($BO50),ISNUMBER($BP50)),BN50,"")) | BE50: =IF(ISNUMBER(BU50),BU50,IF(AND(ISNUMBER($BO50),ISNUMBER($BP50)),BO50,"")) | BF50: =IF(ISNUMBER(BV50),BV50,IF(AND(ISNUMBER($BO50),ISNUMBER($BP50)),BP50,"")) | BJ50: =IF(AND(ISNUMBER(BG50),ISNUMBER(BH50),ISNUMBER(BI50)),EXP(LOG(BI50)-1.96*SQRT((1/BG50)+(1/BH50))),"") | BK50: =IF(AND(ISNUMBER(BG50),ISNUMBER(BH50),ISNUMBER(BI50)),EXP(LOG(BI50)+1.96*SQRT((1/BG50)+(1/BH50))),"") | BO50: =IF(AND(ISNUMBER(BL50),ISNUMBER(BM50),ISNUMBER(BN50)),EXP(LOG(BN50)-1.96*SQRT((1/BL50)+(1/BM50))),"") | BP50: =IF(AND(ISNUMBER(BL50),ISNUMBER(BM50),ISNUMBER(BN50)),EXP(LOG(BN50)+1.96*SQRT((1/BL50)+(1/BM50))),"")
A51: Laskin BL | B51: 2013 | C51: https://pubmed.ncbi.nlm.nih.gov/23665115 | D51: =A51&" "&B51 -> Laskin BL 2013 | E51: =IF(OR(AND(ISNUMBER(AL51),ISNUMBER(CG51)),AND(ISNUMBER(AM51),ISNUMBER(CH51)),AND(ISNUMBER(AP51),ISNUMBER(AN51),ISNUMBER(AR51),ISNUMBER(CK51),ISNUMBER(CI51),ISNUMBER(CM51)),AND(ISNUMBER(AU51),ISNUMBER(AS51),ISNUMBER(AW51),ISNUMBER(CP51),ISNUMBER(CN51),ISNUMBER(CR51)),AND(ISNUMBER(BB51),ISNUMBER(BC51))),"Yes","No") -> No | BA51: =IF(ISNUMBER(BQ51),BQ51,IF(AND(ISNUMBER($BJ51),ISNUMBER($BK51)),BI51,"")) | BB51: =IF(ISNUMBER(BR51),BR51,IF(AND(ISNUMBER($BJ51),ISNUMBER($BK51)),BJ51,"")) | BC51: =IF(ISNUMBER(BS51),BS51,IF(AND(ISNUMBER($BJ51),ISNUMBER($BK51)),BK51,"")) | BD51: =IF(ISNUMBER(BT51),BT51,IF(AND(ISNUMBER($BO51),ISNUMBER($BP51)),BN51,"")) | BE51: =IF(ISNUMBER(BU51),BU51,IF(AND(ISNUMBER($BO51),ISNUMBER($BP51)),BO51,"")) | BF51: =IF(ISNUMBER(BV51),BV51,IF(AND(ISNUMBER($BO51),ISNUMBER($BP51)),BP51,"")) | BJ51: =IF(AND(ISNUMBER(BG51),ISNUMBER(BH51),ISNUMBER(BI51)),EXP(LOG(BI51)-1.96*SQRT((1/BG51)+(1/BH51))),"") | BK51: =IF(AND(ISNUMBER(BG51),ISNUMBER(BH51),ISNUMBER(BI51)),EXP(LOG(BI51)+1.96*SQRT((1/BG51)+(1/BH51))),"") | BO51: =IF(AND(ISNUMBER(BL51),ISNUMBER(BM51),ISNUMBER(BN51)),EXP(LOG(BN51)-1.96*SQRT((1/BL51)+(1/BM51))),"") | BP51: =IF(AND(ISNUMBER(BL51),ISNUMBER(BM51),ISNUMBER(BN51)),EXP(LOG(BN51)+1.96*SQRT((1/BL51)+(1/BM51))),"")
A52: Lee DG | B52: 2003 | C52: https://pubmed.ncbi.nlm.nih.gov/14744020 | D52: =A52&" "&B52 -> Lee DG 2003 | E52: =IF(OR(AND(ISNUMBER(AL52),ISNUMBER(CG52)),AND(ISNUMBER(AM52),ISNUMBER(CH52)),AND(ISNUMBER(AP52),ISNUMBER(AN52),ISNUMBER(AR52),ISNUMBER(CK52),ISNUMBER(CI52),ISNUMBER(CM52)),AND(ISNUMBER(AU52),ISNUMBER(AS52),ISNUMBER(AW52),ISNUMBER(CP52),ISNUMBER(CN52),ISNUMBER(CR52)),AND(ISNUMBER(BB52),ISNUMBER(BC52))),"Yes","No") -> No | BA52: =IF(ISNUMBER(BQ52),BQ52,IF(AND(ISNUMBER($BJ52),ISNUMBER($BK52)),BI52,"")) | BB52: =IF(ISNUMBER(BR52),BR52,IF(AND(ISNUMBER($BJ52),ISNUMBER($BK52)),BJ52,"")) | BC52: =IF(ISNUMBER(BS52),BS52,IF(AND(ISNUMBER($BJ52),ISNUMBER($BK52)),BK52,"")) | BD52: =IF(ISNUMBER(BT52),BT52,IF(AND(ISNUMBER($BO52),ISNUMBER($BP52)),BN52,"")) | BE52: =IF(ISNUMBER(BU52),BU52,IF(AND(ISNUMBER($BO52),ISNUMBER($BP52)),BO52,"")) | BF52: =IF(ISNUMBER(BV52),BV52,IF(AND(ISNUMBER($BO52),ISNUMBER($BP52)),BP52,"")) | BJ52: =IF(AND(ISNUMBER(BG52),ISNUMBER(BH52),ISNUMBER(BI52)),EXP(LOG(BI52)-1.96*SQRT((1/BG52)+(1/BH52))),"") | BK52: =IF(AND(ISNUMBER(BG52),ISNUMBER(BH52),ISNUMBER(BI52)),EXP(LOG(BI52)+1.96*SQRT((1/BG52)+(1/BH52))),"") | BO52: =IF(AND(ISNUMBER(BL52),ISNUMBER(BM52),ISNUMBER(BN52)),EXP(LOG(BN52)-1.96*SQRT((1/BL52)+(1/BM52))),"") | BP52: =IF(AND(ISNUMBER(BL52),ISNUMBER(BM52),ISNUMBER(BN52)),EXP(LOG(BN52)+1.96*SQRT((1/BL52)+(1/BM52))),"")
A53: Lee YJ | B53: 2022 | C53: https://pubmed.ncbi.nlm.nih.gov/34390240 | D53: =A53&" "&B53 -> Lee YJ 2022 | E53: =IF(OR(AND(ISNUMBER(AL53),ISNUMBER(CG53)),AND(ISNUMBER(AM53),ISNUMBER(CH53)),AND(ISNUMBER(AP53),ISNUMBER(AN53),ISNUMBER(AR53),ISNUMBER(CK53),ISNUMBER(CI53),ISNUMBER(CM53)),AND(ISNUMBER(AU53),ISNUMBER(AS53),ISNUMBER(AW53),ISNUMBER(CP53),ISNUMBER(CN53),ISNUMBER(CR53)),AND(ISNUMBER(BB53),ISNUMBER(BC53))),"Yes","No") -> No | AG53: 83 | AO53: 10 | AP53: 11 | AQ53: 11 | AT53: 15 | AU53: 17 | AV53: 20 | BA53: =IF(ISNUMBER(BQ53),BQ53,IF(AND(ISNUMBER($BJ53),ISNUMBER($BK53)),BI53,"")) | BB53: =IF(ISNUMBER(BR53),BR53,IF(AND(ISNUMBER($BJ53),ISNUMBER($BK53)),BJ53,"")) | BC53: =IF(ISNUMBER(BS53),BS53,IF(AND(ISNUMBER($BJ53),ISNUMBER($BK53)),BK53,"")) | BD53: =IF(ISNUMBER(BT53),BT53,IF(AND(ISNUMBER($BO53),ISNUMBER($BP53)),BN53,"")) | BE53: =IF(ISNUMBER(BU53),BU53,IF(AND(ISNUMBER($BO53),ISNUMBER($BP53)),BO53,"")) | BF53: =IF(ISNUMBER(BV53),BV53,IF(AND(ISNUMBER($BO53),ISNUMBER($BP53)),BP53,"")) | BG53: Unclear | BH53: Unclear | BI53: =CK53/AP53 -> 0.90909091 | BJ53: =IF(AND(ISNUMBER(BG53),ISNUMBER(BH53),ISNUMBER(BI53)),EXP(LOG(BI53)-1.96*SQRT((1/BG53)+(1/BH53))),"") | BK53: =IF(AND(ISNUMBER(BG53),ISNUMBER(BH53),ISNUMBER(BI53)),EXP(LOG(BI53)+1.96*SQRT((1/BG53)+(1/BH53))),"") | BL53: Unclear | BM53: Unclear | BN53: =CP53/AU53 -> 1.0588235 | BO53: =IF(AND(ISNUMBER(BL53),ISNUMBER(BM53),ISNUMBER(BN53)),EXP(LOG(BN53)-1.96*SQRT((1/BL53)+(1/BM53))),"") | BP53: =IF(AND(ISNUMBER(BL53),ISNUMBER(BM53),ISNUMBER(BN53)),EXP(LOG(BN53)+1.96*SQRT((1/BL53)+(1/BM53))),"") | CC53: 229 | CJ53: 10 | CK53: 10 | CL53: 11 | CO53: 6 | CP53: 18 | CQ53: 23
A54: Linder KA | B54: 2019 | C54: https://pubmed.ncbi.nlm.nih.gov/30815505 | D54: =A54&" "&B54 -> Linder KA 2019 | E54: =IF(OR(AND(ISNUMBER(AL54),ISNUMBER(CG54)),AND(ISNUMBER(AM54),ISNUMBER(CH54)),AND(ISNUMBER(AP54),ISNUMBER(AN54),ISNUMBER(AR54),ISNUMBER(CK54),ISNUMBER(CI54),ISNUMBER(CM54)),AND(ISNUMBER(AU54),ISNUMBER(AS54),ISNUMBER(AW54),ISNUMBER(CP54),ISNUMBER(CN54),ISNUMBER(CR54)),AND(ISNUMBER(BB54),ISNUMBER(BC54))),"Yes","No") -> No | BA54: =IF(ISNUMBER(BQ54),BQ54,IF(AND(ISNUMBER($BJ54),ISNUMBER($BK54)),BI54,"")) | BB54: =IF(ISNUMBER(BR54),BR54,IF(AND(ISNUMBER($BJ54),ISNUMBER($BK54)),BJ54,"")) | BC54: =IF(ISNUMBER(BS54),BS54,IF(AND(ISNUMBER($BJ54),ISNUMBER($BK54)),BK54,"")) | BD54: =IF(ISNUMBER(BT54),BT54,IF(AND(ISNUMBER($BO54),ISNUMBER($BP54)),BN54,"")) | BE54: =IF(ISNUMBER(BU54),BU54,IF(AND(ISNUMBER($BO54),ISNUMBER($BP54)),BO54,"")) | BF54: =IF(ISNUMBER(BV54),BV54,IF(AND(ISNUMBER($BO54),ISNUMBER($BP54)),BP54,"")) | BJ54: =IF(AND(ISNUMBER(BG54),ISNUMBER(BH54),ISNUMBER(BI54)),EXP(LOG(BI54)-1.96*SQRT((1/BG54)+(1/BH54))),"") | BK54: =IF(AND(ISNUMBER(BG54),ISNUMBER(BH54),ISNUMBER(BI54)),EXP(LOG(BI54)+1.96*SQRT((1/BG54)+(1/BH54))),"") | BO54: =IF(AND(ISNUMBER(BL54),ISNUMBER(BM54),ISNUMBER(BN54)),EXP(LOG(BN54)-1.96*SQRT((1/BL54)+(1/BM54))),"") | BP54: =IF(AND(ISNUMBER(BL54),ISNUMBER(BM54),ISNUMBER(BN54)),EXP(LOG(BN54)+1.96*SQRT((1/BL54)+(1/BM54))),"")
A55: Ljungman P | B55: 2000 | C55: https://pubmed.ncbi.nlm.nih.gov/11122137 | D55: =A55&" "&B55 -> Ljungman P 2000 | E55: =IF(OR(AND(ISNUMBER(AL55),ISNUMBER(CG55)),AND(ISNUMBER(AM55),ISNUMBER(CH55)),AND(ISNUMBER(AP55),ISNUMBER(AN55),ISNUMBER(AR55),ISNUMBER(CK55),ISNUMBER(CI55),ISNUMBER(CM55)),AND(ISNUMBER(AU55),ISNUMBER(AS55),ISNUMBER(AW55),ISNUMBER(CP55),ISNUMBER(CN55),ISNUMBER(CR55)),AND(ISNUMBER(BB55),ISNUMBER(BC55))),"Yes","No") -> No | BA55: =IF(ISNUMBER(BQ55),BQ55,IF(AND(ISNUMBER($BJ55),ISNUMBER($BK55)),BI55,"")) | BB55: =IF(ISNUMBER(BR55),BR55,IF(AND(ISNUMBER($BJ55),ISNUMBER($BK55)),BJ55,"")) | BC55: =IF(ISNUMBER(BS55),BS55,IF(AND(ISNUMBER($BJ55),ISNUMBER($BK55)),BK55,"")) | BD55: =IF(ISNUMBER(BT55),BT55,IF(AND(ISNUMBER($BO55),ISNUMBER($BP55)),BN55,"")) | BE55: =IF(ISNUMBER(BU55),BU55,IF(AND(ISNUMBER($BO55),ISNUMBER($BP55)),BO55,"")) | BF55: =IF(ISNUMBER(BV55),BV55,IF(AND(ISNUMBER($BO55),ISNUMBER($BP55)),BP55,"")) | BJ55: =IF(AND(ISNUMBER(BG55),ISNUMBER(BH55),ISNUMBER(BI55)),EXP(LOG(BI55)-1.96*SQRT((1/BG55)+(1/BH55))),"") | BK55: =IF(AND(ISNUMBER(BG55),ISNUMBER(BH55),ISNUMBER(BI55)),EXP(LOG(BI55)+1.96*SQRT((1/BG55)+(1/BH55))),"") | BO55: =IF(AND(ISNUMBER(BL55),ISNUMBER(BM55),ISNUMBER(BN55)),EXP(LOG(BN55)-1.96*SQRT((1/BL55)+(1/BM55))),"") | BP55: =IF(AND(ISNUMBER(BL55),ISNUMBER(BM55),ISNUMBER(BN55)),EXP(LOG(BN55)+1.96*SQRT((1/BL55)+(1/BM55))),"") | CX55: has cox regression coefs but not HR and CI. maybe convert?
A56: Ma XT | B56: 2001 | C56: https://scholar.google.com/scholar?hl=en&as_sdt=0%2C5&q=The+role+of+human+herpesvirus-6+in+delayed+engraftment+in+stem+cell+transplant+patients+in+China&btnG= | D56: =A56&" "&B56 -> Ma XT 2001 | E56: =IF(OR(AND(ISNUMBER(AL56),ISNUMBER(CG56)),AND(ISNUMBER(AM56),ISNUMBER(CH56)),AND(ISNUMBER(AP56),ISNUMBER(AN56),ISNUMBER(AR56),ISNUMBER(CK56),ISNUMBER(CI56),ISNUMBER(CM56)),AND(ISNUMBER(AU56),ISNUMBER(AS56),ISNUMBER(AW56),ISNUMBER(CP56),ISNUMBER(CN56),ISNUMBER(CR56)),AND(ISNUMBER(BB56),ISNUMBER(BC56))),"Yes","No") -> No | BA56: =IF(ISNUMBER(BQ56),BQ56,IF(AND(ISNUMBER($BJ56),ISNUMBER($BK56)),BI56,"")) | BB56: =IF(ISNUMBER(BR56),BR56,IF(AND(ISNUMBER($BJ56),ISNUMBER($BK56)),BJ56,"")) | BC56: =IF(ISNUMBER(BS56),BS56,IF(AND(ISNUMBER($BJ56),ISNUMBER($BK56)),BK56,"")) | BD56: =IF(ISNUMBER(BT56),BT56,IF(AND(ISNUMBER($BO56),ISNUMBER($BP56)),BN56,"")) | BE56: =IF(ISNUMBER(BU56),BU56,IF(AND(ISNUMBER($BO56),ISNUMBER($BP56)),BO56,"")) | BF56: =IF(ISNUMBER(BV56),BV56,IF(AND(ISNUMBER($BO56),ISNUMBER($BP56)),BP56,"")) | BJ56: =IF(AND(ISNUMBER(BG56),ISNUMBER(BH56),ISNUMBER(BI56)),EXP(LOG(BI56)-1.96*SQRT((1/BG56)+(1/BH56))),"") | BK56: =IF(AND(ISNUMBER(BG56),ISNUMBER(BH56),ISNUMBER(BI56)),EXP(LOG(BI56)+1.96*SQRT((1/BG56)+(1/BH56))),"") | BO56: =IF(AND(ISNUMBER(BL56),ISNUMBER(BM56),ISNUMBER(BN56)),EXP(LOG(BN56)-1.96*SQRT((1/BL56)+(1/BM56))),"") | BP56: =IF(AND(ISNUMBER(BL56),ISNUMBER(BM56),ISNUMBER(BN56)),EXP(LOG(BN56)+1.96*SQRT((1/BL56)+(1/BM56))),"")
A57: Maeda Y | B57: 1999 | C57: https://pubmed.ncbi.nlm.nih.gov/10233397 | D57: =A57&" "&B57 -> Maeda Y 1999 | E57: =IF(OR(AND(ISNUMBER(AL57),ISNUMBER(CG57)),AND(ISNUMBER(AM57),ISNUMBER(CH57)),AND(ISNUMBER(AP57),ISNUMBER(AN57),ISNUMBER(AR57),ISNUMBER(CK57),ISNUMBER(CI57),ISNUMBER(CM57)),AND(ISNUMBER(AU57),ISNUMBER(AS57),ISNUMBER(AW57),ISNUMBER(CP57),ISNUMBER(CN57),ISNUMBER(CR57)),AND(ISNUMBER(BB57),ISNUMBER(BC57))),"Yes","No") -> No | BA57: =IF(ISNUMBER(BQ57),BQ57,IF(AND(ISNUMBER($BJ57),ISNUMBER($BK57)),BI57,"")) | BB57: =IF(ISNUMBER(BR57),BR57,IF(AND(ISNUMBER($BJ57),ISNUMBER($BK57)),BJ57,"")) | BC57: =IF(ISNUMBER(BS57),BS57,IF(AND(ISNUMBER($BJ57),ISNUMBER($BK57)),BK57,"")) | BD57: =IF(ISNUMBER(BT57),BT57,IF(AND(ISNUMBER($BO57),ISNUMBER($BP57)),BN57,"")) | BE57: =IF(ISNUMBER(BU57),BU57,IF(AND(ISNUMBER($BO57),ISNUMBER($BP57)),BO57,"")) | BF57: =IF(ISNUMBER(BV57),BV57,IF(AND(ISNUMBER($BO57),ISNUMBER($BP57)),BP57,"")) | BJ57: =IF(AND(ISNUMBER(BG57),ISNUMBER(BH57),ISNUMBER(BI57)),EXP(LOG(BI57)-1.96*SQRT((1/BG57)+(1/BH57))),"") | BK57: =IF(AND(ISNUMBER(BG57),ISNUMBER(BH57),ISNUMBER(BI57)),EXP(LOG(BI57)+1.96*SQRT((1/BG57)+(1/BH57))),"") | BO57: =IF(AND(ISNUMBER(BL57),ISNUMBER(BM57),ISNUMBER(BN57)),EXP(LOG(BN57)-1.96*SQRT((1/BL57)+(1/BM57))),"") | BP57: =IF(AND(ISNUMBER(BL57),ISNUMBER(BM57),ISNUMBER(BN57)),EXP(LOG(BN57)+1.96*SQRT((1/BL57)+(1/BM57))),"")
A58: Miura H | B58: 2015 | C58: https://pubmed.ncbi.nlm.nih.gov/26083588 | D58: =A58&" "&B58 -> Miura H 2015 | E58: =IF(OR(AND(ISNUMBER(AL58),ISNUMBER(CG58)),AND(ISNUMBER(AM58),ISNUMBER(CH58)),AND(ISNUMBER(AP58),ISNUMBER(AN58),ISNUMBER(AR58),ISNUMBER(CK58),ISNUMBER(CI58),ISNUMBER(CM58)),AND(ISNUMBER(AU58),ISNUMBER(AS58),ISNUMBER(AW58),ISNUMBER(CP58),ISNUMBER(CN58),ISNUMBER(CR58)),AND(ISNUMBER(BB58),ISNUMBER(BC58))),"Yes","No") -> No | BA58: =IF(ISNUMBER(BQ58),BQ58,IF(AND(ISNUMBER($BJ58),ISNUMBER($BK58)),BI58,"")) | BB58: =IF(ISNUMBER(BR58),BR58,IF(AND(ISNUMBER($BJ58),ISNUMBER($BK58)),BJ58,"")) | BC58: =IF(ISNUMBER(BS58),BS58,IF(AND(ISNUMBER($BJ58),ISNUMBER($BK58)),BK58,"")) | BD58: =IF(ISNUMBER(BT58),BT58,IF(AND(ISNUMBER($BO58),ISNUMBER($BP58)),BN58,"")) | BE58: =IF(ISNUMBER(BU58),BU58,IF(AND(ISNUMBER($BO58),ISNUMBER($BP58)),BO58,"")) | BF58: =IF(ISNUMBER(BV58),BV58,IF(AND(ISNUMBER($BO58),ISNUMBER($BP58)),BP58,"")) | BJ58: =IF(AND(ISNUMBER(BG58),ISNUMBER(BH58),ISNUMBER(BI58)),EXP(LOG(BI58)-1.96*SQRT((1/BG58)+(1/BH58))),"") | BK58: =IF(AND(ISNUMBER(BG58),ISNUMBER(BH58),ISNUMBER(BI58)),EXP(LOG(BI58)+1.96*SQRT((1/BG58)+(1/BH58))),"") | BO58: =IF(AND(ISNUMBER(BL58),ISNUMBER(BM58),ISNUMBER(BN58)),EXP(LOG(BN58)-1.96*SQRT((1/BL58)+(1/BM58))),"") | BP58: =IF(AND(ISNUMBER(BL58),ISNUMBER(BM58),ISNUMBER(BN58)),EXP(LOG(BN58)+1.96*SQRT((1/BL58)+(1/BM58))),"")
A59: Muranushi H | B59: 2020 | C59: https://pubmed.ncbi.nlm.nih.gov/32386102 | D59: =A59&" "&B59 -> Muranushi H 2020 | E59: =IF(OR(AND(ISNUMBER(AL59),ISNUMBER(CG59)),AND(ISNUMBER(AM59),ISNUMBER(CH59)),AND(ISNUMBER(AP59),ISNUMBER(AN59),ISNUMBER(AR59),ISNUMBER(CK59),ISNUMBER(CI59),ISNUMBER(CM59)),AND(ISNUMBER(AU59),ISNUMBER(AS59),ISNUMBER(AW59),ISNUMBER(CP59),ISNUMBER(CN59),ISNUMBER(CR59)),AND(ISNUMBER(BB59),ISNUMBER(BC59))),"Yes","No") -> No | BA59: =IF(ISNUMBER(BQ59),BQ59,IF(AND(ISNUMBER($BJ59),ISNUMBER($BK59)),BI59,"")) | BB59: =IF(ISNUMBER(BR59),BR59,IF(AND(ISNUMBER($BJ59),ISNUMBER($BK59)),BJ59,"")) | BC59: =IF(ISNUMBER(BS59),BS59,IF(AND(ISNUMBER($BJ59),ISNUMBER($BK59)),BK59,"")) | BD59: =IF(ISNUMBER(BT59),BT59,IF(AND(ISNUMBER($BO59),ISNUMBER($BP59)),BN59,"")) | BE59: =IF(ISNUMBER(BU59),BU59,IF(AND(ISNUMBER($BO59),ISNUMBER($BP59)),BO59,"")) | BF59: =IF(ISNUMBER(BV59),BV59,IF(AND(ISNUMBER($BO59),ISNUMBER($BP59)),BP59,"")) | BJ59: =IF(AND(ISNUMBER(BG59),ISNUMBER(BH59),ISNUMBER(BI59)),EXP(LOG(BI59)-1.96*SQRT((1/BG59)+(1/BH59))),"") | BK59: =IF(AND(ISNUMBER(BG59),ISNUMBER(BH59),ISNUMBER(BI59)),EXP(LOG(BI59)+1.96*SQRT((1/BG59)+(1/BH59))),"") | BO59: =IF(AND(ISNUMBER(BL59),ISNUMBER(BM59),ISNUMBER(BN59)),EXP(LOG(BN59)-1.96*SQRT((1/BL59)+(1/BM59))),"") | BP59: =IF(AND(ISNUMBER(BL59),ISNUMBER(BM59),ISNUMBER(BN59)),EXP(LOG(BN59)+1.96*SQRT((1/BL59)+(1/BM59))),"")
A60: Mutlu D | B60: 2014 | C60: https://pubmed.ncbi.nlm.nih.gov/24658548 | D60: =A60&" "&B60 -> Mutlu D 2014 | E60: =IF(OR(AND(ISNUMBER(AL60),ISNUMBER(CG60)),AND(ISNUMBER(AM60),ISNUMBER(CH60)),AND(ISNUMBER(AP60),ISNUMBER(AN60),ISNUMBER(AR60),ISNUMBER(CK60),ISNUMBER(CI60),ISNUMBER(CM60)),AND(ISNUMBER(AU60),ISNUMBER(AS60),ISNUMBER(AW60),ISNUMBER(CP60),ISNUMBER(CN60),ISNUMBER(CR60)),AND(ISNUMBER(BB60),ISNUMBER(BC60))),"Yes","No") -> No | BA60: =IF(ISNUMBER(BQ60),BQ60,IF(AND(ISNUMBER($BJ60),ISNUMBER($BK60)),BI60,"")) | BB60: =IF(ISNUMBER(BR60),BR60,IF(AND(ISNUMBER($BJ60),ISNUMBER($BK60)),BJ60,"")) | BC60: =IF(ISNUMBER(BS60),BS60,IF(AND(ISNUMBER($BJ60),ISNUMBER($BK60)),BK60,"")) | BD60: =IF(ISNUMBER(BT60),BT60,IF(AND(ISNUMBER($BO60),ISNUMBER($BP60)),BN60,"")) | BE60: =IF(ISNUMBER(BU60),BU60,IF(AND(ISNUMBER($BO60),ISNUMBER($BP60)),BO60,"")) | BF60: =IF(ISNUMBER(BV60),BV60,IF(AND(ISNUMBER($BO60),ISNUMBER($BP60)),BP60,"")) | BJ60: =IF(AND(ISNUMBER(BG60),ISNUMBER(BH60),ISNUMBER(BI60)),EXP(LOG(BI60)-1.96*SQRT((1/BG60)+(1/BH60))),"") | BK60: =IF(AND(ISNUMBER(BG60),ISNUMBER(BH60),ISNUMBER(BI60)),EXP(LOG(BI60)+1.96*SQRT((1/BG60)+(1/BH60))),"") | BO60: =IF(AND(ISNUMBER(BL60),ISNUMBER(BM60),ISNUMBER(BN60)),EXP(LOG(BN60)-1.96*SQRT((1/BL60)+(1/BM60))),"") | BP60: =IF(AND(ISNUMBER(BL60),ISNUMBER(BM60),ISNUMBER(BN60)),EXP(LOG(BN60)+1.96*SQRT((1/BL60)+(1/BM60))),"")
A61: Noviello M | B61: 2023 | C61: https://pubmed.ncbi.nlm.nih.gov/37067947 | D61: =A61&" "&B61 -> Noviello M 2023 | E61: =IF(OR(AND(ISNUMBER(AL61),ISNUMBER(CG61)),AND(ISNUMBER(AM61),ISNUMBER(CH61)),AND(ISNUMBER(AP61),ISNUMBER(AN61),ISNUMBER(AR61),ISNUMBER(CK61),ISNUMBER(CI61),ISNUMBER(CM61)),AND(ISNUMBER(AU61),ISNUMBER(AS61),ISNUMBER(AW61),ISNUMBER(CP61),ISNUMBER(CN61),ISNUMBER(CR61)),AND(ISNUMBER(BB61),ISNUMBER(BC61))),"Yes","No") -> No | BA61: =IF(ISNUMBER(BQ61),BQ61,IF(AND(ISNUMBER($BJ61),ISNUMBER($BK61)),BI61,"")) | BB61: =IF(ISNUMBER(BR61),BR61,IF(AND(ISNUMBER($BJ61),ISNUMBER($BK61)),BJ61,"")) | BC61: =IF(ISNUMBER(BS61),BS61,IF(AND(ISNUMBER($BJ61),ISNUMBER($BK61)),BK61,"")) | BD61: =IF(ISNUMBER(BT61),BT61,IF(AND(ISNUMBER($BO61),ISNUMBER($BP61)),BN61,"")) | BE61: =IF(ISNUMBER(BU61),BU61,IF(AND(ISNUMBER($BO61),ISNUMBER($BP61)),BO61,"")) | BF61: =IF(ISNUMBER(BV61),BV61,IF(AND(ISNUMBER($BO61),ISNUMBER($BP61)),BP61,"")) | BJ61: =IF(AND(ISNUMBER(BG61),ISNUMBER(BH61),ISNUMBER(BI61)),EXP(LOG(BI61)-1.96*SQRT((1/BG61)+(1/BH61))),"") | BK61: =IF(AND(ISNUMBER(BG61),ISNUMBER(BH61),ISNUMBER(BI61)),EXP(LOG(BI61)+1.96*SQRT((1/BG61)+(1/BH61))),"") | BO61: =IF(AND(ISNUMBER(BL61),ISNUMBER(BM61),ISNUMBER(BN61)),EXP(LOG(BN61)-1.96*SQRT((1/BL61)+(1/BM61))),"") | BP61: =IF(AND(ISNUMBER(BL61),ISNUMBER(BM61),ISNUMBER(BN61)),EXP(LOG(BN61)+1.96*SQRT((1/BL61)+(1/BM61))),"")
A62: Ogata M | B62: 2018 | C62: https://pubmed.ncbi.nlm.nih.gov/29454651 | D62: =A62&" "&B62 -> Ogata M 2018 | E62: =IF(OR(AND(ISNUMBER(AL62),ISNUMBER(CG62)),AND(ISNUMBER(AM62),ISNUMBER(CH62)),AND(ISNUMBER(AP62),ISNUMBER(AN62),ISNUMBER(AR62),ISNUMBER(CK62),ISNUMBER(CI62),ISNUMBER(CM62)),AND(ISNUMBER(AU62),ISNUMBER(AS62),ISNUMBER(AW62),ISNUMBER(CP62),ISNUMBER(CN62),ISNUMBER(CR62)),AND(ISNUMBER(BB62),ISNUMBER(BC62))),"Yes","No") -> No | BA62: =IF(ISNUMBER(BQ62),BQ62,IF(AND(ISNUMBER($BJ62),ISNUMBER($BK62)),BI62,"")) | BB62: =IF(ISNUMBER(BR62),BR62,IF(AND(ISNUMBER($BJ62),ISNUMBER($BK62)),BJ62,"")) | BC62: =IF(ISNUMBER(BS62),BS62,IF(AND(ISNUMBER($BJ62),ISNUMBER($BK62)),BK62,"")) | BD62: =IF(ISNUMBER(BT62),BT62,IF(AND(ISNUMBER($BO62),ISNUMBER($BP62)),BN62,"")) | BE62: =IF(ISNUMBER(BU62),BU62,IF(AND(ISNUMBER($BO62),ISNUMBER($BP62)),BO62,"")) | BF62: =IF(ISNUMBER(BV62),BV62,IF(AND(ISNUMBER($BO62),ISNUMBER($BP62)),BP62,"")) | BJ62: =IF(AND(ISNUMBER(BG62),ISNUMBER(BH62),ISNUMBER(BI62)),EXP(LOG(BI62)-1.96*SQRT((1/BG62)+(1/BH62))),"") | BK62: =IF(AND(ISNUMBER(BG62),ISNUMBER(BH62),ISNUMBER(BI62)),EXP(LOG(BI62)+1.96*SQRT((1/BG62)+(1/BH62))),"") | BO62: =IF(AND(ISNUMBER(BL62),ISNUMBER(BM62),ISNUMBER(BN62)),EXP(LOG(BN62)-1.96*SQRT((1/BL62)+(1/BM62))),"") | BP62: =IF(AND(ISNUMBER(BL62),ISNUMBER(BM62),ISNUMBER(BN62)),EXP(LOG(BN62)+1.96*SQRT((1/BL62)+(1/BM62))),"")
A63: Oltolini C | B63: 2020 | C63: https://pubmed.ncbi.nlm.nih.gov/32004700 | D63: =A63&" "&B63 -> Oltolini C 2020 | E63: =IF(OR(AND(ISNUMBER(AL63),ISNUMBER(CG63)),AND(ISNUMBER(AM63),ISNUMBER(CH63)),AND(ISNUMBER(AP63),ISNUMBER(AN63),ISNUMBER(AR63),ISNUMBER(CK63),ISNUMBER(CI63),ISNUMBER(CM63)),AND(ISNUMBER(AU63),ISNUMBER(AS63),ISNUMBER(AW63),ISNUMBER(CP63),ISNUMBER(CN63),ISNUMBER(CR63)),AND(ISNUMBER(BB63),ISNUMBER(BC63))),"Yes","No") -> No | BA63: =IF(ISNUMBER(BQ63),BQ63,IF(AND(ISNUMBER($BJ63),ISNUMBER($BK63)),BI63,"")) | BB63: =IF(ISNUMBER(BR63),BR63,IF(AND(ISNUMBER($BJ63),ISNUMBER($BK63)),BJ63,"")) | BC63: =IF(ISNUMBER(BS63),BS63,IF(AND(ISNUMBER($BJ63),ISNUMBER($BK63)),BK63,"")) | BD63: =IF(ISNUMBER(BT63),BT63,IF(AND(ISNUMBER($BO63),ISNUMBER($BP63)),BN63,"")) | BE63: =IF(ISNUMBER(BU63),BU63,IF(AND(ISNUMBER($BO63),ISNUMBER($BP63)),BO63,"")) | BF63: =IF(ISNUMBER(BV63),BV63,IF(AND(ISNUMBER($BO63),ISNUMBER($BP63)),BP63,"")) | BJ63: =IF(AND(ISNUMBER(BG63),ISNUMBER(BH63),ISNUMBER(BI63)),EXP(LOG(BI63)-1.96*SQRT((1/BG63)+(1/BH63))),"") | BK63: =IF(AND(ISNUMBER(BG63),ISNUMBER(BH63),ISNUMBER(BI63)),EXP(LOG(BI63)+1.96*SQRT((1/BG63)+(1/BH63))),"") | BO63: =IF(AND(ISNUMBER(BL63),ISNUMBER(BM63),ISNUMBER(BN63)),EXP(LOG(BN63)-1.96*SQRT((1/BL63)+(1/BM63))),"") | BP63: =IF(AND(ISNUMBER(BL63),ISNUMBER(BM63),ISNUMBER(BN63)),EXP(LOG(BN63)+1.96*SQRT((1/BL63)+(1/BM63))),"")
A64: Pawlowska AB | B64: 2021 | C64: https://pubmed.ncbi.nlm.nih.gov/32860467 | D64: =A64&" "&B64 -> Pawlowska AB 2021 | E64: =IF(OR(AND(ISNUMBER(AL64),ISNUMBER(CG64)),AND(ISNUMBER(AM64),ISNUMBER(CH64)),AND(ISNUMBER(AP64),ISNUMBER(AN64),ISNUMBER(AR64),ISNUMBER(CK64),ISNUMBER(CI64),ISNUMBER(CM64)),AND(ISNUMBER(AU64),ISNUMBER(AS64),ISNUMBER(AW64),ISNUMBER(CP64),ISNUMBER(CN64),ISNUMBER(CR64)),AND(ISNUMBER(BB64),ISNUMBER(BC64))),"Yes","No") -> No | BA64: =IF(ISNUMBER(BQ64),BQ64,IF(AND(ISNUMBER($BJ64),ISNUMBER($BK64)),BI64,"")) | BB64: =IF(ISNUMBER(BR64),BR64,IF(AND(ISNUMBER($BJ64),ISNUMBER($BK64)),BJ64,"")) | BC64: =IF(ISNUMBER(BS64),BS64,IF(AND(ISNUMBER($BJ64),ISNUMBER($BK64)),BK64,"")) | BD64: =IF(ISNUMBER(BT64),BT64,IF(AND(ISNUMBER($BO64),ISNUMBER($BP64)),BN64,"")) | BE64: =IF(ISNUMBER(BU64),BU64,IF(AND(ISNUMBER($BO64),ISNUMBER($BP64)),BO64,"")) | BF64: =IF(ISNUMBER(BV64),BV64,IF(AND(ISNUMBER($BO64),ISNUMBER($BP64)),BP64,"")) | BJ64: =IF(AND(ISNUMBER(BG64),ISNUMBER(BH64),ISNUMBER(BI64)),EXP(LOG(BI64)-1.96*SQRT((1/BG64)+(1/BH64))),"") | BK64: =IF(AND(ISNUMBER(BG64),ISNUMBER(BH64),ISNUMBER(BI64)),EXP(LOG(BI64)+1.96*SQRT((1/BG64)+(1/BH64))),"") | BO64: =IF(AND(ISNUMBER(BL64),ISNUMBER(BM64),ISNUMBER(BN64)),EXP(LOG(BN64)-1.96*SQRT((1/BL64)+(1/BM64))),"") | BP64: =IF(AND(ISNUMBER(BL64),ISNUMBER(BM64),ISNUMBER(BN64)),EXP(LOG(BN64)+1.96*SQRT((1/BL64)+(1/BM64))),"")
A65: Perissinotti AJ | B65: 2015 | C65: https://pubmed.ncbi.nlm.nih.gov/24407957 | D65: =A65&" "&B65 -> Perissinotti AJ 2015 | E65: =IF(OR(AND(ISNUMBER(AL65),ISNUMBER(CG65)),AND(ISNUMBER(AM65),ISNUMBER(CH65)),AND(ISNUMBER(AP65),ISNUMBER(AN65),ISNUMBER(AR65),ISNUMBER(CK65),ISNUMBER(CI65),ISNUMBER(CM65)),AND(ISNUMBER(AU65),ISNUMBER(AS65),ISNUMBER(AW65),ISNUMBER(CP65),ISNUMBER(CN65),ISNUMBER(CR65)),AND(ISNUMBER(BB65),ISNUMBER(BC65))),"Yes","No") -> No | BA65: =IF(ISNUMBER(BQ65),BQ65,IF(AND(ISNUMBER($BJ65),ISNUMBER($BK65)),BI65,"")) | BB65: =IF(ISNUMBER(BR65),BR65,IF(AND(ISNUMBER($BJ65),ISNUMBER($BK65)),BJ65,"")) | BC65: =IF(ISNUMBER(BS65),BS65,IF(AND(ISNUMBER($BJ65),ISNUMBER($BK65)),BK65,"")) | BD65: =IF(ISNUMBER(BT65),BT65,IF(AND(ISNUMBER($BO65),ISNUMBER($BP65)),BN65,"")) | BE65: =IF(ISNUMBER(BU65),BU65,IF(AND(ISNUMBER($BO65),ISNUMBER($BP65)),BO65,"")) | BF65: =IF(ISNUMBER(BV65),BV65,IF(AND(ISNUMBER($BO65),ISNUMBER($BP65)),BP65,"")) | BJ65: =IF(AND(ISNUMBER(BG65),ISNUMBER(BH65),ISNUMBER(BI65)),EXP(LOG(BI65)-1.96*SQRT((1/BG65)+(1/BH65))),"") | BK65: =IF(AND(ISNUMBER(BG65),ISNUMBER(BH65),ISNUMBER(BI65)),EXP(LOG(BI65)+1.96*SQRT((1/BG65)+(1/BH65))),"") | BO65: =IF(AND(ISNUMBER(BL65),ISNUMBER(BM65),ISNUMBER(BN65)),EXP(LOG(BN65)-1.96*SQRT((1/BL65)+(1/BM65))),"") | BP65: =IF(AND(ISNUMBER(BL65),ISNUMBER(BM65),ISNUMBER(BN65)),EXP(LOG(BN65)+1.96*SQRT((1/BL65)+(1/BM65))),"")
A66: Perruccio K | B66: 2018 | C66: https://pubmed.ncbi.nlm.nih.gov/30067953 | D66: =A66&" "&B66 -> Perruccio K 2018 | E66: =IF(OR(AND(ISNUMBER(AL66),ISNUMBER(CG66)),AND(ISNUMBER(AM66),ISNUMBER(CH66)),AND(ISNUMBER(AP66),ISNUMBER(AN66),ISNUMBER(AR66),ISNUMBER(CK66),ISNUMBER(CI66),ISNUMBER(CM66)),AND(ISNUMBER(AU66),ISNUMBER(AS66),ISNUMBER(AW66),ISNUMBER(CP66),ISNUMBER(CN66),ISNUMBER(CR66)),AND(ISNUMBER(BB66),ISNUMBER(BC66))),"Yes","No") -> No | BA66: =IF(ISNUMBER(BQ66),BQ66,IF(AND(ISNUMBER($BJ66),ISNUMBER($BK66)),BI66,"")) | BB66: =IF(ISNUMBER(BR66),BR66,IF(AND(ISNUMBER($BJ66),ISNUMBER($BK66)),BJ66,"")) | BC66: =IF(ISNUMBER(BS66),BS66,IF(AND(ISNUMBER($BJ66),ISNUMBER($BK66)),BK66,"")) | BD66: =IF(ISNUMBER(BT66),BT66,IF(AND(ISNUMBER($BO66),ISNUMBER($BP66)),BN66,"")) | BE66: =IF(ISNUMBER(BU66),BU66,IF(AND(ISNUMBER($BO66),ISNUMBER($BP66)),BO66,"")) | BF66: =IF(ISNUMBER(BV66),BV66,IF(AND(ISNUMBER($BO66),ISNUMBER($BP66)),BP66,"")) | BJ66: =IF(AND(ISNUMBER(BG66),ISNUMBER(BH66),ISNUMBER(BI66)),EXP(LOG(BI66)-1.96*SQRT((1/BG66)+(1/BH66))),"") | BK66: =IF(AND(ISNUMBER(BG66),ISNUMBER(BH66),ISNUMBER(BI66)),EXP(LOG(BI66)+1.96*SQRT((1/BG66)+(1/BH66))),"") | BO66: =IF(AND(ISNUMBER(BL66),ISNUMBER(BM66),ISNUMBER(BN66)),EXP(LOG(BN66)-1.96*SQRT((1/BL66)+(1/BM66))),"") | BP66: =IF(AND(ISNUMBER(BL66),ISNUMBER(BM66),ISNUMBER(BN66)),EXP(LOG(BN66)+1.96*SQRT((1/BL66)+(1/BM66))),"")
A67: Potenza L | B67: 2009 | C67: https://pubmed.ncbi.nlm.nih.gov/19519818 | D67: =A67&" "&B67 -> Potenza L 2009 | E67: =IF(OR(AND(ISNUMBER(AL67),ISNUMBER(CG67)),AND(ISNUMBER(AM67),ISNUMBER(CH67)),AND(ISNUMBER(AP67),ISNUMBER(AN67),ISNUMBER(AR67),ISNUMBER(CK67),ISNUMBER(CI67),ISNUMBER(CM67)),AND(ISNUMBER(AU67),ISNUMBER(AS67),ISNUMBER(AW67),ISNUMBER(CP67),ISNUMBER(CN67),ISNUMBER(CR67)),AND(ISNUMBER(BB67),ISNUMBER(BC67))),"Yes","No") -> No | BA67: =IF(ISNUMBER(BQ67),BQ67,IF(AND(ISNUMBER($BJ67),ISNUMBER($BK67)),BI67,"")) | BB67: =IF(ISNUMBER(BR67),BR67,IF(AND(ISNUMBER($BJ67),ISNUMBER($BK67)),BJ67,"")) | BC67: =IF(ISNUMBER(BS67),BS67,IF(AND(ISNUMBER($BJ67),ISNUMBER($BK67)),BK67,"")) | BD67: =IF(ISNUMBER(BT67),BT67,IF(AND(ISNUMBER($BO67),ISNUMBER($BP67)),BN67,"")) | BE67: =IF(ISNUMBER(BU67),BU67,IF(AND(ISNUMBER($BO67),ISNUMBER($BP67)),BO67,"")) | BF67: =IF(ISNUMBER(BV67),BV67,IF(AND(ISNUMBER($BO67),ISNUMBER($BP67)),BP67,"")) | BJ67: =IF(AND(ISNUMBER(BG67),ISNUMBER(BH67),ISNUMBER(BI67)),EXP(LOG(BI67)-1.96*SQRT((1/BG67)+(1/BH67))),"") | BK67: =IF(AND(ISNUMBER(BG67),ISNUMBER(BH67),ISNUMBER(BI67)),EXP(LOG(BI67)+1.96*SQRT((1/BG67)+(1/BH67))),"") | BO67: =IF(AND(ISNUMBER(BL67),ISNUMBER(BM67),ISNUMBER(BN67)),EXP(LOG(BN67)-1.96*SQRT((1/BL67)+(1/BM67))),"") | BP67: =IF(AND(ISNUMBER(BL67),ISNUMBER(BM67),ISNUMBER(BN67)),EXP(LOG(BN67)+1.96*SQRT((1/BL67)+(1/BM67))),"")
A68: Radonić A | B68: 2005 | C68: https://pubmed.ncbi.nlm.nih.gov/16281938 | D68: =A68&" "&B68 -> Radonić A 2005 | E68: =IF(OR(AND(ISNUMBER(AL68),ISNUMBER(CG68)),AND(ISNUMBER(AM68),ISNUMBER(CH68)),AND(ISNUMBER(AP68),ISNUMBER(AN68),ISNUMBER(AR68),ISNUMBER(CK68),ISNUMBER(CI68),ISNUMBER(CM68)),AND(ISNUMBER(AU68),ISNUMBER(AS68),ISNUMBER(AW68),ISNUMBER(CP68),ISNUMBER(CN68),ISNUMBER(CR68)),AND(ISNUMBER(BB68),ISNUMBER(BC68))),"Yes","No") -> No | BA68: =IF(ISNUMBER(BQ68),BQ68,IF(AND(ISNUMBER($BJ68),ISNUMBER($BK68)),BI68,"")) | BB68: =IF(ISNUMBER(BR68),BR68,IF(AND(ISNUMBER($BJ68),ISNUMBER($BK68)),BJ68,"")) | BC68: =IF(ISNUMBER(BS68),BS68,IF(AND(ISNUMBER($BJ68),ISNUMBER($BK68)),BK68,"")) | BD68: =IF(ISNUMBER(BT68),BT68,IF(AND(ISNUMBER($BO68),ISNUMBER($BP68)),BN68,"")) | BE68: =IF(ISNUMBER(BU68),BU68,IF(AND(ISNUMBER($BO68),ISNUMBER($BP68)),BO68,"")) | BF68: =IF(ISNUMBER(BV68),BV68,IF(AND(ISNUMBER($BO68),ISNUMBER($BP68)),BP68,"")) | BJ68: =IF(AND(ISNUMBER(BG68),ISNUMBER(BH68),ISNUMBER(BI68)),EXP(LOG(BI68)-1.96*SQRT((1/BG68)+(1/BH68))),"") | BK68: =IF(AND(ISNUMBER(BG68),ISNUMBER(BH68),ISNUMBER(BI68)),EXP(LOG(BI68)+1.96*SQRT((1/BG68)+(1/BH68))),"") | BO68: =IF(AND(ISNUMBER(BL68),ISNUMBER(BM68),ISNUMBER(BN68)),EXP(LOG(BN68)-1.96*SQRT((1/BL68)+(1/BM68))),"") | BP68: =IF(AND(ISNUMBER(BL68),ISNUMBER(BM68),ISNUMBER(BN68)),EXP(LOG(BN68)+1.96*SQRT((1/BL68)+(1/BM68))),"") | BT68: See note | BU68: See note | BV68: See note | CX68: These results don't make sense, I think they inverted the convention. They note a delay in engraftment, then give an HR > 1, which indicates greater chance of engraftment.
A69: Schönberger S | B69: 2010 | C69: https://pubmed.ncbi.nlm.nih.gov/20399877 | D69: =A69&" "&B69 -> Schönberger S 2010 | E69: =IF(OR(AND(ISNUMBER(AL69),ISNUMBER(CG69)),AND(ISNUMBER(AM69),ISNUMBER(CH69)),AND(ISNUMBER(AP69),ISNUMBER(AN69),ISNUMBER(AR69),ISNUMBER(CK69),ISNUMBER(CI69),ISNUMBER(CM69)),AND(ISNUMBER(AU69),ISNUMBER(AS69),ISNUMBER(AW69),ISNUMBER(CP69),ISNUMBER(CN69),ISNUMBER(CR69)),AND(ISNUMBER(BB69),ISNUMBER(BC69))),"Yes","No") -> No | BA69: =IF(ISNUMBER(BQ69),BQ69,IF(AND(ISNUMBER($BJ69),ISNUMBER($BK69)),BI69,"")) | BB69: =IF(ISNUMBER(BR69),BR69,IF(AND(ISNUMBER($BJ69),ISNUMBER($BK69)),BJ69,"")) | BC69: =IF(ISNUMBER(BS69),BS69,IF(AND(ISNUMBER($BJ69),ISNUMBER($BK69)),BK69,"")) | BD69: =IF(ISNUMBER(BT69),BT69,IF(AND(ISNUMBER($BO69),ISNUMBER($BP69)),BN69,"")) | BE69: =IF(ISNUMBER(BU69),BU69,IF(AND(ISNUMBER($BO69),ISNUMBER($BP69)),BO69,"")) | BF69: =IF(ISNUMBER(BV69),BV69,IF(AND(ISNUMBER($BO69),ISNUMBER($BP69)),BP69,"")) | BJ69: =IF(AND(ISNUMBER(BG69),ISNUMBER(BH69),ISNUMBER(BI69)),EXP(LOG(BI69)-1.96*SQRT((1/BG69)+(1/BH69))),"") | BK69: =IF(AND(ISNUMBER(BG69),ISNUMBER(BH69),ISNUMBER(BI69)),EXP(LOG(BI69)+1.96*SQRT((1/BG69)+(1/BH69))),"") | BO69: =IF(AND(ISNUMBER(BL69),ISNUMBER(BM69),ISNUMBER(BN69)),EXP(LOG(BN69)-1.96*SQRT((1/BL69)+(1/BM69))),"") | BP69: =IF(AND(ISNUMBER(BL69),ISNUMBER(BM69),ISNUMBER(BN69)),EXP(LOG(BN69)+1.96*SQRT((1/BL69)+(1/BM69))),"")
A70: Secchiero P | B70: 1995 | C70: https://pubmed.ncbi.nlm.nih.gov/7844362 | D70: =A70&" "&B70 -> Secchiero P 1995 | E70: =IF(OR(AND(ISNUMBER(AL70),ISNUMBER(CG70)),AND(ISNUMBER(AM70),ISNUMBER(CH70)),AND(ISNUMBER(AP70),ISNUMBER(AN70),ISNUMBER(AR70),ISNUMBER(CK70),ISNUMBER(CI70),ISNUMBER(CM70)),AND(ISNUMBER(AU70),ISNUMBER(AS70),ISNUMBER(AW70),ISNUMBER(CP70),ISNUMBER(CN70),ISNUMBER(CR70)),AND(ISNUMBER(BB70),ISNUMBER(BC70))),"Yes","No") -> No | BA70: =IF(ISNUMBER(BQ70),BQ70,IF(AND(ISNUMBER($BJ70),ISNUMBER($BK70)),BI70,"")) | BB70: =IF(ISNUMBER(BR70),BR70,IF(AND(ISNUMBER($BJ70),ISNUMBER($BK70)),BJ70,"")) | BC70: =IF(ISNUMBER(BS70),BS70,IF(AND(ISNUMBER($BJ70),ISNUMBER($BK70)),BK70,"")) | BD70: =IF(ISNUMBER(BT70),BT70,IF(AND(ISNUMBER($BO70),ISNUMBER($BP70)),BN70,"")) | BE70: =IF(ISNUMBER(BU70),BU70,IF(AND(ISNUMBER($BO70),ISNUMBER($BP70)),BO70,"")) | BF70: =IF(ISNUMBER(BV70),BV70,IF(AND(ISNUMBER($BO70),ISNUMBER($BP70)),BP70,"")) | BJ70: =IF(AND(ISNUMBER(BG70),ISNUMBER(BH70),ISNUMBER(BI70)),EXP(LOG(BI70)-1.96*SQRT((1/BG70)+(1/BH70))),"") | BK70: =IF(AND(ISNUMBER(BG70),ISNUMBER(BH70),ISNUMBER(BI70)),EXP(LOG(BI70)+1.96*SQRT((1/BG70)+(1/BH70))),"") | BO70: =IF(AND(ISNUMBER(BL70),ISNUMBER(BM70),ISNUMBER(BN70)),EXP(LOG(BN70)-1.96*SQRT((1/BL70)+(1/BM70))),"") | BP70: =IF(AND(ISNUMBER(BL70),ISNUMBER(BM70),ISNUMBER(BN70)),EXP(LOG(BN70)+1.96*SQRT((1/BL70)+(1/BM70))),"")
A71: Silcock R | B71: 2021 | C71: https://pubmed.ncbi.nlm.nih.gov/33533068 | D71: =A71&" "&B71 -> Silcock R 2021 | E71: =IF(OR(AND(ISNUMBER(AL71),ISNUMBER(CG71)),AND(ISNUMBER(AM71),ISNUMBER(CH71)),AND(ISNUMBER(AP71),ISNUMBER(AN71),ISNUMBER(AR71),ISNUMBER(CK71),ISNUMBER(CI71),ISNUMBER(CM71)),AND(ISNUMBER(AU71),ISNUMBER(AS71),ISNUMBER(AW71),ISNUMBER(CP71),ISNUMBER(CN71),ISNUMBER(CR71)),AND(ISNUMBER(BB71),ISNUMBER(BC71))),"Yes","No") -> No | BA71: =IF(ISNUMBER(BQ71),BQ71,IF(AND(ISNUMBER($BJ71),ISNUMBER($BK71)),BI71,"")) | BB71: =IF(ISNUMBER(BR71),BR71,IF(AND(ISNUMBER($BJ71),ISNUMBER($BK71)),BJ71,"")) | BC71: =IF(ISNUMBER(BS71),BS71,IF(AND(ISNUMBER($BJ71),ISNUMBER($BK71)),BK71,"")) | BD71: =IF(ISNUMBER(BT71),BT71,IF(AND(ISNUMBER($BO71),ISNUMBER($BP71)),BN71,"")) | BE71: =IF(ISNUMBER(BU71),BU71,IF(AND(ISNUMBER($BO71),ISNUMBER($BP71)),BO71,"")) | BF71: =IF(ISNUMBER(BV71),BV71,IF(AND(ISNUMBER($BO71),ISNUMBER($BP71)),BP71,"")) | BJ71: =IF(AND(ISNUMBER(BG71),ISNUMBER(BH71),ISNUMBER(BI71)),EXP(LOG(BI71)-1.96*SQRT((1/BG71)+(1/BH71))),"") | BK71: =IF(AND(ISNUMBER(BG71),ISNUMBER(BH71),ISNUMBER(BI71)),EXP(LOG(BI71)+1.96*SQRT((1/BG71)+(1/BH71))),"") | BO71: =IF(AND(ISNUMBER(BL71),ISNUMBER(BM71),ISNUMBER(BN71)),EXP(LOG(BN71)-1.96*SQRT((1/BL71)+(1/BM71))),"") | BP71: =IF(AND(ISNUMBER(BL71),ISNUMBER(BM71),ISNUMBER(BN71)),EXP(LOG(BN71)+1.96*SQRT((1/BL71)+(1/BM71))),"")
A72: Sisinni L | B72: 2018 | C72: https://pubmed.ncbi.nlm.nih.gov/30031939 | D72: =A72&" "&B72 -> Sisinni L 2018 | E72: =IF(OR(AND(ISNUMBER(AL72),ISNUMBER(CG72)),AND(ISNUMBER(AM72),ISNUMBER(CH72)),AND(ISNUMBER(AP72),ISNUMBER(AN72),ISNUMBER(AR72),ISNUMBER(CK72),ISNUMBER(CI72),ISNUMBER(CM72)),AND(ISNUMBER(AU72),ISNUMBER(AS72),ISNUMBER(AW72),ISNUMBER(CP72),ISNUMBER(CN72),ISNUMBER(CR72)),AND(ISNUMBER(BB72),ISNUMBER(BC72))),"Yes","No") -> No | BA72: =IF(ISNUMBER(BQ72),BQ72,IF(AND(ISNUMBER($BJ72),ISNUMBER($BK72)),BI72,"")) | BB72: =IF(ISNUMBER(BR72),BR72,IF(AND(ISNUMBER($BJ72),ISNUMBER($BK72)),BJ72,"")) | BC72: =IF(ISNUMBER(BS72),BS72,IF(AND(ISNUMBER($BJ72),ISNUMBER($BK72)),BK72,"")) | BD72: =IF(ISNUMBER(BT72),BT72,IF(AND(ISNUMBER($BO72),ISNUMBER($BP72)),BN72,"")) | BE72: =IF(ISNUMBER(BU72),BU72,IF(AND(ISNUMBER($BO72),ISNUMBER($BP72)),BO72,"")) | BF72: =IF(ISNUMBER(BV72),BV72,IF(AND(ISNUMBER($BO72),ISNUMBER($BP72)),BP72,"")) | BJ72: =IF(AND(ISNUMBER(BG72),ISNUMBER(BH72),ISNUMBER(BI72)),EXP(LOG(BI72)-1.96*SQRT((1/BG72)+(1/BH72))),"") | BK72: =IF(AND(ISNUMBER(BG72),ISNUMBER(BH72),ISNUMBER(BI72)),EXP(LOG(BI72)+1.96*SQRT((1/BG72)+(1/BH72))),"") | BO72: =IF(AND(ISNUMBER(BL72),ISNUMBER(BM72),ISNUMBER(BN72)),EXP(LOG(BN72)-1.96*SQRT((1/BL72)+(1/BM72))),"") | BP72: =IF(AND(ISNUMBER(BL72),ISNUMBER(BM72),ISNUMBER(BN72)),EXP(LOG(BN72)+1.96*SQRT((1/BL72)+(1/BM72))),"")
A73: Takatsuka H | B73: 2001 | C73: https://pubmed.ncbi.nlm.nih.gov/27419347 | D73: =A73&" "&B73 -> Takatsuka H 2001 | E73: =IF(OR(AND(ISNUMBER(AL73),ISNUMBER(CG73)),AND(ISNUMBER(AM73),ISNUMBER(CH73)),AND(ISNUMBER(AP73),ISNUMBER(AN73),ISNUMBER(AR73),ISNUMBER(CK73),ISNUMBER(CI73),ISNUMBER(CM73)),AND(ISNUMBER(AU73),ISNUMBER(AS73),ISNUMBER(AW73),ISNUMBER(CP73),ISNUMBER(CN73),ISNUMBER(CR73)),AND(ISNUMBER(BB73),ISNUMBER(BC73))),"Yes","No") -> No | BA73: =IF(ISNUMBER(BQ73),BQ73,IF(AND(ISNUMBER($BJ73),ISNUMBER($BK73)),BI73,"")) | BB73: =IF(ISNUMBER(BR73),BR73,IF(AND(ISNUMBER($BJ73),ISNUMBER($BK73)),BJ73,"")) | BC73: =IF(ISNUMBER(BS73),BS73,IF(AND(ISNUMBER($BJ73),ISNUMBER($BK73)),BK73,"")) | BD73: =IF(ISNUMBER(BT73),BT73,IF(AND(ISNUMBER($BO73),ISNUMBER($BP73)),BN73,"")) | BE73: =IF(ISNUMBER(BU73),BU73,IF(AND(ISNUMBER($BO73),ISNUMBER($BP73)),BO73,"")) | BF73: =IF(ISNUMBER(BV73),BV73,IF(AND(ISNUMBER($BO73),ISNUMBER($BP73)),BP73,"")) | BJ73: =IF(AND(ISNUMBER(BG73),ISNUMBER(BH73),ISNUMBER(BI73)),EXP(LOG(BI73)-1.96*SQRT((1/BG73)+(1/BH73))),"") | BK73: =IF(AND(ISNUMBER(BG73),ISNUMBER(BH73),ISNUMBER(BI73)),EXP(LOG(BI73)+1.96*SQRT((1/BG73)+(1/BH73))),"") | BO73: =IF(AND(ISNUMBER(BL73),ISNUMBER(BM73),ISNUMBER(BN73)),EXP(LOG(BN73)-1.96*SQRT((1/BL73)+(1/BM73))),"") | BP73: =IF(AND(ISNUMBER(BL73),ISNUMBER(BM73),ISNUMBER(BN73)),EXP(LOG(BN73)+1.96*SQRT((1/BL73)+(1/BM73))),"")
A74: Tang FF | B74: 2020 | C74: https://pubmed.ncbi.nlm.nih.gov/31704470 | D74: =A74&" "&B74 -> Tang FF 2020 | E74: =IF(OR(AND(ISNUMBER(AL74),ISNUMBER(CG74)),AND(ISNUMBER(AM74),ISNUMBER(CH74)),AND(ISNUMBER(AP74),ISNUMBER(AN74),ISNUMBER(AR74),ISNUMBER(CK74),ISNUMBER(CI74),ISNUMBER(CM74)),AND(ISNUMBER(AU74),ISNUMBER(AS74),ISNUMBER(AW74),ISNUMBER(CP74),ISNUMBER(CN74),ISNUMBER(CR74)),AND(ISNUMBER(BB74),ISNUMBER(BC74))),"Yes","No") -> No | BA74: =IF(ISNUMBER(BQ74),BQ74,IF(AND(ISNUMBER($BJ74),ISNUMBER($BK74)),BI74,"")) | BB74: =IF(ISNUMBER(BR74),BR74,IF(AND(ISNUMBER($BJ74),ISNUMBER($BK74)),BJ74,"")) | BC74: =IF(ISNUMBER(BS74),BS74,IF(AND(ISNUMBER($BJ74),ISNUMBER($BK74)),BK74,"")) | BD74: =IF(ISNUMBER(BT74),BT74,IF(AND(ISNUMBER($BO74),ISNUMBER($BP74)),BN74,"")) | BE74: =IF(ISNUMBER(BU74),BU74,IF(AND(ISNUMBER($BO74),ISNUMBER($BP74)),BO74,"")) | BF74: =IF(ISNUMBER(BV74),BV74,IF(AND(ISNUMBER($BO74),ISNUMBER($BP74)),BP74,"")) | BJ74: =IF(AND(ISNUMBER(BG74),ISNUMBER(BH74),ISNUMBER(BI74)),EXP(LOG(BI74)-1.96*SQRT((1/BG74)+(1/BH74))),"") | BK74: =IF(AND(ISNUMBER(BG74),ISNUMBER(BH74),ISNUMBER(BI74)),EXP(LOG(BI74)+1.96*SQRT((1/BG74)+(1/BH74))),"") | BO74: =IF(AND(ISNUMBER(BL74),ISNUMBER(BM74),ISNUMBER(BN74)),EXP(LOG(BN74)-1.96*SQRT((1/BL74)+(1/BM74))),"") | BP74: =IF(AND(ISNUMBER(BL74),ISNUMBER(BM74),ISNUMBER(BN74)),EXP(LOG(BN74)+1.96*SQRT((1/BL74)+(1/BM74))),"")
A75: Verhoeven DH | B75: 2015 | C75: https://pubmed.ncbi.nlm.nih.gov/26132825 | D75: =A75&" "&B75 -> Verhoeven DH 2015 | E75: =IF(OR(AND(ISNUMBER(AL75),ISNUMBER(CG75)),AND(ISNUMBER(AM75),ISNUMBER(CH75)),AND(ISNUMBER(AP75),ISNUMBER(AN75),ISNUMBER(AR75),ISNUMBER(CK75),ISNUMBER(CI75),ISNUMBER(CM75)),AND(ISNUMBER(AU75),ISNUMBER(AS75),ISNUMBER(AW75),ISNUMBER(CP75),ISNUMBER(CN75),ISNUMBER(CR75)),AND(ISNUMBER(BB75),ISNUMBER(BC75))),"Yes","No") -> No | BA75: =IF(ISNUMBER(BQ75),BQ75,IF(AND(ISNUMBER($BJ75),ISNUMBER($BK75)),BI75,"")) | BB75: =IF(ISNUMBER(BR75),BR75,IF(AND(ISNUMBER($BJ75),ISNUMBER($BK75)),BJ75,"")) | BC75: =IF(ISNUMBER(BS75),BS75,IF(AND(ISNUMBER($BJ75),ISNUMBER($BK75)),BK75,"")) | BD75: =IF(ISNUMBER(BT75),BT75,IF(AND(ISNUMBER($BO75),ISNUMBER($BP75)),BN75,"")) | BE75: =IF(ISNUMBER(BU75),BU75,IF(AND(ISNUMBER($BO75),ISNUMBER($BP75)),BO75,"")) | BF75: =IF(ISNUMBER(BV75),BV75,IF(AND(ISNUMBER($BO75),ISNUMBER($BP75)),BP75,"")) | BJ75: =IF(AND(ISNUMBER(BG75),ISNUMBER(BH75),ISNUMBER(BI75)),EXP(LOG(BI75)-1.96*SQRT((1/BG75)+(1/BH75))),"") | BK75: =IF(AND(ISNUMBER(BG75),ISNUMBER(BH75),ISNUMBER(BI75)),EXP(LOG(BI75)+1.96*SQRT((1/BG75)+(1/BH75))),"") | BO75: =IF(AND(ISNUMBER(BL75),ISNUMBER(BM75),ISNUMBER(BN75)),EXP(LOG(BN75)-1.96*SQRT((1/BL75)+(1/BM75))),"") | BP75: =IF(AND(ISNUMBER(BL75),ISNUMBER(BM75),ISNUMBER(BN75)),EXP(LOG(BN75)+1.96*SQRT((1/BL75)+(1/BM75))),"")
A76: Vittayawacharin P | B76: 2023 | C76: https://pubmed.ncbi.nlm.nih.gov/36878429 | D76: =A76&" "&B76 -> Vittayawacharin P 2023 | E76: =IF(OR(AND(ISNUMBER(AL76),ISNUMBER(CG76)),AND(ISNUMBER(AM76),ISNUMBER(CH76)),AND(ISNUMBER(AP76),ISNUMBER(AN76),ISNUMBER(AR76),ISNUMBER(CK76),ISNUMBER(CI76),ISNUMBER(CM76)),AND(ISNUMBER(AU76),ISNUMBER(AS76),ISNUMBER(AW76),ISNUMBER(CP76),ISNUMBER(CN76),ISNUMBER(CR76)),AND(ISNUMBER(BB76),ISNUMBER(BC76))),"Yes","No") -> No | BA76: =IF(ISNUMBER(BQ76),BQ76,IF(AND(ISNUMBER($BJ76),ISNUMBER($BK76)),BI76,"")) | BB76: =IF(ISNUMBER(BR76),BR76,IF(AND(ISNUMBER($BJ76),ISNUMBER($BK76)),BJ76,"")) | BC76: =IF(ISNUMBER(BS76),BS76,IF(AND(ISNUMBER($BJ76),ISNUMBER($BK76)),BK76,"")) | BD76: =IF(ISNUMBER(BT76),BT76,IF(AND(ISNUMBER($BO76),ISNUMBER($BP76)),BN76,"")) | BE76: =IF(ISNUMBER(BU76),BU76,IF(AND(ISNUMBER($BO76),ISNUMBER($BP76)),BO76,"")) | BF76: =IF(ISNUMBER(BV76),BV76,IF(AND(ISNUMBER($BO76),ISNUMBER($BP76)),BP76,"")) | BJ76: =IF(AND(ISNUMBER(BG76),ISNUMBER(BH76),ISNUMBER(BI76)),EXP(LOG(BI76)-1.96*SQRT((1/BG76)+(1/BH76))),"") | BK76: =IF(AND(ISNUMBER(BG76),ISNUMBER(BH76),ISNUMBER(BI76)),EXP(LOG(BI76)+1.96*SQRT((1/BG76)+(1/BH76))),"") | BO76: =IF(AND(ISNUMBER(BL76),ISNUMBER(BM76),ISNUMBER(BN76)),EXP(LOG(BN76)-1.96*SQRT((1/BL76)+(1/BM76))),"") | BP76: =IF(AND(ISNUMBER(BL76),ISNUMBER(BM76),ISNUMBER(BN76)),EXP(LOG(BN76)+1.96*SQRT((1/BL76)+(1/BM76))),"")
A77: Volin L | B77: 2004 | C77: https://pubmed.ncbi.nlm.nih.gov/15327521 | D77: =A77&" "&B77 -> Volin L 2004 | E77: =IF(OR(AND(ISNUMBER(AL77),ISNUMBER(CG77)),AND(ISNUMBER(AM77),ISNUMBER(CH77)),AND(ISNUMBER(AP77),ISNUMBER(AN77),ISNUMBER(AR77),ISNUMBER(CK77),ISNUMBER(CI77),ISNUMBER(CM77)),AND(ISNUMBER(AU77),ISNUMBER(AS77),ISNUMBER(AW77),ISNUMBER(CP77),ISNUMBER(CN77),ISNUMBER(CR77)),AND(ISNUMBER(BB77),ISNUMBER(BC77))),"Yes","No") -> No | BA77: =IF(ISNUMBER(BQ77),BQ77,IF(AND(ISNUMBER($BJ77),ISNUMBER($BK77)),BI77,"")) | BB77: =IF(ISNUMBER(BR77),BR77,IF(AND(ISNUMBER($BJ77),ISNUMBER($BK77)),BJ77,"")) | BC77: =IF(ISNUMBER(BS77),BS77,IF(AND(ISNUMBER($BJ77),ISNUMBER($BK77)),BK77,"")) | BD77: =IF(ISNUMBER(BT77),BT77,IF(AND(ISNUMBER($BO77),ISNUMBER($BP77)),BN77,"")) | BE77: =IF(ISNUMBER(BU77),BU77,IF(AND(ISNUMBER($BO77),ISNUMBER($BP77)),BO77,"")) | BF77: =IF(ISNUMBER(BV77),BV77,IF(AND(ISNUMBER($BO77),ISNUMBER($BP77)),BP77,"")) | BJ77: =IF(AND(ISNUMBER(BG77),ISNUMBER(BH77),ISNUMBER(BI77)),EXP(LOG(BI77)-1.96*SQRT((1/BG77)+(1/BH77))),"") | BK77: =IF(AND(ISNUMBER(BG77),ISNUMBER(BH77),ISNUMBER(BI77)),EXP(LOG(BI77)+1.96*SQRT((1/BG77)+(1/BH77))),"") | BO77: =IF(AND(ISNUMBER(BL77),ISNUMBER(BM77),ISNUMBER(BN77)),EXP(LOG(BN77)-1.96*SQRT((1/BL77)+(1/BM77))),"") | BP77: =IF(AND(ISNUMBER(BL77),ISNUMBER(BM77),ISNUMBER(BN77)),EXP(LOG(BN77)+1.96*SQRT((1/BL77)+(1/BM77))),"")
A78: Vu T | B78: 2007 | C78: https://pubmed.ncbi.nlm.nih.gov/17401392 | D78: =A78&" "&B78 -> Vu T 2007 | E78: =IF(OR(AND(ISNUMBER(AL78),ISNUMBER(CG78)),AND(ISNUMBER(AM78),ISNUMBER(CH78)),AND(ISNUMBER(AP78),ISNUMBER(AN78),ISNUMBER(AR78),ISNUMBER(CK78),ISNUMBER(CI78),ISNUMBER(CM78)),AND(ISNUMBER(AU78),ISNUMBER(AS78),ISNUMBER(AW78),ISNUMBER(CP78),ISNUMBER(CN78),ISNUMBER(CR78)),AND(ISNUMBER(BB78),ISNUMBER(BC78))),"Yes","No") -> No | BA78: =IF(ISNUMBER(BQ78),BQ78,IF(AND(ISNUMBER($BJ78),ISNUMBER($BK78)),BI78,"")) | BB78: =IF(ISNUMBER(BR78),BR78,IF(AND(ISNUMBER($BJ78),ISNUMBER($BK78)),BJ78,"")) | BC78: =IF(ISNUMBER(BS78),BS78,IF(AND(ISNUMBER($BJ78),ISNUMBER($BK78)),BK78,"")) | BD78: =IF(ISNUMBER(BT78),BT78,IF(AND(ISNUMBER($BO78),ISNUMBER($BP78)),BN78,"")) | BE78: =IF(ISNUMBER(BU78),BU78,IF(AND(ISNUMBER($BO78),ISNUMBER($BP78)),BO78,"")) | BF78: =IF(ISNUMBER(BV78),BV78,IF(AND(ISNUMBER($BO78),ISNUMBER($BP78)),BP78,"")) | BJ78: =IF(AND(ISNUMBER(BG78),ISNUMBER(BH78),ISNUMBER(BI78)),EXP(LOG(BI78)-1.96*SQRT((1/BG78)+(1/BH78))),"") | BK78: =IF(AND(ISNUMBER(BG78),ISNUMBER(BH78),ISNUMBER(BI78)),EXP(LOG(BI78)+1.96*SQRT((1/BG78)+(1/BH78))),"") | BO78: =IF(AND(ISNUMBER(BL78),ISNUMBER(BM78),ISNUMBER(BN78)),EXP(LOG(BN78)-1.96*SQRT((1/BL78)+(1/BM78))),"") | BP78: =IF(AND(ISNUMBER(BL78),ISNUMBER(BM78),ISNUMBER(BN78)),EXP(LOG(BN78)+1.96*SQRT((1/BL78)+(1/BM78))),"")
A79: Wang FZ | B79: 1999 | C79: https://pubmed.ncbi.nlm.nih.gov/10642809 | D79: =A79&" "&B79 -> Wang FZ 1999 | E79: =IF(OR(AND(ISNUMBER(AL79),ISNUMBER(CG79)),AND(ISNUMBER(AM79),ISNUMBER(CH79)),AND(ISNUMBER(AP79),ISNUMBER(AN79),ISNUMBER(AR79),ISNUMBER(CK79),ISNUMBER(CI79),ISNUMBER(CM79)),AND(ISNUMBER(AU79),ISNUMBER(AS79),ISNUMBER(AW79),ISNUMBER(CP79),ISNUMBER(CN79),ISNUMBER(CR79)),AND(ISNUMBER(BB79),ISNUMBER(BC79))),"Yes","No") -> No | BA79: =IF(ISNUMBER(BQ79),BQ79,IF(AND(ISNUMBER($BJ79),ISNUMBER($BK79)),BI79,"")) | BB79: =IF(ISNUMBER(BR79),BR79,IF(AND(ISNUMBER($BJ79),ISNUMBER($BK79)),BJ79,"")) | BC79: =IF(ISNUMBER(BS79),BS79,IF(AND(ISNUMBER($BJ79),ISNUMBER($BK79)),BK79,"")) | BD79: =IF(ISNUMBER(BT79),BT79,IF(AND(ISNUMBER($BO79),ISNUMBER($BP79)),BN79,"")) | BE79: =IF(ISNUMBER(BU79),BU79,IF(AND(ISNUMBER($BO79),ISNUMBER($BP79)),BO79,"")) | BF79: =IF(ISNUMBER(BV79),BV79,IF(AND(ISNUMBER($BO79),ISNUMBER($BP79)),BP79,"")) | BJ79: =IF(AND(ISNUMBER(BG79),ISNUMBER(BH79),ISNUMBER(BI79)),EXP(LOG(BI79)-1.96*SQRT((1/BG79)+(1/BH79))),"") | BK79: =IF(AND(ISNUMBER(BG79),ISNUMBER(BH79),ISNUMBER(BI79)),EXP(LOG(BI79)+1.96*SQRT((1/BG79)+(1/BH79))),"") | BO79: =IF(AND(ISNUMBER(BL79),ISNUMBER(BM79),ISNUMBER(BN79)),EXP(LOG(BN79)-1.96*SQRT((1/BL79)+(1/BM79))),"") | BP79: =IF(AND(ISNUMBER(BL79),ISNUMBER(BM79),ISNUMBER(BN79)),EXP(LOG(BN79)+1.96*SQRT((1/BL79)+(1/BM79))),"") | CX79: Labeled 1999b in FTR
A80: Winestone LE | B80: 2018 | C80: https://pubmed.ncbi.nlm.nih.gov/29181879 | D80: =A80&" "&B80 -> Winestone LE 2018 | E80: =IF(OR(AND(ISNUMBER(AL80),ISNUMBER(CG80)),AND(ISNUMBER(AM80),ISNUMBER(CH80)),AND(ISNUMBER(AP80),ISNUMBER(AN80),ISNUMBER(AR80),ISNUMBER(CK80),ISNUMBER(CI80),ISNUMBER(CM80)),AND(ISNUMBER(AU80),ISNUMBER(AS80),ISNUMBER(AW80),ISNUMBER(CP80),ISNUMBER(CN80),ISNUMBER(CR80)),AND(ISNUMBER(BB80),ISNUMBER(BC80))),"Yes","No") -> No | BA80: =IF(ISNUMBER(BQ80),BQ80,IF(AND(ISNUMBER($BJ80),ISNUMBER($BK80)),BI80,"")) | BB80: =IF(ISNUMBER(BR80),BR80,IF(AND(ISNUMBER($BJ80),ISNUMBER($BK80)),BJ80,"")) | BC80: =IF(ISNUMBER(BS80),BS80,IF(AND(ISNUMBER($BJ80),ISNUMBER($BK80)),BK80,"")) | BD80: =IF(ISNUMBER(BT80),BT80,IF(AND(ISNUMBER($BO80),ISNUMBER($BP80)),BN80,"")) | BE80: =IF(ISNUMBER(BU80),BU80,IF(AND(ISNUMBER($BO80),ISNUMBER($BP80)),BO80,"")) | BF80: =IF(ISNUMBER(BV80),BV80,IF(AND(ISNUMBER($BO80),ISNUMBER($BP80)),BP80,"")) | BJ80: =IF(AND(ISNUMBER(BG80),ISNUMBER(BH80),ISNUMBER(BI80)),EXP(LOG(BI80)-1.96*SQRT((1/BG80)+(1/BH80))),"") | BK80: =IF(AND(ISNUMBER(BG80),ISNUMBER(BH80),ISNUMBER(BI80)),EXP(LOG(BI80)+1.96*SQRT((1/BG80)+(1/BH80))),"") | BO80: =IF(AND(ISNUMBER(BL80),ISNUMBER(BM80),ISNUMBER(BN80)),EXP(LOG(BN80)-1.96*SQRT((1/BL80)+(1/BM80))),"") | BP80: =IF(AND(ISNUMBER(BL80),ISNUMBER(BM80),ISNUMBER(BN80)),EXP(LOG(BN80)+1.96*SQRT((1/BL80)+(1/BM80))),"")

Sheet Full-text review
A1: First Author | B1: Publication Year | C1: DOI | D1: PubMed link | E1: Excluded? | F1: Reason for exlcusion (brief) | G1: Notes
A2: Balsat M | B2: 2019 | C2: 10.1016/j.jinf.2019.05.001 | D2: https://pubmed.ncbi.nlm.nih.gov/31075291 | E2: No | G2: Fit inclusion criteria but does not provide raw data. Double check this is not available anywhere and reach out if so
A3: Betts BC | B3: 2011 | C3: 10.1016/j.bbmt.2011.04.004 | D3: https://pubmed.ncbi.nlm.nih.gov/21549850 | E3: No | I3: N patients | J3: =SUMIFS(Included!F2:F1000,Included!E2:E1000,"Yes") -> 2290
A4: Chan PK | B4: 1997 | C4: 10.1002/(sici)1096-9071(199711)53:3<295::aid-jmv20>3.0.co;2-f | D4: https://pubmed.ncbi.nlm.nih.gov/9365899 | E4: No | I4: Table 1: Patient characteristics
A5: Chevallier P | B5: 2010 | C5: 10.1038/bmt.2009.326 | D5: https://pubmed.ncbi.nlm.nih.gov/19935727 | E5: No | G5: Has comparisons for engraftment for HHV-6 pos and neg, but not raw data. Circle back / reach out | I5: Characteristic | J5: N patients
A6: Cirrone F | B6: 2016 | C6: 10.3109/10428194.2016.1157873 | D6: https://pubmed.ncbi.nlm.nih.gov/26984480 | E6: No | G6: Has comparisons for engraftment for HHV-6 pos and neg, but not raw data. Circle back / reach out | I6: Conditioning regimens
A7: de Koning C | B7: 2018 | C7: 10.1182/bloodadvances.2017012724 | D7: https://pubmed.ncbi.nlm.nih.gov/29487057 | E7: No | G7: Compares engraftment for HHV-6 pos compared to neg but does not provide raw data. Perhaps reach out | I7: RIC | J7: =SUMIFS(Included!J2:J1000,Included!E2:E1000,"Yes") -> 365
A8: de Pagter AP | B8: 2012 | C8: 10.1016/j.clim.2012.06.006 | D8: https://pubmed.ncbi.nlm.nih.gov/22820131 | E8: No | G8: Compares engraftment for HHV-6 pos compared to neg but does not provide raw data. Perhaps reach out | I8: MAC | J8: =SUMIFS(Included!K2:K1000,Included!E2:E1000,"Yes") -> 622
A9: Drobyski WR | B9: 1993 | C9: 10.1093/infdis/167.3.735 | D9: https://pubmed.ncbi.nlm.nih.gov/8382723 | E9: No | I9: Unclear | J9: =SUMIFS(Included!L2:L1000,Included!E2:E1000,"Yes") -> 168
A10: Dulery R | B10: 2012 | C10: 10.1016/j.bbmt.2011.12.579 | D10: https://pubmed.ncbi.nlm.nih.gov/22212513 | E10: No | G10: Compares engraftment for HHV-6 pos and neg, but does not give raw data. Perhaps reach out | I10: Antiviral PPX
A11: Düver F | B11: 2020 | C11: 10.1371/journal.pone.0228451 | D11: https://pubmed.ncbi.nlm.nih.gov/32017805 | E11: No | I11: AYC | J11: =SUMIFS(Included!M2:M1000,Included!E2:E1000,"Yes") -> 1051
A12: Dzieciątkowski T | B12: 2010 | C12: 10.1007/s00005-010-0096-8 | D12: https://pubmed.ncbi.nlm.nih.gov/20872080 | E12: No | I12: GAN | J12: =SUMIFS(Included!N2:N1000,Included!E2:E1000,"Yes") -> 0
A13: El Jurdi N | B13: 2021 | C13: 10.1016/j.bbmt.2020.10.008 | D13: https://pubmed.ncbi.nlm.nih.gov/33053448 | E13: No | I13: FOS | J13: =SUMIFS(Included!O2:O1000,Included!E2:E1000,"Yes") -> 0
A14: Fule Robles JD | B14: 2014 | C14: 10.12659/AOT.889995 | D14: https://pubmed.ncbi.nlm.nih.gov/24881673 | E14: No | G14: Has days to neutrophil and platelet engraftment as well as HHV-6 status, but not together. Perhaps reach out | I14: Unclear | J14: =SUMIFS(Included!P2:P1000,Included!E2:E1000,"Yes") -> 1239 | Q14: =L14&M14&N14&O14&P14
A15: Gasior M | B15: 2021 | C15: 10.1111/trf.16354 | D15: https://pubmed.ncbi.nlm.nih.gov/33713461 | E15: No | G15: Has engraftment and HHV-6 data but not together. Maybe reach out | I15: GVHD PPX: | Q15: =L15&M15&N15&O15&P15
A16: Gomes de Oliveira PG | B16: 2016 | C16: 10.1097/TP.0000000000000986 | D16: https://pubmed.ncbi.nlm.nih.gov/26555946 | E16: No | I16: Cyclosporine | J16: =SUMIFS(Included!Q2:Q1000,Included!E2:E1000,"Yes") -> 122 | Q16: =L16&M16&N16&O16&P16
A17: Gotoh M | B17: 2014 | C17: 10.1111/tid.12229 | D17: https://pubmed.ncbi.nlm.nih.gov/24810656 | E17: No | I17: CsA+MMF | J17: =SUMIFS(Included!R2:R1000,Included!E2:E1000,"Yes") -> 120 | Q17: =L17&M17&N17&O17&P17
A18: Greco R | B18: 2016 | C18: 10.1016/j.bbmt.2016.09.018 | D18: https://pubmed.ncbi.nlm.nih.gov/27697585 | E18: No | G18: Gives N delayed engraftment for HHV-6 pos, but not neg. Perhaps reach out | I18: CsA+MMF+MTX | J18: =SUMIFS(Included!S2:S1000,Included!E2:E1000,"Yes") -> 174 | Q18: =L18&M18&N18&O18&P18
A19: Han TT | B19: 2021 | C19: 10.1111/tid.13544 | D19: https://pubmed.ncbi.nlm.nih.gov/33326670 | E19: No | I19: CsA+MTX | J19: =SUMIFS(Included!T2:T1000,Included!E2:E1000,"Yes") -> 97 | Q19: =L19&M19&N19&O19&P19
A20: Hentrich M | B20: 2005 | C20: 10.1111/j.1365-2141.2004.05254.x | D20: https://pubmed.ncbi.nlm.nih.gov/15606551 | E20: No | I20: Cyclophosphamide | J20: =SUMIFS(Included!U2:U1000,Included!E2:E1000,"Yes") -> 9 | Q20: =L20&M20&N20&O20&P20
A21: Hill JA | B21: 2024 | C21: 10.1038/s41467-024-44828-9 | D21: https://pubmed.ncbi.nlm.nih.gov/38228644 | E21: No | G21: Has ANC and HHV-6 status, but not an engraftment definition. Perhaps reach out | I21: Cy+CsA+MMF | J21: =SUMIFS(Included!V2:V1000,Included!E2:E1000,"Yes") -> 110 | Q21: =L21&M21&N21&O21&P21
A22: Hill JA | B22: 2018 | C22: 10.1093/cid/cix804 | D22: https://pubmed.ncbi.nlm.nih.gov/29020348 | E22: No | G22: Has engraftment data and HHV-6 status, but not raw data. Perhaps reach out | I22: MMF | J22: =SUMIFS(Included!X2:X1000,Included!E2:E1000,"Yes") -> 86 | Q22: =L22&M22&N22&O22&P22
A23: Iesato K | B23: 2018 | C23: 10.1111/ped.13551 | D23: https://pubmed.ncbi.nlm.nih.gov/29542206 | E23: No | G23: Has engraftment data and HHV-6 status, but not raw data. Perhaps reach out | I23: TAC+MTX | J23: =SUMIFS(Included!Y2:Y1000,Included!E2:E1000,"Yes") -> 3 | Q23: =L23&M23&N23&O23&P23
A24: Iino M | B24: 2021 | C24: 10.1016/j.transproceed.2020.10.018 | D24: https://pubmed.ncbi.nlm.nih.gov/33308840 | E24: No | G24: Has engraftment data and HHV-6 status, but not raw data. Perhaps reach out | I24: CAMPATH-1 | J24: =SUMIFS(Included!Z2:Z1000,Included!E2:E1000,"Yes") -> 8 | Q24: =L24&M24&N24&O24&P24
A25: Illiaquer M | B25: 2014 | C25: 10.1093/infdis/jiu129 | D25: https://pubmed.ncbi.nlm.nih.gov/24596281 | E25: No | G25: Has engraftment data and HHV-6 status, but not raw data. Perhaps reach out | I25: Unclear | J25: =SUMIFS(Included!AA2:AA1000,Included!E2:E1000,"Yes") -> 590 | Q25: =L25&M25&N25&O25&P25
A26: Illiaquer M | B26: 2017 | C26: 10.1016/j.jcv.2017.05.019 | D26: https://pubmed.ncbi.nlm.nih.gov/28601677 | E26: No | G26: Has engraftment data and HHV-6 status, but not raw data. Perhaps reach out | I26: Transplant type
A27: Imbert-Marcille BM | B27: 2000 | C27: 10.1086/318142 | D27: https://pubmed.ncbi.nlm.nih.gov/11049765 | E27: No | G27: Has engraftment data and HHV-6 status, but not raw data. Perhaps reach out | I27: BM | J27: =SUMIFS(Included!AB2:AB1000,Included!E2:E1000,"Yes") -> 961
A28: Inazawa N | B28: 2017 | C28: 10.1002/jmv.24621 | D28: https://pubmed.ncbi.nlm.nih.gov/27364410 | E28: No | G28: Has engraftment data and HHV-6 status, but not raw data. Perhaps reach out | I28: PBSC | J28: =SUMIFS(Included!AC2:AC1000,Included!E2:E1000,"Yes") -> 815
A29: Ishiyama K | B29: 2011 | C29: 10.1038/bmt.2010.201 | D29: https://pubmed.ncbi.nlm.nih.gov/20838386 | E29: No | G29: Has engraftment data and HHV-6 status, but not raw data. Perhaps reach out | I29: CBT | J29: =SUMIFS(Included!AD2:AD1000,Included!E2:E1000,"Yes") -> 248
A30: Jeulin H | B30: 2013 | C30: 10.1097/TP.0b013e318289958b | D30: https://pubmed.ncbi.nlm.nih.gov/23514960 | E30: No | G30: Gives N HHV-6 pos with delayed engraftment, but not neg. Perhaps reach out | I30: Unclear | J30: =SUMIFS(Included!AE2:AE1000,Included!E2:E1000,"Yes") -> 221
A31: Kadakia MP | B31: 1996 | C31: 87(12):5341-54 | D31: https://pubmed.ncbi.nlm.nih.gov/8652850 | E31: No | G31: Gives N HHV-6 pos with delayed engraftment, but not neg. Perhaps reach out (but this was published in 1996)
A32: Kageyama K | B32: 2021 | C32: 10.1038/s41409-020-01028-5 | D32: https://pubmed.ncbi.nlm.nih.gov/32782352 | E32: No | G32: Has HHV-6 status and engraftment, but not raw data. Perhaps reach out
A33: Khimani F | B33: 2021 | C33: 10.1016/j.jtct.2021.07.023 | D33: https://pubmed.ncbi.nlm.nih.gov/34329754 | E33: No | G33: Has HHV-6 status and engraftment, but not raw data. Perhaps reach out
A34: Laskin BL | B34: 2013 | C34: 10.1016/j.bbmt.2013.05.002 | D34: https://pubmed.ncbi.nlm.nih.gov/23665115 | E34: No | G34: Has HHV-6 status and engraftment, but not raw data. Perhaps reach out
A35: Le Bourgeois A | B35: 2014 | C35: 10.1016/j.exphem.2014.07.264 | D35: https://pubmed.ncbi.nlm.nih.gov/25072620 | E35: No
A36: Lee DG | B36: 2003 | C36: 16(3):307-15 | D36: https://pubmed.ncbi.nlm.nih.gov/14744020 | E36: No | G36: Has engraftment data for HHV-6 pos, but not neg. Perhaps reach out (but this is 20+ years old)
A37: Lee YJ | B37: 2022 | C37: 10.1093/infdis/jiab412 | D37: https://pubmed.ncbi.nlm.nih.gov/34390240 | E37: No | G37: Has HHV-6 status and engraftment, but not raw data. Perhaps reach out
A38: Linder KA | B38: 2019 | C38: 10.1093/ofid/ofz037 | D38: https://pubmed.ncbi.nlm.nih.gov/30815505 | E38: No | G38: Has HHV-6 status and engraftment, but not raw data. Perhaps reach out
A39: Ljungman P | B39: 2000 | C39: 111(3):774-81 | D39: https://pubmed.ncbi.nlm.nih.gov/11122137 | E39: No | G39: Has HHV-6 status and engraftment, but not raw data. Perhaps reach out
A40: Ma XT | B40: 2001 | C40: 86.3 (2001): 329-330 | D40: https://scholar.google.com/scholar?hl=en&as_sdt=0%2C5&q=The+role+of+human+herpesvirus-6+in+delayed+engraftment+in+stem+cell+transplant+patients+in+China&btnG= | E40: No | G40: Has HHV-6 status and engraftment, but not raw data. Perhaps reach out
A41: Maeda Y | B41: 1999 | C41: 105(1):295-302 | D41: https://pubmed.ncbi.nlm.nih.gov/10233397 | E41: No | G41: Has HHV-6 status and engraftment, but not raw data to my reading. The data are reported in a confusing way so way be worth a second pair of eyes here. Perhaps reach out
A42: Miranda-Silva W | B42: 2023 | C42: 10.1111/odi.14022 | D42: https://pubmed.ncbi.nlm.nih.gov/34523191 | E42: No
A43: Miura H | B43: 2015 | C43: 10.1097/INF.0000000000000777 | D43: https://pubmed.ncbi.nlm.nih.gov/26083588 | E43: No | G43: Mentions HHV-6 status and neutrophil recovery, but does not give raw data for either. Perhaps reach out
A44: Muranushi H | B44: 2020 | C44: 10.1111/bcp.14354 | D44: https://pubmed.ncbi.nlm.nih.gov/32386102 | E44: No | G44: Has HHV-6 status and engraftment data, but not raw data. Perhaps reach out
A45: Mutlu D | B45: 2014 | C45: 10.5144/0256-4947.2014.6 | D45: https://pubmed.ncbi.nlm.nih.gov/24658548 | E45: No | G45: Has HHV-6 status and engraftment data, but not raw data. Perhaps reach out
A46: Noviello M | B46: 2023 | C46: 10.1182/bloodadvances.2022009274 | D46: https://pubmed.ncbi.nlm.nih.gov/37067947 | E46: No | G46: Has N delayed engraftment for HHV-6 pos, but not neg. Perhaps reach out
A47: Ogata M | B47: 2006 | C47: 10.1086/498531 | D47: https://pubmed.ncbi.nlm.nih.gov/16323134 | E47: No
A48: Ogata M | B48: 2018 | C48: 10.1016/j.bbmt.2018.02.008 | D48: https://pubmed.ncbi.nlm.nih.gov/29454651 | E48: No | G48: Has HHV-6 status and engraftment data, but not raw data. Perhaps reach out
A49: Ohyashiki JH | B49: 2000 | C49: 10.3892/ijmm.6.4.427 | D49: https://pubmed.ncbi.nlm.nih.gov/10998432 | E49: No
A50: Olson AL | B50: 2014 | C50: 10.1016/j.bbmt.2014.02.010 | D50: https://pubmed.ncbi.nlm.nih.gov/24548875 | E50: No | G50: Has HHV-6 status and engraftment data, but not raw data. Perhaps reach out
A51: Oltolini C | B51: 2020 | C51: 10.1016/j.bbmt.2020.01.013 | D51: https://pubmed.ncbi.nlm.nih.gov/32004700 | E51: No | G51: Has HHV-6 status and engraftment data, but not raw data. Perhaps reach out
A52: Pawlowska AB | B52: 2021 | C52: 10.1111/tid.13453 | D52: https://pubmed.ncbi.nlm.nih.gov/32860467 | E52: No | G52: Has HHV-6 status and engraftment data, but not raw data. Perhaps reach out
A53: Perissinotti AJ | B53: 2015 | C53: 10.1177/1078155213519837 | D53: https://pubmed.ncbi.nlm.nih.gov/24407957 | E53: No | G53: Has HHV-6 status and N HHV-6 pos with delayed engraftment, but not neg. Perhaps reach out
A54: Perruccio K | B54: 2018 | C54: 10.1016/j.bbmt.2018.07.033 | D54: https://pubmed.ncbi.nlm.nih.gov/30067953 | E54: No | G54: Has HHV-6 status and engraftment, but not raw data. Perhaps reach out
A55: Potenza L | B55: 2009 | C55: 10.1111/j.1600-6143.2009.02685.x | D55: https://pubmed.ncbi.nlm.nih.gov/19519818 | E55: No | G55: Has HHV-6 status and N pos with thrombocytopenia, but not neg
A56: Quintela A | B56: 2016 | C56: 10.1016/j.jinf.2015.09.039 | D56: https://pubmed.ncbi.nlm.nih.gov/26518057 | E56: No | G56: Has HHV-6 status and engraftment, but not raw data. Perhaps reach out
A57: Radonić A | B57: 2005 | C57: 10.1111/j.1365-2141.2005.05788.x | D57: https://pubmed.ncbi.nlm.nih.gov/16281938 | E57: No | G57: Has HHV-6 status and engraftment, but not raw data. Perhaps reach out
A58: Raouf MME | B58: 2023 | C58: 10.1186/s12985-023-01980-w | D58: https://pubmed.ncbi.nlm.nih.gov/36739398 | E58: No
A59: Rapaport D | B59: 2002 | C59: 10.1034/j.1399-3062.2002.040101.x | D59: https://pubmed.ncbi.nlm.nih.gov/12123421 | E59: No
A60: Savolainen H | B60: 2005 | C60: 10.1002/pbc.20337 | D60: https://pubmed.ncbi.nlm.nih.gov/15700258 | E60: No
A61: Schönberger S | B61: 2010 | C61: 10.1016/j.bbmt.2010.04.008 | D61: https://pubmed.ncbi.nlm.nih.gov/20399877 | E61: No | G61: Has HHV-6 status and engraftment data, but not raw data. Perhaps reach out
A62: Secchiero P | B62: 1995 | C62: 10.1093/infdis/171.2.273 | D62: https://pubmed.ncbi.nlm.nih.gov/7844362 | E62: No | G62: Has HHV-6 status and N pos with "poor engraftment", but not neg
A63: Silcock R | B63: 2021 | C63: 10.1111/tid.13580 | D63: https://pubmed.ncbi.nlm.nih.gov/33533068 | E63: No | G63: Has HHV-6 status and engraftment data, but not raw data. Perhaps raw data
A64: Sisinni L | B64: 2018 | C64: 10.1016/j.bbmt.2018.07.016 | D64: https://pubmed.ncbi.nlm.nih.gov/30031939 | E64: No | G64: Has HHV-6 status and engraftment data, but not raw data. Perhaps raw data
A65: Takatsuka H | B65: 2001 | C65: 10.1080/10245332.2001.11746541 | D65: https://pubmed.ncbi.nlm.nih.gov/27419347 | E65: No | G65: Has HHV-6 status and describes 2 cases of possible delayed engraftment, but does not explicitly daignose delayed engraftment. Does not include this for HHV-6 neg
A66: Tang FF | B66: 2020 | C66: 10.1016/j.bbmt.2019.10.031 | D66: https://pubmed.ncbi.nlm.nih.gov/31704470 | E66: No | G66: Has HHV-6 status and engraftment, but not raw data. Perhaps reach out
A67: Tormo N | B67: 2010 | C67: 10.1016/j.bbmt.2009.12.003 | D67: https://pubmed.ncbi.nlm.nih.gov/20005968 | E67: No | G67: Has HHV-6 status and engraftment, but not raw data. Perhaps reach out
A68: Verhoeven DH | B68: 2015 | C68: 10.1097/INF.0000000000000824 | D68: https://pubmed.ncbi.nlm.nih.gov/26132825 | E68: No | G68: Has HHV-6 status and engraftment data, but not raw data. Perhaps reach out
A69: Violago L | B69: 2015 | C69: 10.1111/petr.12572 | D69: https://pubmed.ncbi.nlm.nih.gov/26329541 | E69: No
A70: Vittayawacharin P | B70: 2023 | C70: 10.1016/j.jtct.2023.02.022 | D70: https://pubmed.ncbi.nlm.nih.gov/36878429 | E70: No | G70: Has HHV-6 status and engraftment data, but not raw data. Perhaps reach out
A71: Volin L | B71: 2004 | C71: 10.1111/j.1365-2141.2004.05101.x | D71: https://pubmed.ncbi.nlm.nih.gov/15327521 | E71: No | G71: Has N delayed engraftment for HHV-6 pos and does not explicitly say no delayed engraftment for HHV-6 neg but in context that might be a reasonable interpretation
A72: Vu T | B72: 2007 | C72: 10.1038/sj.bmt.1705666 | D72: https://pubmed.ncbi.nlm.nih.gov/17401392 | E72: No | G72: Has HHV-6 status and engraftment data, but not raw data. Perhaps reach out
A73: Wang FZ | B73: 1999 | C73: 10.1038/sj.bmt.1702058 | D73: https://pubmed.ncbi.nlm.nih.gov/10642809 | E73: No | G73: Labeled as 1999b in FTR. Has HHV-6 status and engraftment data, but not raw data. Perhaps reach out (20+)
A74: Wang FZ | B74: 1996 | C74: 88(9):3615-20 | D74: https://pubmed.ncbi.nlm.nih.gov/8896431 | E74: No | G74: Gives raw data for delayed engraftment for HHV-6 pos and neg, but gives as per sample instead of per patient
A75: Wang LR | B75: 2006 | C75: 10.1016/j.bbmt.2006.06.001 | D75: https://pubmed.ncbi.nlm.nih.gov/17067909 | E75: No | G75: Labeled as 2006a in FTR
A76: Winestone LE | B76: 2018 | C76: 10.1111/petr.13084 | D76: https://pubmed.ncbi.nlm.nih.gov/29181879 | E76: No | G76: Has N HHV-6 pos with delayed engraftment, but not neg. Perhaps reach out
A77: Yoshikawa T | B77: 2002 | C77: 10.1086/339411 | D77: https://pubmed.ncbi.nlm.nih.gov/11920307 | E77: No | G77: Has HHV-6 status and engraftment data, but not raw data. Perhaps reach out (20+ years old)
A78: Zerr DM | B78: 2005 | C78: 10.1086/428060 | D78: https://pubmed.ncbi.nlm.nih.gov/15824982 | E78: No | G78: Has HHV-6 status and engraftment data, but not raw data. Perhaps reach out
A79: Mata JR | B79: 2024 | C79: 10.1016/j.jtct.2024.03.018 | D79: https://pubmed.ncbi.nlm.nih.gov/38521411 | E79: No | G79: Added 7/7/24
A80: Paviglianiti A | B80: 2024 | C80: 10.46989/001c.92525 | D80: https://pubmed.ncbi.nlm.nih.gov/38817703 | E80: No | G80: Added 7/7/24
A81: Abidi MZ | B81: 2019 | C81: 10.1038/s41409-019-0457-9 | D81: https://pubmed.ncbi.nlm.nih.gov/30696997 | E81: Yes | F81: Article does not describe at least one type of delayed or failed engraftment for the number of HCT recipients with and without HHV-6
A82: Admiraal R | B82: 2017 | C82: 10.1016/j.jaci.2016.12.992 | D82: https://pubmed.ncbi.nlm.nih.gov/28392330 | E82: Yes | F82: Article does not describe at least one type of delayed or failed engraftment for the number of HCT recipients with and without HHV-6 | G82: Update - this does not have the data we need. Circle back. This is super close but does not appear to have the raw data we would need. Perhaps reach out to author.
A83: Alexandersson A | B83: 2019 | C83: 10.1080/23744235.2019.1650198 | D83: https://pubmed.ncbi.nlm.nih.gov/31380705 | E83: Yes | F83: Article does not describe at least one type of delayed or failed engraftment for the number of HCT recipients with and without HHV-6 | G83: Update - this does not have the data we need. Circle back. This is super close but does not appear to have the raw data we would need. Perhaps reach out to author
A84: Allen UD | B84: 2001 | C84: 10.1038/sj.bmt.1703153 | D84: https://pubmed.ncbi.nlm.nih.gov/11593320 | E84: Yes | F84: Article does not describe at least one type of delayed or failed engraftment for the number of HCT recipients with and without HHV-6 | G84: Update - this does not have the data we need. Touches on BM suppression, but not delayed engraftment. Maybe useful?
A85: Aoki J | B85: 2015 | C85: 10.1016/j.bbmt.2015.07.022 | D85: https://pubmed.ncbi.nlm.nih.gov/26226409 | E85: Yes | F85: Article does not describe at least one type of delayed or failed engraftment for the number of HCT recipients with and without HHV-6 | G85: Provides HR for neutrophil and platelet engraftment by HHV-6 detection. Perhaps reach out to authors for raw data
A86: Appleton AL | B86: 1995 | C86: 16(6):777-82 | D86: https://pubmed.ncbi.nlm.nih.gov/8750269 | E86: Yes | F86: No full text available
A87: Asano Y | B87: 1991 | C87: 10.1056/NEJM199102283240915 | D87: https://pubmed.ncbi.nlm.nih.gov/1846942 | E87: Yes | F87: Article does not describe at least one type of delayed or failed engraftment for the number of HCT recipients with and without HHV-6
A88: Atay D | B88: 2018 | C88: 10.1111/petr.13109 | D88: https://pubmed.ncbi.nlm.nih.gov/29297965 | E88: Yes | F88: Article does not describe at least one type of delayed or failed engraftment for the number of HCT recipients with and without HHV-6 | G88: Provides general engraftment data not given by HHV-6 pos and neg
A89: Baker M | B89: 2016 | C89: 10.1016/j.bbmt.2016.08.003 | D89: https://pubmed.ncbi.nlm.nih.gov/27522040 | E89: Yes | F89: Article does not describe at least one type of delayed or failed engraftment for the number of HCT recipients with and without HHV-6 | G89: Provides general engraftment data not given by HHV-6 pos and neg
A90: Bartelink IH | B90: 2014 | C90: 10.1016/j.bbmt.2013.11.027 | D90: https://pubmed.ncbi.nlm.nih.gov/24315842 | E90: Yes | F90: Article does not describe at least one type of delayed or failed engraftment for the number of HCT recipients with and without HHV-6 | G90: Has number of patients with delayed engraftment and HHV-6 pos and neg, but not together. Maybe reach out
A91: Behzad-Behbahani A | B91: 2008 | C91: 10.4103/0255-0857.42038 | D91: https://pubmed.ncbi.nlm.nih.gov/18695326 | E91: Yes | F91: Article does not describe at least one type of delayed or failed engraftment for the number of HCT recipients with and without HHV-6
A92: Behzad-Behbahani A | B92: 2005 | C92: 10.1016/j.transproceed.2005.07.007 | D92: https://pubmed.ncbi.nlm.nih.gov/16213350 | E92: Yes | F92: Article does not describe at least one type of delayed or failed engraftment for the number of HCT recipients with and without HHV-6
A93: Bejanyan N | B93: 2021 | C93: 10.1016/j.jtct.2020.11.014 | D93: https://pubmed.ncbi.nlm.nih.gov/33718897 | E93: Yes | F93: Article does not describe at least one type of delayed or failed engraftment for the number of HCT recipients with and without HHV-6 | G93: Gives engraftment data but not by HHV-6 pos and neg
A94: Berneking L | B94: 2022 | C94: 10.1111/tid.13836 | D94: https://pubmed.ncbi.nlm.nih.gov/35389547 | E94: Yes | F94: Article does not describe at least one type of delayed or failed engraftment for the number of HCT recipients with and without HHV-6 | G94: Gives HHV-6 viral load and after engraftment. I don't think we can get much from that
A95: Berzero G | B95: 2021 | C95: 10.1212/NXI.0000000000000942 | D95: https://pubmed.ncbi.nlm.nih.gov/33587722 | E95: Yes | F95: Article does not describe at least one type of delayed or failed engraftment for the number of HCT recipients with and without HHV-6
A96: Bhanushali MJ | B96: 2013 | C96: 10.1212/WNL.0b013e31828cf8a2 | D96: https://pubmed.ncbi.nlm.nih.gov/23516318 | E96: Yes | F96: Article does not describe at least one type of delayed or failed engraftment for the number of HCT recipients with and without HHV-6
A97: Bogunia-Kubik K | B97: 2015 | C97: 10.1016/j.cyto.2015.05.001 | D97: https://pubmed.ncbi.nlm.nih.gov/25982843 | E97: Yes | F97: Article does not describe at least one type of delayed or failed engraftment for the number of HCT recipients with and without HHV-6
A98: Boutolleau D | B98: 2003 | C98: 10.1086/367677 | D98: https://pubmed.ncbi.nlm.nih.gov/12552442 | E98: Yes | F98: Article does not describe at least one type of delayed or failed engraftment for the number of HCT recipients with and without HHV-6 | G98: Gives HHV-6 median load for patients with delayed engraftment, but not delayed engraftment for HHV-6 pos and neg
A99: Brands-Nijenhuis AV | B99: 2011 | C99: 10.1038/bmt.2010.245 | D99: https://pubmed.ncbi.nlm.nih.gov/20956957 | E99: Yes | F99: Article does not describe primary data for a cohort of HCT recipients
A100: Buchbinder S | B100: 2000 | C100: 10.1038/sj.bmt.1702569 | D100: https://pubmed.ncbi.nlm.nih.gov/11035370 | E100: Yes | F100: Article does not describe at least one type of delayed or failed engraftment for the number of HCT recipients with and without HHV-6 | G100: Gives median time to engrfatment for HHV-6 pos, no HHV-6 neg. Maybe reach out to authors
...

Sheet Screening
A1: First Author | B1: Publication Year | C1: DOI | D1: PubMed link | E1: Excluded? | F1: Reason for exlcusion (brief) | G1: Notes
A2: Abidi MZ | B2: 2019 | C2: 10.1038/s41409-019-0457-9 | D2: https://pubmed.ncbi.nlm.nih.gov/30696997 | E2: No | H2: Figure 1 caption
A3: Admiraal R | B3: 2017 | C3: 10.1016/j.jaci.2016.12.992 | D3: https://pubmed.ncbi.nlm.nih.gov/28392330 | E3: No | H3: n results | I3: =COUNTA(A2:A2000) -> 1742
A4: Alexandersson A | B4: 2019 | C4: 10.1080/23744235.2019.1650198 | D4: https://pubmed.ncbi.nlm.nih.gov/31380705 | E4: No | H4: n screened | I4: =COUNTIF(E2:E2000,"Yes")+COUNTIF(E2:E2000,"No") -> 1742
A5: Allen UD | B5: 2001 | C5: 10.1038/sj.bmt.1703153 | D5: https://pubmed.ncbi.nlm.nih.gov/11593320 | E5: No | H5: n excluded in screening | I5: =COUNTIF(E2:E2000,"Yes") -> 1458
A6: Aoki J | B6: 2015 | C6: 10.1016/j.bbmt.2015.07.022 | D6: https://pubmed.ncbi.nlm.nih.gov/26226409 | E6: No | H6: Brief reasons for exclusion in screening:
A7: Appleton AL | B7: 1995 | C7: 16(6):777-82 | D7: https://pubmed.ncbi.nlm.nih.gov/8750269 | E7: No | H7: Article does not describe primary data for a cohort of HCT recipients | I7: =COUNTIF(F2:F2000,H7) -> 1343
A8: Asano Y | B8: 1991 | C8: 10.1056/NEJM199102283240915 | D8: https://pubmed.ncbi.nlm.nih.gov/1846942 | E8: No | H8: Article does not describe the number of HCT recipients with and without HHV-6 | I8: =COUNTIF(F2:F2000,H8) -> 0
A9: Atay D | B9: 2018 | C9: 10.1111/petr.13109 | D9: https://pubmed.ncbi.nlm.nih.gov/29297965 | E9: No | H9: Article does not describe at least one type of delayed or failed engraftment for the number of HCT recipients with and without HHV-6 | I9: =COUNTIF(F2:F2000,H9) -> 0
A10: Baker M | B10: 2016 | C10: 10.1016/j.bbmt.2016.08.003 | D10: https://pubmed.ncbi.nlm.nih.gov/27522040 | E10: No | H10: Not in Engish | I10: =COUNTIF(F2:F2000,H10) -> 113
A11: Balsat M | B11: 2019 | C11: 10.1016/j.jinf.2019.05.001 | D11: https://pubmed.ncbi.nlm.nih.gov/31075291 | E11: No | H11: Retracted article | I11: =COUNTIF(F2:F2000,H11) -> 2 | J11: =IF(SUM(I7:I11)<>I5,"reasons do NOT add up","validated: reasons add up") -> validated: reasons add up
A12: Bartelink IH | B12: 2014 | C12: 10.1016/j.bbmt.2013.11.027 | D12: https://pubmed.ncbi.nlm.nih.gov/24315842 | E12: No | H12: n full text review | I12: =COUNTIF(E2:E2000,"No") -> 284 | J12: =IF(SUM(I12,I5)<>I4,"included and excluded do NOT add up","validated: included/exlcuded add up") -> validated: included/exlcuded add up
A13: Behzad-Behbahani A | B13: 2008 | C13: 10.4103/0255-0857.42038 | D13: https://pubmed.ncbi.nlm.nih.gov/18695326 | E13: No | H13: n excluded in full text revew | I13: =COUNTIF('Full-text review'!E2:E2000,"Yes") -> 205
A14: Behzad-Behbahani A | B14: 2005 | C14: 10.1016/j.transproceed.2005.07.007 | D14: https://pubmed.ncbi.nlm.nih.gov/16213350 | E14: No | H14: Brief reasons for exclusion in full text review:
A15: Bejanyan N | B15: 2021 | C15: 10.1016/j.jtct.2020.11.014 | D15: https://pubmed.ncbi.nlm.nih.gov/33718897 | E15: No | H15: No full text available | I15: =COUNTIF('Full-text review'!F2:F2000,H15) -> 5
A16: Berneking L | B16: 2022 | C16: 10.1111/tid.13836 | D16: https://pubmed.ncbi.nlm.nih.gov/35389547 | E16: No | H16: HHV-6 positivity or disease was criteria for inclusion, percluding analysis | I16: =COUNTIF('Full-text review'!F2:F2000,H16) -> 20
A17: Berzero G | B17: 2021 | C17: 10.1212/NXI.0000000000000942 | D17: https://pubmed.ncbi.nlm.nih.gov/33587722 | E17: No | H17: Article does not describe primary data for a cohort of HCT recipients | I17: =COUNTIF('Full-text review'!F2:F2000,H17) -> 16
A18: Betts BC | B18: 2011 | C18: 10.1016/j.bbmt.2011.04.004 | D18: https://pubmed.ncbi.nlm.nih.gov/21549850 | E18: No | H18: Article does not describe the number of HCT recipients with and without HHV-6 | I18: =COUNTIF('Full-text review'!F2:F2000,H18) -> 1
A19: Bhanushali MJ | B19: 2013 | C19: 10.1212/WNL.0b013e31828cf8a2 | D19: https://pubmed.ncbi.nlm.nih.gov/23516318 | E19: No | H19: Article does not describe at least one type of delayed or failed engraftment for the number of HCT recipients with and without HHV-6 | I19: =COUNTIF('Full-text review'!F2:F2000,H19) -> 160
A20: Bogunia-Kubik K | B20: 2015 | C20: 10.1016/j.cyto.2015.05.001 | D20: https://pubmed.ncbi.nlm.nih.gov/25982843 | E20: No | H20: Not in Engish | I20: =COUNTIF('Full-text review'!F2:F2000,H20) -> 0
A21: Boutolleau D | B21: 2003 | C21: 10.1086/367677 | D21: https://pubmed.ncbi.nlm.nih.gov/12552442 | E21: No | H21: Retracted article | I21: =COUNTIF('Full-text review'!F2:F2000,H21) -> 0
A22: Brands-Nijenhuis AV | B22: 2011 | C22: 10.1038/bmt.2010.245 | D22: https://pubmed.ncbi.nlm.nih.gov/20956957 | E22: No | H22: Chromosomally integrated HHV-6 was criteria for inclusion, precluding analysis | I22: =COUNTIF('Full-text review'!F2:F2000,H22) -> 3 | J22: =IF(SUM(I15:I22)<>COUNTIF('Full-text review'!E:E,"Yes"),"reasons do NOT add up","validated: reasons add up") -> validated: reasons add up
A23: Buchbinder S | B23: 2000 | C23: 10.1038/sj.bmt.1702569 | D23: https://pubmed.ncbi.nlm.nih.gov/11035370 | E23: No | H23: n met inclusion criteria | I23: =COUNTIF('Full-text review'!E2:E2000,"No") -> 79 | J23: =IF(SUM(I15:I23)<>COUNTA('Full-text review'!E2:E2000),"included and excluded do NOT add up","validated: included/exlcuded add up") -> validated: included/exlcuded add up
A24: Carrigan DR | B24: 1994 | C24: 84(10):3307-10 | D24: https://pubmed.ncbi.nlm.nih.gov/7949085 | E24: No | H24: n excluded from analysis | I24: =COUNTIF(Included!E2:E2000,"No") -> 58
A25: Castagna L | B25: 2021 | C25: 10.1016/j.jtct.2021.03.010 | D25: https://pubmed.ncbi.nlm.nih.gov/33819481 | E25: No | H25: Reasons for exclusion from analysis:
A26: Chan PK | B26: 1997 | C26: 10.1002/(sici)1096-9071(199711)53:3<295::aid-jmv20>3.0.co;2-f | D26: https://pubmed.ncbi.nlm.nih.gov/9365899 | E26: No | H26: Study discussed HHV-6 status and engraftment after HSCT, but did not provide data required for inclusion in statistical analyses | I26: =COUNTIF(Included!E2:E2000,"No") -> 58 | J26: =IF(SUM(I26)<>COUNTIF(Included!E:E,"No"),"reasons do NOT add up","validated: reasons add up") -> validated: reasons add up
A27: Chan PK | B27: 2004 | C27: 10.1002/jmv.20032 | D27: https://pubmed.ncbi.nlm.nih.gov/14981771 | E27: No | H27: N included in analyses | I27: =COUNTIF(Included!E2:E2000,"Yes") -> 21 | J27: =IF(SUM(I26:I27)<>COUNTA(Included!E2:E2000),"included and excluded do NOT add up","validated: included/exlcuded add up") -> validated: included/exlcuded add up
A28: Chapenko S | B28: 2012 | C28: 10.1002/jmv.23412 | D28: https://pubmed.ncbi.nlm.nih.gov/23080502 | E28: No
A29: Cheng FW | B29: 2010 | C29: 10.1111/j.1399-3046.2010.01333.x | D29: https://pubmed.ncbi.nlm.nih.gov/20534025 | E29: No
A30: Cheng FW | B30: 2010 | C30: 10.1111/j.1399-3046.2009.01253.x | D30: https://pubmed.ncbi.nlm.nih.gov/19843234 | E30: No
A31: Chevallier P | B31: 2010 | C31: 10.1038/bmt.2009.326 | D31: https://pubmed.ncbi.nlm.nih.gov/19935727 | E31: No
A32: Cirrone F | B32: 2016 | C32: 10.3109/10428194.2016.1157873 | D32: https://pubmed.ncbi.nlm.nih.gov/26984480 | E32: No
A33: Colombier MA | B33: 2017 | C33: 10.1016/j.jinf.2017.05.011 | D33: https://pubmed.ncbi.nlm.nih.gov/28551368 | E33: No
A34: Cone RW | B34: 1996 | C34: 10.1128/jcm.34.4.877-881.1996 | D34: https://pubmed.ncbi.nlm.nih.gov/8815100 | E34: No
A35: Costa ALF | B35: 2021 | C35: 10.1111/odi.13690 | D35: https://pubmed.ncbi.nlm.nih.gov/33085827 | E35: No
A36: Costa C | B36: 2008 | C36: 10.1097/TP.0b013e3181890415 | D36: https://pubmed.ncbi.nlm.nih.gov/19034008 | E36: No
A37: Cox K | B37: 2017 | C37: 10.1016/j.bbmt.2017.03.028 | D37: https://pubmed.ncbi.nlm.nih.gov/28390986 | E37: No
A38: Crocchiolo R | B38: 2016 | C38: 10.1016/j.jcv.2016.09.008 | D38: https://pubmed.ncbi.nlm.nih.gov/27669362 | E38: No
A39: de Koning C | B39: 2018 | C39: 10.1182/bloodadvances.2017012724 | D39: https://pubmed.ncbi.nlm.nih.gov/29487057 | E39: No
... A278: Zhou X | B278: 2019 | C278: 10.1164/rccm.201809-1635OC | D278: https://pubmed.ncbi.nlm.nih.gov/30742492 | E278: No
A279: Ogata M | B279: 2024 | C279: 10.1007/s12185-024-03714-2 | D279: https://pubmed.ncbi.nlm.nih.gov/38407786 | E279: No | G279: Added 7/7/24
A280: Mata JR | B280: 2024 | C280: 10.1016/j.jtct.2024.03.018 | D280: https://pubmed.ncbi.nlm.nih.gov/38521411 | E280: No | G280: Added 7/7/24
A281: Dadwal SS | B281: 2024 | C281: 10.1182/bloodadvances.2023011562 | D281: https://pubmed.ncbi.nlm.nih.gov/38593233 | E281: No | G281: Added 7/7/24
A282: Kampouri E | B282: 2024 | C282: 10.1182/blood.2024024145 | D282: https://pubmed.ncbi.nlm.nih.gov/38635788 | E282: No | G282: Added 7/7/24
A283: Terao T | B283: 2024 | C283: 10.1038/s41409-024-02313-3 | D283: https://pubmed.ncbi.nlm.nih.gov/38796633 | E283: No | G283: Added 7/7/24
A284: Paviglianiti A | B284: 2024 | C284: 10.46989/001c.92525 | D284: https://pubmed.ncbi.nlm.nih.gov/38817703 | E284: No | G284: Added 7/7/24
A285: Yu Y | B285: 2024 | C285: 10.1038/s41409-024-02332-0 | D285: https://pubmed.ncbi.nlm.nih.gov/38937612 | E285: No | G285: Added 7/7/24
A286: Abdel Massih RC | B286: 2009 | C286: 10.3748/wjg.15.2561 | D286: https://pubmed.ncbi.nlm.nih.gov/19496184 | E286: Yes | F286: Article does not describe primary data for a cohort of HCT recipients
A287: Abdel-Haq NM | B287: 2004 | C287: 10.1007/BF02725664 | D287: https://pubmed.ncbi.nlm.nih.gov/14979393 | E287: Yes | F287: Article does not describe primary data for a cohort of HCT recipients
A288: Ablashi DV | B288: 1998 | C288: 10.1177/135245859800400606 | D288: https://pubmed.ncbi.nlm.nih.gov/9987758 | E288: Yes | F288: Article does not describe primary data for a cohort of HCT recipients
A289: Ablashi DV | B289: 1991 | D289: https://pubmed.ncbi.nlm.nih.gov/1654146 | E289: Yes | F289: Article does not describe primary data for a cohort of HCT recipients
A290: Ablashi DV | B290: 2010 | C290: 10.1002/jmv.21860 | D290: https://pubmed.ncbi.nlm.nih.gov/20872717 | E290: Yes | F290: Article does not describe primary data for a cohort of HCT recipients
A291: Ablashi DV | B291: 1991 | C291: 10.1016/0042-6822(91)90424-a | D291: https://pubmed.ncbi.nlm.nih.gov/1653487 | E291: Yes | F291: Article does not describe primary data for a cohort of HCT recipients
A292: Ablashi DV | B292: 1994 | D292: https://pubmed.ncbi.nlm.nih.gov/7893986 | E292: Yes | F292: Article does not describe primary data for a cohort of HCT recipients
A293: Ablashi DV | B293: 1994 | D293: https://pubmed.ncbi.nlm.nih.gov/7893985 | E293: Yes | F293: Article does not describe primary data for a cohort of HCT recipients
A294: Ablashi DV | B294: 1994 | D294: https://pubmed.ncbi.nlm.nih.gov/7893982 | E294: Yes | F294: Article does not describe primary data for a cohort of HCT recipients
A295: Ablashi DV | B295: 1989 | D295: https://pubmed.ncbi.nlm.nih.gov/2759346 | E295: Yes | F295: Article does not describe primary data for a cohort of HCT recipients
A296: Ablashi DV | B296: 1988 | C296: 10.1002/ijc.2910420526 | D296: https://pubmed.ncbi.nlm.nih.gov/3053468 | E296: Yes | F296: Article does not describe primary data for a cohort of HCT recipients
A297: Ablashi DV | B297: 1995 | C297: 10.1016/0928-0197(95)00005-s | D297: https://pubmed.ncbi.nlm.nih.gov/15566823 | E297: Yes | F297: Article does not describe primary data for a cohort of HCT recipients
A298: Ablashi DV | B298: 1987 | C298: 10.1038/329207a0 | D298: https://pubmed.ncbi.nlm.nih.gov/3627265 | E298: Yes | F298: Article does not describe primary data for a cohort of HCT recipients
A299: Ablashi DV | B299: 1998 | C299: 10.1016/s0166-0934(98)00037-8 | D299: https://pubmed.ncbi.nlm.nih.gov/9766884 | E299: Yes | F299: Article does not describe primary data for a cohort of HCT recipients
A300: Abu Sitta E | B300: 2020 | C300: 10.1136/bcr-2020-234303 | D300: https://pubmed.ncbi.nlm.nih.gov/32188617 | E300: Yes | F300: Article does not describe primary data for a cohort of HCT recipients
A301: Acott PD | B301: 2004 | C301: 10.1016/j.transproceed.2003.12.041 | D301: https://pubmed.ncbi.nlm.nih.gov/15041393 | E301: Yes | F301: Article does not describe primary data for a cohort of HCT recipients
A302: Acott PD | B302: 2001 | C302: 10.1016/s0041-1345(01)02354-5 | D302: https://pubmed.ncbi.nlm.nih.gov/11750365 | E302: Yes | F302: Article does not describe primary data for a cohort of HCT recipients
A303: Acott PD | B303: 1996 | C303: 10.1097/00007890-199609150-00026 | D303: https://pubmed.ncbi.nlm.nih.gov/8830838 | E303: Yes | F303: Article does not describe primary data for a cohort of HCT recipients
A304: Acott PD | B304: 2004 | C304: 10.1016/j.transproceed.2004.09.081 | D304: https://pubmed.ncbi.nlm.nih.gov/15621108 | E304: Yes | F304: Article does not describe primary data for a cohort of HCT recipients
A305: Adams O | B305: 1998 | C305: 10.1086/517470 | D305: https://pubmed.ncbi.nlm.nih.gov/9697740 | E305: Yes | F305: Article does not describe primary data for a cohort of HCT recipients
A306: Agarwal L | B306: 2022 | C306: 10.1016/j.rmcr.2022.101672 | D306: https://pubmed.ncbi.nlm.nih.gov/35651518 | E306: Yes | F306: Article does not describe primary data for a cohort of HCT recipients
A307: Agnihotri SP | B307: 2019 | C307: 10.1055/s-0039-1687842 | D307: https://pubmed.ncbi.nlm.nih.gov/31378873 | E307: Yes | F307: Article does not describe primary data for a cohort of HCT recipients
... A316: Agut H | B316: 2011 | C316: 10.1016/j.jcv.2011.06.008 | D316: https://pubmed.ncbi.nlm.nih.gov/21782505 | E316: Yes | F316: Article does not describe primary data for a cohort of HCT recipients
A317: Agut H | B317: 1994 | D317: https://pubmed.ncbi.nlm.nih.gov/7939295 | E317: Yes | F317: Not in Engish
A318: Agut H | B318: 2011 | C318: 10.1016/j.patbio.2010.07.015 | D318: https://pubmed.ncbi.nlm.nih.gov/20832191 | E318: Yes | F318: Not in Engish
A319: Agut H | B319: 1998 | C319: 10.1016/s1246-7820(98)80109-2 | D319: https://pubmed.ncbi.nlm.nih.gov/9577878 | E319: Yes | F319: Not in Engish
A320: Ahlqvist J | B320: 2005 | C320: 10.1080/13550280591002379 | D320: https://pubmed.ncbi.nlm.nih.gov/16162481 | E320: Yes | F320: Article does not describe primary data for a cohort of HCT recipients
A321: Ahlqvist J | B321: 2006 | C321: 10.1002/jmv.20737 | D321: https://pubmed.ncbi.nlm.nih.gov/17063514 | E321: Yes | F321: Article does not describe primary data for a cohort of HCT recipients
A322: Akhyani N | B322: 2006 | C322: 10.1080/13550280600880772 | D322: https://pubmed.ncbi.nlm.nih.gov/16966219 | E322: Yes | F322: Article does not describe primary data for a cohort of HCT recipients
A323: Al Fawaz T | B323: 2014 | C323: 10.1111/petr.12176 | D323: https://pubmed.ncbi.nlm.nih.gov/24384048 | E323: Yes | F323: Article does not describe primary data for a cohort of HCT recipients
A324: al-Khaldi N | B324: 1994 | C324: 10.1007/BF00866361 | D324: https://pubmed.ncbi.nlm.nih.gov/7917866 | E324: Yes | F324: Article does not describe primary data for a cohort of HCT recipients
A325: Al-Sadeq DW | B325: 2021 | C325: 10.1016/j.ijregi.2021.12.005 | D325: https://pubmed.ncbi.nlm.nih.gov/35757074 | E325: Yes | F325: Article does not describe primary data for a cohort of HCT recipients
A326: Alari-Pahissa E | B326: 2018 | C326: 10.1111/ene.13622 | D326: https://pubmed.ncbi.nlm.nih.gov/29528545 | E326: Yes | F326: Article does not describe primary data for a cohort of HCT recipients
A327: Alazzam MB | B327: 2022 | C327: 10.1155/2022/1422963 | D327: https://pubmed.ncbi.nlm.nih.gov/35035452 | E327: Yes | F327: Retracted article
A328: Alfson ED | B328: 2013 | C328: 10.1016/j.psym.2012.03.003 | D328: https://pubmed.ncbi.nlm.nih.gov/22705183 | E328: Yes | F328: Article does not describe primary data for a cohort of HCT recipients
A329: Allory Y | B329: 2001 | C329: 10.1097/00000478-200107000-00004 | D329: https://pubmed.ncbi.nlm.nih.gov/11420457 | E329: Yes | F329: Article does not describe primary data for a cohort of HCT recipients
... A339: Aoki K | B339: 2012 | C339: 10.1007/s00277-012-1444-z | D339: https://pubmed.ncbi.nlm.nih.gov/22415068 | E339: Yes | F339: Article does not describe primary data for a cohort of HCT recipients
A340: Appleton AL | B340: 1993 | D340: https://pubmed.ncbi.nlm.nih.gov/8232499 | E340: Yes | F340: Article does not describe primary data for a cohort of HCT recipients
A341: Appleton AL | B341: 1994 | C341: 10.1016/s0140-6736(94)90718-8 | D341: https://pubmed.ncbi.nlm.nih.gov/7832888 | E341: Yes | F341: Article does not describe primary data for a cohort of HCT recipients
A342: Arasaratnam RJ | B342: 2018 | C342: 10.1111/ajt.14967 | D342: https://pubmed.ncbi.nlm.nih.gov/29900673 | E342: Yes | F342: Article does not describe primary data for a cohort of HCT recipients
A343: Araujo A | B343: 2011 | C343: 10.1016/j.arcped.2011.01.006 | D343: https://pubmed.ncbi.nlm.nih.gov/21397473 | E343: Yes | F343: Not in Engish
A344: Arena A | B344: 2002 | D344: https://pubmed.ncbi.nlm.nih.gov/12173776 | E344: Yes | F344: Article does not describe primary data for a cohort of HCT recipients
A345: Arena A | B345: 2000 | D345: https://pubmed.ncbi.nlm.nih.gov/10872679 | E345: Yes | F345: Article does not describe primary data for a cohort of HCT recipients
A346: Arena A | B346: 1999 | D346: https://pubmed.ncbi.nlm.nih.gov/10555198 | E346: Yes | F346: Article does not describe primary data for a cohort of HCT recipients
A347: Arena A | B347: 1996 | D347: https://pubmed.ncbi.nlm.nih.gov/8841033 | E347: Yes | F347: Article does not describe primary data for a cohort of HCT recipients
A348: Arena A | B348: 1997 | D348: https://pubmed.ncbi.nlm.nih.gov/9037664 | E348: Yes | F348: Article does not describe primary data for a cohort of HCT recipients
A349: Aritaki K | B349: 2001 | C349: 10.1038/sj.bmt.1703266 | D349: https://pubmed.ncbi.nlm.nih.gov/11753554 | E349: Yes | F349: Article does not describe primary data for a cohort of HCT recipients
A350: Arribas Anta J | B350: 2016 | C350: 10.1016/j.gastrohep.2015.09.003 | D350: https://pubmed.ncbi.nlm.nih.gov/26596368 | E350: Yes | F350: Not in Engish
A351: Arroyo HA | B351: 1997 | D351: https://pubmed.ncbi.nlm.nih.gov/9244628 | E351: Yes | F351: Not in Engish
A352: Asada H | B352: 1989 | C352: 10.1128/jcm.27.10.2204-2207.1989 | D352: https://pubmed.ncbi.nlm.nih.gov/2555389 | E352: Yes | F352: Article does not describe primary data for a cohort of HCT recipients
A353: Asadi-Pooya AA | B353: 2020 | C353: 10.1080/00207454.2020.1730370 | D353: https://pubmed.ncbi.nlm.nih.gov/32053411 | E353: Yes | F353: Article does not describe primary data for a cohort of HCT recipients
A354: Asano Y | B354: 1989 | C354: 10.1016/s0140-6736(89)91993-4 | D354: https://pubmed.ncbi.nlm.nih.gov/2574324 | E354: Yes | F354: Article does not describe primary data for a cohort of HCT recipients
A355: Asano Y | B355: 1990 | C355: 10.1002/jmv.1890320209 | D355: https://pubmed.ncbi.nlm.nih.gov/2177773 | E355: Yes | F355: Article does not describe primary data for a cohort of HCT recipients
...

Sheet Search compare
A1: 2024-07-07 PMID | B1: 2024-01-31 PMID | C1: Results in 7/7 not in 1/31 | D1: Sorted results in 7/7 not in 1/31 | E1: First Author | F1: Publication Year | G1: DOI | H1: PubMed link
A2: 27337451 | B2: 27337451 | C2: =IFERROR(IF(MATCH(A2,B:B,0)>0,""),A2) | D2: 38298135 | E2: {=_xludf.XLOOKUP(D2,'2024-07-07 pubmed search result'!A:A,'2024-07-07 pubmed search result'!E:E)} -> #NAME? | F2: {=_xludf.XLOOKUP(D2,'2024-07-07 pubmed search result'!A:A,'2024-07-07 pubmed search result'!G:G)} -> #NAME? | G2: {=_xludf.XLOOKUP(D2,'2024-07-07 pubmed search result'!A:A,'2024-07-07 pubmed search result'!K:K)} -> #NAME? | H2: ="https://pubmed.ncbi.nlm.nih.gov/"&D2 -> https://pubmed.ncbi.nlm.nih.gov/38298135
A3: 37938768 | B3: 33587722 | C3: =IFERROR(IF(MATCH(A3,B:B,0)>0,""),A3) | D3: 38377081 | E3: {=_xludf.XLOOKUP(D3,'2024-07-07 pubmed search result'!A:A,'2024-07-07 pubmed search result'!E:E)} -> #NAME? | F3: {=_xludf.XLOOKUP(D3,'2024-07-07 pubmed search result'!A:A,'2024-07-07 pubmed search result'!G:G)} -> #NAME? | G3: {=_xludf.XLOOKUP(D3,'2024-07-07 pubmed search result'!A:A,'2024-07-07 pubmed search result'!K:K)} -> #NAME? | H3: ="https://pubmed.ncbi.nlm.nih.gov/"&D3 -> https://pubmed.ncbi.nlm.nih.gov/38377081
A4: 25762531 | B4: 25762531 | C4: =IFERROR(IF(MATCH(A4,B:B,0)>0,""),A4) | D4: 38407786 | E4: {=_xludf.XLOOKUP(D4,'2024-07-07 pubmed search result'!A:A,'2024-07-07 pubmed search result'!E:E)} -> #NAME? | F4: {=_xludf.XLOOKUP(D4,'2024-07-07 pubmed search result'!A:A,'2024-07-07 pubmed search result'!G:G)} -> #NAME? | G4: {=_xludf.XLOOKUP(D4,'2024-07-07 pubmed search result'!A:A,'2024-07-07 pubmed search result'!K:K)} -> #NAME? | H4: ="https://pubmed.ncbi.nlm.nih.gov/"&D4 -> https://pubmed.ncbi.nlm.nih.gov/38407786
A5: 33587722 | B5: 37938768 | C5: =IFERROR(IF(MATCH(A5,B:B,0)>0,""),A5) | D5: 38414857 | E5: {=_xludf.XLOOKUP(D5,'2024-07-07 pubmed search result'!A:A,'2024-07-07 pubmed search result'!E:E)} -> #NAME? | F5: {=_xludf.XLOOKUP(D5,'2024-07-07 pubmed search result'!A:A,'2024-07-07 pubmed search result'!G:G)} -> #NAME? | G5: {=_xludf.XLOOKUP(D5,'2024-07-07 pubmed search result'!A:A,'2024-07-07 pubmed search result'!K:K)} -> #NAME? | H5: ="https://pubmed.ncbi.nlm.nih.gov/"&D5 -> https://pubmed.ncbi.nlm.nih.gov/38414857
A6: 31439151 | B6: 29795424 | C6: =IFERROR(IF(MATCH(A6,B:B,0)>0,""),A6) | D6: 38470444 | E6: {=_xludf.XLOOKUP(D6,'2024-07-07 pubmed search result'!A:A,'2024-07-07 pubmed search result'!E:E)} -> #NAME? | F6: {=_xludf.XLOOKUP(D6,'2024-07-07 pubmed search result'!A:A,'2024-07-07 pubmed search result'!G:G)} -> #NAME? | G6: {=_xludf.XLOOKUP(D6,'2024-07-07 pubmed search result'!A:A,'2024-07-07 pubmed search result'!K:K)} -> #NAME? | H6: ="https://pubmed.ncbi.nlm.nih.gov/"&D6 -> https://pubmed.ncbi.nlm.nih.gov/38470444
A7: 37067947 | B7: 31439151 | C7: =IFERROR(IF(MATCH(A7,B:B,0)>0,""),A7) | D7: 38487325 | E7: {=_xludf.XLOOKUP(D7,'2024-07-07 pubmed search result'!A:A,'2024-07-07 pubmed search result'!E:E)} -> #NAME? | F7: {=_xludf.XLOOKUP(D7,'2024-07-07 pubmed search result'!A:A,'2024-07-07 pubmed search result'!G:G)} -> #NAME? | G7: {=_xludf.XLOOKUP(D7,'2024-07-07 pubmed search result'!A:A,'2024-07-07 pubmed search result'!K:K)} -> #NAME? | H7: ="https://pubmed.ncbi.nlm.nih.gov/"&D7 -> https://pubmed.ncbi.nlm.nih.gov/38487325
A8: 14979393 | B8: 10069356 | C8: =IFERROR(IF(MATCH(A8,B:B,0)>0,""),A8) | D8: 38496135 | E8: {=_xludf.XLOOKUP(D8,'2024-07-07 pubmed search result'!A:A,'2024-07-07 pubmed search result'!E:E)} -> #NAME? | F8: {=_xludf.XLOOKUP(D8,'2024-07-07 pubmed search result'!A:A,'2024-07-07 pubmed search result'!G:G)} -> #NAME? | G8: {=_xludf.XLOOKUP(D8,'2024-07-07 pubmed search result'!A:A,'2024-07-07 pubmed search result'!K:K)} -> #NAME? | H8: ="https://pubmed.ncbi.nlm.nih.gov/"&D8 -> https://pubmed.ncbi.nlm.nih.gov/38496135
A9: 29194419 | B9: 7663047 | C9: =IFERROR(IF(MATCH(A9,B:B,0)>0,""),A9) | D9: 38521411 | E9: {=_xludf.XLOOKUP(D9,'2024-07-07 pubmed search result'!A:A,'2024-07-07 pubmed search result'!E:E)} -> #NAME? | F9: {=_xludf.XLOOKUP(D9,'2024-07-07 pubmed search result'!A:A,'2024-07-07 pubmed search result'!G:G)} -> #NAME? | G9: {=_xludf.XLOOKUP(D9,'2024-07-07 pubmed search result'!A:A,'2024-07-07 pubmed search result'!K:K)} -> #NAME? | H9: ="https://pubmed.ncbi.nlm.nih.gov/"&D9 -> https://pubmed.ncbi.nlm.nih.gov/38521411
A10: 10069356 | B10: 20304745 | C10: =IFERROR(IF(MATCH(A10,B:B,0)>0,""),A10) | D10: 38593233 | E10: {=_xludf.XLOOKUP(D10,'2024-07-07 pubmed search result'!A:A,'2024-07-07 pubmed search result'!E:E)} -> #NAME? | F10: {=_xludf.XLOOKUP(D10,'2024-07-07 pubmed search result'!A:A,'2024-07-07 pubmed search result'!G:G)} -> #NAME? | G10: {=_xludf.XLOOKUP(D10,'2024-07-07 pubmed search result'!A:A,'2024-07-07 pubmed search result'!K:K)} -> #NAME? | H10: ="https://pubmed.ncbi.nlm.nih.gov/"&D10 -> https://pubmed.ncbi.nlm.nih.gov/38593233
A11: 26802216 | B11: 27538995 | C11: =IFERROR(IF(MATCH(A11,B:B,0)>0,""),A11) | D11: 38596415 | E11: {=_xludf.XLOOKUP(D11,'2024-07-07 pubmed search result'!A:A,'2024-07-07 pubmed search result'!E:E)} -> #NAME? | F11: {=_xludf.XLOOKUP(D11,'2024-07-07 pubmed search result'!A:A,'2024-07-07 pubmed search result'!G:G)} -> #NAME? | G11: {=_xludf.XLOOKUP(D11,'2024-07-07 pubmed search result'!A:A,'2024-07-07 pubmed search result'!K:K)} -> #NAME? | H11: ="https://pubmed.ncbi.nlm.nih.gov/"&D11 -> https://pubmed.ncbi.nlm.nih.gov/38596415
A12: 25462448 | B12: 28650593 | C12: =IFERROR(IF(MATCH(A12,B:B,0)>0,""),A12) | D12: 38597860 | E12: {=_xludf.XLOOKUP(D12,'2024-07-07 pubmed search result'!A:A,'2024-07-07 pubmed search result'!E:E)} -> #NAME? | F12: {=_xludf.XLOOKUP(D12,'2024-07-07 pubmed search result'!A:A,'2024-07-07 pubmed search result'!G:G)} -> #NAME? | G12: {=_xludf.XLOOKUP(D12,'2024-07-07 pubmed search result'!A:A,'2024-07-07 pubmed search result'!K:K)} -> #NAME? | H12: ="https://pubmed.ncbi.nlm.nih.gov/"&D12 -> https://pubmed.ncbi.nlm.nih.gov/38597860
A13: 10815027 | B13: 8386499 | C13: =IFERROR(IF(MATCH(A13,B:B,0)>0,""),A13) | D13: 38631099 | E13: {=_xludf.XLOOKUP(D13,'2024-07-07 pubmed search result'!A:A,'2024-07-07 pubmed search result'!E:E)} -> #NAME? | F13: {=_xludf.XLOOKUP(D13,'2024-07-07 pubmed search result'!A:A,'2024-07-07 pubmed search result'!G:G)} -> #NAME? | G13: {=_xludf.XLOOKUP(D13,'2024-07-07 pubmed search result'!A:A,'2024-07-07 pubmed search result'!K:K)} -> #NAME? | H13: ="https://pubmed.ncbi.nlm.nih.gov/"&D13 -> https://pubmed.ncbi.nlm.nih.gov/38631099
... A31: 24792343 | B31: 30398125 | C31: =IFERROR(IF(MATCH(A31,B:B,0)>0,""),A31) | D31: 38971380 | E31: {=_xludf.XLOOKUP(D31,'2024-07-07 pubmed search result'!A:A,'2024-07-07 pubmed search result'!E:E)} -> #NAME? | F31: {=_xludf.XLOOKUP(D31,'2024-07-07 pubmed search result'!A:A,'2024-07-07 pubmed search result'!G:G)} -> #NAME? | G31: {=_xludf.XLOOKUP(D31,'2024-07-07 pubmed search result'!A:A,'2024-07-07 pubmed search result'!K:K)} -> #NAME? | H31: ="https://pubmed.ncbi.nlm.nih.gov/"&D31 -> https://pubmed.ncbi.nlm.nih.gov/38971380
A32: 31449472 | B32: 32827324 | C32: =IFERROR(IF(MATCH(A32,B:B,0)>0,""),A32)
A33: 25462440 | B33: 36927092 | C33: =IFERROR(IF(MATCH(A33,B:B,0)>0,""),A33)
A34: 25285614 | B34: 10855769 | C34: =IFERROR(IF(MATCH(A34,B:B,0)>0,""),A34)
A35: 38631099 | B35: 31075291 | C35: =IFERROR(IF(MATCH(A35,B:B,0)>0,""),A35) -> 38631099
A36: 1654146 | B36: 17276368 | C36: =IFERROR(IF(MATCH(A36,B:B,0)>0,""),A36)
A37: 21782505 | B37: 25462440 | C37: =IFERROR(IF(MATCH(A37,B:B,0)>0,""),A37)
A38: 27538995 | B38: 36833448 | C38: =IFERROR(IF(MATCH(A38,B:B,0)>0,""),A38)
A39: 30427305 | B39: 25462451 | C39: =IFERROR(IF(MATCH(A39,B:B,0)>0,""),A39)
A40: 26160819 | B40: 22052666 | C40: =IFERROR(IF(MATCH(A40,B:B,0)>0,""),A40)
A41: 32860467 | B41: 24792343 | C41: =IFERROR(IF(MATCH(A41,B:B,0)>0,""),A41)
A42: 23526966 | B42: 11964854 | C42: =IFERROR(IF(MATCH(A42,B:B,0)>0,""),A42)
A43: 38228644 | B43: 12430932 | C43: =IFERROR(IF(MATCH(A43,B:B,0)>0,""),A43)
... A1713: 33363781 | B1713: 26460048 | C1713: =IFERROR(IF(MATCH(A1713,B:B,0)>0,""),A1713)
A1714: 10738138 | C1714: =IFERROR(IF(MATCH(A1714,B:B,0)>0,""),A1714)
A1715: 22542037 | C1715: =IFERROR(IF(MATCH(A1715,B:B,0)>0,""),A1715)
A1716: 29642192 | C1716: =IFERROR(IF(MATCH(A1716,B:B,0)>0,""),A1716)
A1717: 21300108 | C1717: =IFERROR(IF(MATCH(A1717,B:B,0)>0,""),A1717)
A1718: 34206597 | C1718: =IFERROR(IF(MATCH(A1718,B:B,0)>0,""),A1718)
A1719: 12182687 | C1719: =IFERROR(IF(MATCH(A1719,B:B,0)>0,""),A1719)
A1720: 9155970 | C1720: =IFERROR(IF(MATCH(A1720,B:B,0)>0,""),A1720)
A1721: 32944150 | C1721: =IFERROR(IF(MATCH(A1721,B:B,0)>0,""),A1721)
A1722: 23588740 | C1722: =IFERROR(IF(MATCH(A1722,B:B,0)>0,""),A1722)
A1723: 19910888 | C1723: =IFERROR(IF(MATCH(A1723,B:B,0)>0,""),A1723)
A1724: 36806616 | C1724: =IFERROR(IF(MATCH(A1724,B:B,0)>0,""),A1724)
A1725: 29535361 | C1725: =IFERROR(IF(MATCH(A1725,B:B,0)>0,""),A1725)
... A1743: 26460048 | C1743: =IFERROR(IF(MATCH(A1743,B:B,0)>0,""),A1743)

Sheet 2024-07-07 pubmed search result
A1: PMID | B1: Title | C1: Authors | D1: Citation | E1: First Author | F1: Journal/Book | G1: Publication Year | H1: Create Date | I1: PMCID | J1: NIHMS ID | K1: DOI | L1: query: | M1: ((hematopoietic OR stem cell OR cord blood OR bone marrow OR transplant*) OR (engraftment OR reconstitution OR graft failure OR marrow failure OR neutrophil OR NK OR natural killer OR platelet OR T cell OR thymus OR chimerism)) AND (HHV-6 OR HHV6 OR herpesvirus-6 OR HHV-6A OR HHV6A OR herpesvirus-6A OR HHV-6B OR HHV6B OR herpesvirus-6B)
A2: 27337451 | B2: Human Herpesviruses 6A, 6B, and 7 | C2: Agut H, Bonnafous P, Gautheret-Dejean A. | D2: Microbiol Spectr. 2016 Jun;4(3). doi: 10.1128/microbiolspec.DMIH2-0007-2015. | E2: Agut H | F2: Microbiol Spectr | G2: 2016 | H2: 42545 | K2: 10.1128/microbiolspec.DMIH2-0007-2015 | L2: date: | M2: 45480
A3: 37938768 | B3: Latent human herpesvirus 6 is reactivated in CAR T cells | C3: Lareau CA, Yin Y, Maurer K, Sandor KD, Daniel B, Yagnik G, Peña J, Crawford JC, Spanjaart AM, Gutierrez JC, Haradhvala NJ, Riberdy JM, Abay T, Stickels RR, Verboon JM, Liu V, Buquicchio FA, Wang F, Southard J, Song R, Li W, Shrestha A, Parida L, Getz G, Maus MV, Li S, Moore A, Roberts ZJ, Ludwig LS, Talleur AC, Thomas PG, Dehghani H, Pertel T, Kundaje A, Gottschalk S, Roth TL, Kersten MJ, Wu CJ, Majzner RG, Satpathy AT. | D3: Nature. 2023 Nov;623(7987):608-615. doi: 10.1038/s41586-023-06704-2. Epub 2023 Nov 8. | E3: Lareau CA | F3: Nature | G3: 2023 | H3: 45238 | I3: PMC10999258 | J3: NIHMS1979850 | K3: 10.1038/s41586-023-06704-2 | L3: n results: | M3: 1742
A4: 25762531 | B4: Laboratory and clinical aspects of human herpesvirus 6 infections | C4: Agut H, Bonnafous P, Gautheret-Dejean A. | D4: Clin Microbiol Rev. 2015 Apr;28(2):313-35. doi: 10.1128/CMR.00122-14. | E4: Agut H | F4: Clin Microbiol Rev | G4: 2015 | H4: 42076 | I4: PMC4402955 | K4: 10.1128/CMR.00122-14
A5: 33587722 | B5: Human Herpesvirus 6 Encephalitis in Immunocompetent and Immunocompromised Hosts | C5: Berzero G, Campanini G, Vegezzi E, Paoletti M, Pichiecchio A, Simoncelli AM, Colombo AA, Bernasconi P, Borsani O, Di Matteo A, Rossi V, Foiadelli T, Savasta S, Compagno F, Zecca M, Baldanti F, Marchioni E. | D5: Neurol Neuroimmunol Neuroinflamm. 2021 Jan 12;8(2):e942. doi: 10.1212/NXI.0000000000000942. Print 2021 Mar. | E5: Berzero G | F5: Neurol Neuroimmunol Neuroinflamm | G5: 2021 | H5: 44242 | I5: PMC7963435 | K5: 10.1212/NXI.0000000000000942
A6: 31439151 | B6: Entry of betaherpesviruses | C6: Nishimura M, Mori Y. | D6: Adv Virus Res. 2019;104:283-312. doi: 10.1016/bs.aivir.2019.05.005. Epub 2019 Jun 21. | E6: Nishimura M | F6: Adv Virus Res | G6: 2019 | H6: 43701 | K6: 10.1016/bs.aivir.2019.05.005
A7: 37067947 | B7: Human herpesvirus 6-specific T-cell immunity in allogeneic hematopoietic stem cell transplant recipients | C7: Noviello M, Lorentino F, Xue E, Racca S, Furnari G, Valtolina V, Campodonico E, Dvir R, Lupo-Stanghellini MT, Giglio F, Piemontese S, Clerici D, Oltolini C, Tassi E, Beretta V, Farina F, Mannina D, Ardemagni A, Vago L, Bernardi M, Corti C, Peccatori J, Clementi M, Ciceri F, Bonini C, Greco R. | D7: Blood Adv. 2023 Sep 26;7(18):5446-5457. doi: 10.1182/bloodadvances.2022009274. | E7: Noviello M | F7: Blood Adv | G7: 2023 | H7: 45033 | I7: PMC10515312 | K7: 10.1182/bloodadvances.2022009274
A8: 14979393 | B8: Human herpesvirus 6 (HHV6) infection | C8: Abdel-Haq NM, Asmar BI. | D8: Indian J Pediatr. 2004 Jan;71(1):89-96. doi: 10.1007/BF02725664. | E8: Abdel-Haq NM | F8: Indian J Pediatr | G8: 2004 | H8: 38043 | K8: 10.1007/BF02725664
A9: 29194419 | B9: The Interplay between Natural Killer Cells and Human Herpesvirus-6 | C9: Eliassen E, Di Luca D, Rizzo R, Barao I. | D9: Viruses. 2017 Dec 1;9(12):367. doi: 10.3390/v9120367. | E9: Eliassen E | F9: Viruses | G9: 2017 | H9: 43071 | I9: PMC5744142 | K9: 10.3390/v9120367
A10: 10069356 | B10: Human herpesvirus 6 | C10: Dockrell DH, Smith TF, Paya CV. | D10: Mayo Clin Proc. 1999 Feb;74(2):163-70. doi: 10.4065/74.2.163. | E10: Dockrell DH | F10: Mayo Clin Proc | G10: 1999 | H10: 36228 | K10: 10.4065/74.2.163
A11: 26802216 | B11: Clinical and laboratory features of human herpesvirus 6 chromosomal integration | C11: Clark DA. | D11: Clin Microbiol Infect. 2016 Apr;22(4):333-339. doi: 10.1016/j.cmi.2015.12.022. Epub 2016 Jan 21. | E11: Clark DA | F11: Clin Microbiol Infect | G11: 2016 | H11: 42393 | K11: 10.1016/j.cmi.2015.12.022
A12: 25462448 | B12: Immune response to HHV-6 and implications for immunotherapy | C12: Becerra A, Gibson L, Stern LJ, Calvo-Calle JM. | D12: Curr Opin Virol. 2014 Dec;9:154-61. doi: 10.1016/j.coviro.2014.10.001. Epub 2014 Oct 27. | E12: Becerra A | F12: Curr Opin Virol | G12: 2014 | H12: 41976 | I12: PMC4274602 | J12: NIHMS635662 | K12: 10.1016/j.coviro.2014.10.001
A13: 10815027 | B13: Human herpesvirus 6 | C13: Clark DA. | D13: Rev Med Virol. 2000 May-Jun;10(3):155-73. doi: 10.1002/(sici)1099-1654(200005/06)10:3<155::aid-rmv277>3.0.co;2-6. | E13: Clark DA | F13: Rev Med Virol | G13: 2000 | H13: 36664 | K13: 10.1002/(sici)1099-1654(200005/06)10:3<155::aid-rmv277>3.0.co;2-6
A14: 29795424 | B14: HHV-6B infection, T-cell reconstitution, and graft-vs-host disease after hematopoietic stem cell transplantation | C14: Phan TL, Pritchett JC, Leifer C, Zerr DM, Koelle DM, Di Luca D, Lusso P. | D14: Bone Marrow Transplant. 2018 Dec;53(12):1508-1517. doi: 10.1038/s41409-018-0225-2. Epub 2018 May 24. | E14: Phan TL | F14: Bone Marrow Transplant | G14: 2018 | H14: 43246 | K14: 10.1038/s41409-018-0225-2
A15: 36739398 | B15: Human herpesvirus-6 in hematopoietic stem cell transplant recipients: a prospective cohort study in Egypt | C15: Raouf MME, Ouf NM, Elsorady MAS, Ghoneim FM. | D15: Virol J. 2023 Feb 4;20(1):20. doi: 10.1186/s12985-023-01980-w. | E15: Raouf MME | F15: Virol J | G15: 2023 | H15: 44961 | I15: PMC9899109 | K15: 10.1186/s12985-023-01980-w
A16: 29304865 | B16: Evaluation of a method to measure HHV-6B infection in vitro based on cell size | C16: Becerra-Artiles A, Santoro T, Stern LJ. | D16: Virol J. 2018 Jan 5;15(1):4. doi: 10.1186/s12985-017-0917-z. | E16: Becerra-Artiles A | F16: Virol J | G16: 2018 | H16: 43107 | I16: PMC5755443 | K16: 10.1186/s12985-017-0917-z
A17: 36878429 | B17: Once-Daily Foscarnet Is Effective for Human Herpesvirus 6 Reactivation after Hematopoietic Stem Cell Transplantation | C17: Vittayawacharin P, E'Leimat G, Lee BJ, Griffin S, Doh J, Nam H, Blodget E, Jeyakumar D, Kongtim P, Ciurea SO. | D17: Transplant Cell Ther. 2023 Jun;29(6):397.e1-397.e6. doi: 10.1016/j.jtct.2023.02.022. Epub 2023 Mar 4. | E17: Vittayawacharin P | F17: Transplant Cell Ther | G17: 2023 | H17: 44991 | K17: 10.1016/j.jtct.2023.02.022
A18: 15480369 | B18: Congenital infections with human herpesvirus 6 (HHV6) and human herpesvirus 7 (HHV7) | C18: Hall CB, Caserta MT, Schnabel KC, Boettrich C, McDermott MP, Lofthus GK, Carnahan JA, Dewhurst S. | D18: J Pediatr. 2004 Oct;145(4):472-7. doi: 10.1016/j.jpeds.2004.06.017. | E18: Hall CB | F18: J Pediatr | G18: 2004 | H18: 38274 | K18: 10.1016/j.jpeds.2004.06.017
A19: 29512392 | B19: Human herpesvirus 6A and 6B and NK cells | C19: Rizzo R, Di Luca D. | D19: Acta Microbiol Immunol Hung. 2018 Jun 1;65(2):119-125. doi: 10.1556/030.65.2018.010. Epub 2018 Mar 7. | E19: Rizzo R | F19: Acta Microbiol Immunol Hung | G19: 2018 | H19: 43167 | K19: 10.1556/030.65.2018.010
A20: 27773488 | B20: Update on infections with human herpesviruses 6A, 6B, and 7 | C20: Agut H, Bonnafous P, Gautheret-Dejean A. | D20: Med Mal Infect. 2017 Mar;47(2):83-91. doi: 10.1016/j.medmal.2016.09.004. Epub 2016 Oct 20. | E20: Agut H | F20: Med Mal Infect | G20: 2017 | H20: 42668 | K20: 10.1016/j.medmal.2016.09.004
A21: 33952641 | B21: The Roseoloviruses Downregulate the Protein Tyrosine Phosphatase PTPRC (CD45) | C21: Whyte ML, Smith KA, Buchberger A, Berg Luecke L, Tjan LH, Mori Y, Gundry RL, Hudson AW. | D21: J Virol. 2021 Jun 24;95(14):e0162820. doi: 10.1128/JVI.01628-20. Epub 2021 Jun 24. | E21: Whyte ML | F21: J Virol | G21: 2021 | H21: 44322 | I21: PMC8223955 | K21: 10.1128/JVI.01628-20
A22: 17276368 | B22: HHV-6 and the immune system: mechanisms of immunomodulation and viral escape | C22: Lusso P. | D22: J Clin Virol. 2006 Dec;37 Suppl 1:S4-10. doi: 10.1016/S1386-6532(06)70004-X. | E22: Lusso P | F22: J Clin Virol | G22: 2006 | H22: 39119 | K22: 10.1016/S1386-6532(06)70004-X
A23: 22356254 | B23: Human herpesvirus-6 infections in kidney, liver, lung, and heart transplantation: review | C23: Lautenschlager I, Razonable RR. | D23: Transpl Int. 2012 May;25(5):493-502. doi: 10.1111/j.1432-2277.2012.01443.x. Epub 2012 Feb 23. | E23: Lautenschlager I | F23: Transpl Int | G23: 2012 | H23: 40963 | K23: 10.1111/j.1432-2277.2012.01443.x
A24: 22052666 | B24: Chromosomally integrated human herpesvirus 6: questions and answers | C24: Pellett PE, Ablashi DV, Ambros PF, Agut H, Caserta MT, Descamps V, Flamand L, Gautheret-Dejean A, Hall CB, Kamble RT, Kuehl U, Lassner D, Lautenschlager I, Loomis KS, Luppi M, Lusso P, Medveczky PG, Montoya JG, Mori Y, Ogata M, Pritchett JC, Rogez S, Seto E, Ward KN, Yoshikawa T, Razonable RR. | D24: Rev Med Virol. 2012 May;22(3):144-55. doi: 10.1002/rmv.715. Epub 2011 Nov 4. | E24: Pellett PE | F24: Rev Med Virol | G24: 2012 | H24: 40852 | I24: PMC3498727 | K24: 10.1002/rmv.715
A25: 28650593 | B25: HHV-6 in liver transplantation: A literature review | C25: Phan TL, Lautenschlager I, Razonable RR, Munoz FM. | D25: Liver Int. 2018 Feb;38(2):210-223. doi: 10.1111/liv.13506. Epub 2017 Jul 29. | E25: Phan TL | F25: Liver Int | G25: 2018 | H25: 42913 | K25: 10.1111/liv.13506
A26: 35911725 | B26: Differential Impacts of HHV-6A versus HHV-6B Infection in Differentiated Human Neural Stem Cells | C26: Bahramian E, Furr M, Wu JT, Ceballos RM. | D26: Front Immunol. 2022 Jul 13;13:847106. doi: 10.3389/fimmu.2022.847106. eCollection 2022. | E26: Bahramian E | F26: Front Immunol | G26: 2022 | H26: 44774 | I26: PMC9326508 | K26: 10.3389/fimmu.2022.847106
A27: 17276370 | B27: Human herpesvirus 6 and central nervous system disease in hematopoietic cell transplantation | C27: Zerr DM. | D27: J Clin Virol. 2006 Dec;37 Suppl 1:S52-6. doi: 10.1016/S1386-6532(06)70012-9. | E27: Zerr DM | F27: J Clin Virol | G27: 2006 | H27: 39119 | K27: 10.1016/S1386-6532(06)70012-9
A28: 33548682 | B28: Human herpesvirus 6 and central nervous system disease in oncology patients: A retrospective case series and literature review | C28: Handley G, Hasbun R, Okhuysen P. | D28: J Clin Virol. 2021 Mar;136:104740. doi: 10.1016/j.jcv.2021.104740. Epub 2021 Jan 28. | E28: Handley G | F28: J Clin Virol | G28: 2021 | H28: 44233 | K28: 10.1016/j.jcv.2021.104740
A29: 34647632 | B29: Presence and clinical impact of human herpesvirus-6 infection in patients with moderate to critical coronavirus disease-19 | C29: Lino K, Alves LS, Raposo JV, Medeiros T, Souza CF, Silva AAD, de Paula VS, Almeida JR. | D29: J Med Virol. 2022 Mar;94(3):1212-1216. doi: 10.1002/jmv.27392. Epub 2021 Oct 19. | E29: Lino K | F29: J Med Virol | G29: 2022 | H29: 44483 | I29: PMC8662171 | K29: 10.1002/jmv.27392
A30: 12430932 | B30: Human herpesvirus 6 and human herpesvirus 7: emerging pathogens in transplant patients | C30: Clark DA. | D30: Int J Hematol. 2002 Aug;76 Suppl 2:246-52. doi: 10.1007/BF03165124. | E30: Clark DA | F30: Int J Hematol | G30: 2002 | H30: 37575 | K30: 10.1007/BF03165124
A31: 24792343 | B31: Child and adult forms of human herpesvirus 6 encephalitis: looking back, looking forward | C31: Ward KN. | D31: Curr Opin Neurol. 2014 Jun;27(3):349-55. doi: 10.1097/WCO.0000000000000085. | E31: Ward KN | F31: Curr Opin Neurol | G31: 2014 | H31: 41765 | K31: 10.1097/WCO.0000000000000085
A32: 31449472 | B32: Human Herpesvirus 6B and Lower Respiratory Tract Disease After Hematopoietic Cell Transplantation | C32: Hill JA, Vande Vusse LK, Xie H, Chung EL, Yeung CCS, Seo S, Stevens-Ayers T, Fisher CE, Huang ML, Stewart FM, Jerome KR, Zerr DM, Corey L, Leisenring WM, Boeckh M. | D32: J Clin Oncol. 2019 Oct 10;37(29):2670-2681. doi: 10.1200/JCO.19.00908. Epub 2019 Aug 26. | E32: Hill JA | F32: J Clin Oncol | G32: 2019 | H32: 43704 | I32: PMC7351330 | K32: 10.1200/JCO.19.00908
A33: 25462440 | B33: Recent developments in animal models for human herpesvirus 6A and 6B | C33: Horvat B, Berges BK, Lusso P. | D33: Curr Opin Virol. 2014 Dec;9:97-103. doi: 10.1016/j.coviro.2014.09.012. Epub 2014 Oct 14. | E33: Horvat B | F33: Curr Opin Virol | G33: 2014 | H33: 41976 | I33: PMC4268362 | J33: NIHMS632692 | K33: 10.1016/j.coviro.2014.09.012
A34: 25285614 | B34: Roseoloviruses in transplant recipients: clinical consequences and prospects for treatment and prevention trials | C34: Hill JA, Zerr DM. | D34: Curr Opin Virol. 2014 Dec;9:53-60. doi: 10.1016/j.coviro.2014.09.006. Epub 2014 Oct 4. | E34: Hill JA | F34: Curr Opin Virol | G34: 2014 | H34: 41919 | I34: PMC4570620 | J34: NIHMS721610 | K34: 10.1016/j.coviro.2014.09.006
A35: 38631099 | B35: AMPK restricts HHV-6A replication by inhibiting glycolysis and mTOR signaling | C35: Yang X, Tian S, Min Z, Garbarino E, Ma J, Jia J, Tang H, Li L. | D35: Virology. 2024 Jul;595:110080. doi: 10.1016/j.virol.2024.110080. Epub 2024 Apr 9. | E35: Yang X | F35: Virology | G35: 2024 | H35: 45399 | K35: 10.1016/j.virol.2024.110080
A36: 1654146 | B36: Human herpesvirus-6 (HHV-6) (short review) | C36: Ablashi DV, Salahuddin SZ, Josephs SF, Balachandran N, Krueger GR, Gallo RC. | D36: In Vivo. 1991 May-Jun;5(3):193-9. | E36: Ablashi DV | F36: In Vivo | G36: 1991 | H36: 33359
A37: 21782505 | B37: Deciphering the clinical impact of acute human herpesvirus 6 (HHV-6) infections | C37: Agut H. | D37: J Clin Virol. 2011 Nov;52(3):164-71. doi: 10.1016/j.jcv.2011.06.008. Epub 2011 Jul 22. | E37: Agut H | F37: J Clin Virol | G37: 2011 | H37: 40750 | K37: 10.1016/j.jcv.2011.06.008
A38: 27538995 | B38: Roseolovirus-associated encephalitis in immunocompetent and immunocompromised individuals | C38: Ongrádi J, Ablashi DV, Yoshikawa T, Stercz B, Ogata M. | D38: J Neurovirol. 2017 Feb;23(1):1-19. doi: 10.1007/s13365-016-0473-0. Epub 2016 Aug 18. | E38: Ongrádi J | F38: J Neurovirol | G38: 2017 | H38: 42602 | I38: PMC5329081 | K38: 10.1007/s13365-016-0473-0
A39: 30427305 | B39: Impact of HHV-6A and HHV-6B lytic infection on autophagy and endoplasmic reticulum stress | C39: Romeo MA, Masuelli L, Gaeta A, Nazzari C, Granato M, Gilardini Montani MS, Faggioni A, Cirone M. | D39: J Gen Virol. 2019 Jan;100(1):89-98. doi: 10.1099/jgv.0.001176. Epub 2018 Nov 14. | E39: Romeo MA | F39: J Gen Virol | G39: 2019 | H39: 43419 | K39: 10.1099/jgv.0.001176
A40: 26160819 | B40: [Human Herpesvirus-6 Encephalitis in Allogeneic Hematopoietic Stem Cell Transplantation] | C40: Ogata M. | D40: Brain Nerve. 2015 Jul;67(7):919-30. doi: 10.11477/mf.1416200231. | E40: Ogata M | F40: Brain Nerve | G40: 2015 | H40: 42196 | K40: 10.11477/mf.1416200231
A41: 32860467 | B41: Reactivation of human herpesvirus 6 in pediatric allogeneic hematopoietic stem cell transplant recipients | C41: Pawlowska AB, Karras NA, Liu H, DiMundo J, Cheng JC, Sun W, Armenian S, Yang D, Palmer JM, Bell A, Tahoun A, Tegtmeier B, Dadwal S, Rosenthal J. | D41: Transpl Infect Dis. 2021 Feb;23(1):e13453. doi: 10.1111/tid.13453. Epub 2020 Sep 22. | E41: Pawlowska AB | F41: Transpl Infect Dis | G41: 2021 | H41: 44073 | K41: 10.1111/tid.13453
A42: 23526966 | B42: Human herpesvirus 6A partially suppresses functional properties of DC without viral replication | C42: Gustafsson RK, Engdahl EE, Hammarfjord O, Adikari SB, Lourda M, Klingström J, Svensson M, Fogdell-Hahn A. | D42: PLoS One. 2013;8(3):e58122. doi: 10.1371/journal.pone.0058122. Epub 2013 Mar 5. | E42: Gustafsson RK | F42: PLoS One | G42: 2013 | H42: 41359 | I42: PMC3590851 | K42: 10.1371/journal.pone.0058122
A43: 38228644 | B43: HHV-6B detection and host gene expression implicate HHV-6B as pulmonary pathogen after hematopoietic cell transplant | C43: Hill JA, Lee YJ, Vande Vusse LK, Xie H, Chung EL, Waghmare A, Cheng GS, Zhu H, Huang ML, Hill GR, Jerome KR, Leisenring WM, Zerr DM, Gharib SA, Dadwal S, Boeckh M. | D43: Nat Commun. 2024 Jan 16;15(1):542. doi: 10.1038/s41467-024-44828-9. | E43: Hill JA | F43: Nat Commun | G43: 2024 | H43: 45307 | I43: PMC10791683 | K43: 10.1038/s41467-024-44828-9
A44: 8386499 | B44: Human herpesvirus-6 | C44: Caserta MT, Hall CB. | D44: Annu Rev Med. 1993;44:377-83. doi: 10.1146/annurev.me.44.020193.002113. | E44: Caserta MT | F44: Annu Rev Med | G44: 1993 | H44: 33970 | K44: 10.1146/annurev.me.44.020193.002113
A45: 32663845 | B45: Donor-Derived CD4+ T Cells and Human Herpesvirus 6B Detection After Allogeneic Hematopoietic Cell Transplantation | C45: Hanson DJ, Xie H, Zerr DM, Leisenring WM, Jerome KR, Huang ML, Stevens-Ayers T, Boeckh M, Koelle DM, Hill JA. | D45: J Infect Dis. 2021 Feb 24;223(4):709-713. doi: 10.1093/infdis/jiaa422. | E45: Hanson DJ | F45: J Infect Dis | G45: 2021 | H45: 44027 | I45: PMC7904283 | K45: 10.1093/infdis/jiaa422
A46: 25462439 | B46: Clinical impact of primary infection with roseoloviruses | C46: Tesini BL, Epstein LG, Caserta MT. | D46: Curr Opin Virol. 2014 Dec;9:91-6. doi: 10.1016/j.coviro.2014.09.013. Epub 2014 Oct 14. | E46: Tesini BL | F46: Curr Opin Virol | G46: 2014 | H46: 41976 | I46: PMC4267952 | J46: NIHMS632651 | K46: 10.1016/j.coviro.2014.09.013
A47: 29797616 | B47: Late-phase human herpesvirus 6B reactivation in hematopoietic stem cell transplant recipients | C47: Miura H, Kawamura Y, Hattori F, Tanaka M, Kudo K, Ihira M, Yatsuya H, Takahashi Y, Kojima S, Yoshikawa T. | D47: Transpl Infect Dis. 2018 Aug;20(4):e12916. doi: 10.1111/tid.12916. Epub 2018 Jun 13. | E47: Miura H | F47: Transpl Infect Dis | G47: 2018 | H47: 43246 | K47: 10.1111/tid.12916
A48: 12488560 | B48: Human herpesvirus 6: molecular biology and clinical features | C48: Dockrell DH. | D48: J Med Microbiol. 2003 Jan;52(Pt 1):5-18. doi: 10.1099/jmm.0.05074-0. | E48: Dockrell DH | F48: J Med Microbiol | G48: 2003 | H48: 37609 | K48: 10.1099/jmm.0.05074-0
A49: 25694589 | B49: Maturation of human herpesvirus 6A glycoprotein O requires coexpression of glycoprotein H and glycoprotein L | C49: Tang H, Mahmoud NF, Mori Y. | D49: J Virol. 2015 May;89(9):5159-63. doi: 10.1128/JVI.00140-15. Epub 2015 Feb 18. | E49: Tang H | F49: J Virol | G49: 2015 | H49: 42055 | I49: PMC4403471 | K49: 10.1128/JVI.00140-15
A50: 15653828 | B50: Update on human herpesvirus 6 biology, clinical features, and therapy | C50: De Bolle L, Naesens L, De Clercq E. | D50: Clin Microbiol Rev. 2005 Jan;18(1):217-45. doi: 10.1128/CMR.18.1.217-245.2005. | E50: De Bolle L | F50: Clin Microbiol Rev | G50: 2005 | H50: 38370 | I50: PMC544175 | K50: 10.1128/CMR.18.1.217-245.2005
A51: 32775465 | B51: Comprehensive Screening of Mouse T-Cell Epitopes in Human Herpesvirus 6B Glycoprotein H/L/Q1/Q2 Tetramer Complex | C51: Okutani M, Kawabata A, Nishimura M, Nagamata S, Kuwabara S, Haseda Y, Munakata L, Suzuki R, Mori Y, Aoshi T. | D51: J Immunol Res. 2020 Jul 26;2020:4697529. doi: 10.1155/2020/4697529. eCollection 2020. | E51: Okutani M | F51: J Immunol Res | G51: 2020 | H51: 44054 | I51: PMC7399772 | K51: 10.1155/2020/4697529
A52: 36833448 | B52: The Telomeric Repeats of HHV-6A Do Not Determine the Chromosome into Which the Virus Is Integrated | C52: Kusakin AV, Goleva OV, Danilov LG, Krylov AV, Tsay VV, Kalinin RS, Tian NS, Eismont YA, Mukomolova AL, Chukhlovin AB, Komissarov AS, Glotov OS. | D52: Genes (Basel). 2023 Feb 18;14(2):521. doi: 10.3390/genes14020521. | E52: Kusakin AV | F52: Genes (Basel) | G52: 2023 | H52: 44982 | I52: PMC9957103 | K52: 10.3390/genes14020521
A53: 30398125 | B53: Leukocytoclastic Vasculitis Associated with HHV6-A/ciHHV6-A and HHV6-B Coinfection in an Immunocompetent Woman | C53: Calvario A, Foti C, Scarasciulli M, Romita P, Eliassen E, Marzullo A, Colacicco AM, Miragliotta G. | D53: Endocr Metab Immune Disord Drug Targets. 2019;19(2):221-225. doi: 10.2174/1871530318666181106153758. | E53: Calvario A | F53: Endocr Metab Immune Disord Drug Targets | G53: 2019 | H53: 43411 | K53: 10.2174/1871530318666181106153758
A54: 21400833 | B54: [HHV-6 encephalopathy] | C54: Kawamura Y, Yoshikawa T. | D54: Nihon Rinsho. 2011 Mar;69(3):423-8. | E54: Kawamura Y | F54: Nihon Rinsho | G54: 2011 | H54: 40618
A55: 11964854 | B55: Fifth (human parvovirus) and sixth (herpesvirus 6) diseases | C55: Koch WC. | D55: Curr Opin Infect Dis. 2001 Jun;14(3):343-56. doi: 10.1097/00001432-200106000-00016. | E55: Koch WC | F55: Curr Opin Infect Dis | G55: 2001 | H55: 37366 | K55: 10.1097/00001432-200106000-00016
A56: 32295911 | B56: gp96 Is Critical for both Human Herpesvirus 6A (HHV-6A) and HHV-6B Infections | C56: Ma J, Jia J, Jiang X, Xu M, Guo J, Tang T, Xu X, Wu Z, Hu B, Yao K, Li L, Tang H. | D56: J Virol. 2020 Jun 16;94(13):e00311-20. doi: 10.1128/JVI.00311-20. Print 2020 Jun 16. | E56: Ma J | F56: J Virol | G56: 2020 | H56: 43938 | I56: PMC7307172 | K56: 10.1128/JVI.00311-20
A57: 38918446 | B57: Fetal cord plasma herpesviruses and preeclampsia: an observational cohort study | C57: Häkkinen I, Yazgeldi Gunaydin G, Pyöriä L, Kojima S, Parrish N, Perdomo MF, Wedenoja J, Hedman K, Heinonen S, Kajantie E, Laivuori H, Kere J, Katayama S, Wedenoja S. | D57: Sci Rep. 2024 Jun 25;14(1):14605. doi: 10.1038/s41598-024-65386-6. | E57: Häkkinen I | F57: Sci Rep | G57: 2024 | H57: 45468 | I57: PMC11199493 | K57: 10.1038/s41598-024-65386-6
A58: 32908059 | B58: [Human herpesvirus-6B encephalitis following allogeneic hematopoietic stem cell transplantation: how should it be managed?] | C58: Ogata M. | D58: Rinsho Ketsueki. 2020;61(8):945-952. doi: 10.11406/rinketsu.61.945. | E58: Ogata M | F58: Rinsho Ketsueki | G58: 2020 | H58: 44084 | K58: 10.11406/rinketsu.61.945
A59: 31075291 | B59: Human herpesvirus 6 infection after autologous stem cell transplantation: A multicenter prospective study in adult patients | C59: Balsat M, Pillet S, Tavernier E, Cacheux V, Escuret V, Moluçon-Chabrot C, Augeul-Meunier K, Mirand A, Regagnon C, Tinquaut F, Bousser V, Oriol M, Guyotat D, Salles G, Bay JO, Pozzetto B, Cornillon J. | D59: J Infect. 2019 Jul;79(1):36-42. doi: 10.1016/j.jinf.2019.05.001. Epub 2019 May 7. | E59: Balsat M | F59: J Infect | G59: 2019 | H59: 43596 | K59: 10.1016/j.jinf.2019.05.001
A60: 1365539 | B60: Pathogenesis of human herpesvirus 6 (HHV-6) | C60: Yamanishi K. | D60: Infect Agents Dis. 1992 Jun;1(3):149-55. | E60: Yamanishi K | F60: Infect Agents Dis | G60: 1992 | H60: 33756
A61: 29698478 | B61: Cross-sectional analysis of CD8 T cell immunity to human herpesvirus 6B | C61: Martin LK, Hollaus A, Stahuber A, Hübener C, Fraccaroli A, Tischer J, Schub A, Moosmann A. | D61: PLoS Pathog. 2018 Apr 26;14(4):e1006991. doi: 10.1371/journal.ppat.1006991. eCollection 2018 Apr. | E61: Martin LK | F61: PLoS Pathog | G61: 2018 | H61: 43217 | I61: PMC5919459 | K61: 10.1371/journal.ppat.1006991
A62: 30996090 | B62: Phenotypic and Functional Differences between Human Herpesvirus 6- and Human Cytomegalovirus-Specific T Cells | C62: Fastenackels S, Bayard C, Larsen M, Magnier P, Bonnafous P, Seddiki N, Appay V, Gautheret-Dejean A, Sauce D. | D62: J Virol. 2019 Jun 14;93(13):e02321-18. doi: 10.1128/JVI.02321-18. Print 2019 Jul 1. | E62: Fastenackels S | F62: J Virol | G62: 2019 | H62: 43574 | I62: PMC6580948 | K62: 10.1128/JVI.02321-18
A63: 35444636 | B63: Structural Models for Roseolovirus U20 And U21: Non-Classical MHC-I Like Proteins From HHV-6A, HHV-6B, and HHV-7 | C63: Weaver GC, Arya R, Schneider CL, Hudson AW, Stern LJ. | D63: Front Immunol. 2022 Apr 4;13:864898. doi: 10.3389/fimmu.2022.864898. eCollection 2022. | E63: Weaver GC | F63: Front Immunol | G63: 2022 | H63: 44672 | I63: PMC9013968 | K63: 10.3389/fimmu.2022.864898
A64: 21488335 | B64: [Human herpesvirus-6 and human herpesvirus-7 (HHV-6, HHV-7)] | C64: Tang H, Sadaoka T, Mori Y. | D64: Uirusu. 2010 Dec;60(2):221-35. doi: 10.2222/jsv.60.221. | E64: Tang H | F64: Uirusu | G64: 2010 | H64: 40648 | K64: 10.2222/jsv.60.221
A65: 27697585 | B65: Human Herpesvirus 6 Infection Following Haploidentical Transplantation: Immune Recovery and Outcome | C65: Greco R, Crucitti L, Noviello M, Racca S, Mannina D, Forcina A, Lorentino F, Valtolina V, Rolla S, Dvir R, Morelli M, Giglio F, Barbanti MC, Lupo Stanghellini MT, Oltolini C, Vago L, Scarpellini P, Assanelli A, Carrabba MG, Marktel S, Bernardi M, Corti C, Clementi M, Peccatori J, Bonini C, Ciceri F. | D65: Biol Blood Marrow Transplant. 2016 Dec;22(12):2250-2255. doi: 10.1016/j.bbmt.2016.09.018. Epub 2016 Sep 30. | E65: Greco R | F65: Biol Blood Marrow Transplant | G65: 2016 | H65: 42648 | K65: 10.1016/j.bbmt.2016.09.018
A66: 1314102 | B66: Human herpesvirus type 6: review | C66: Oren I, Sobel JD. | D66: Clin Infect Dis. 1992 Mar;14(3):741-6. doi: 10.1093/clinids/14.3.741. | E66: Oren I | F66: Clin Infect Dis | G66: 1992 | H66: 33664 | K66: 10.1093/clinids/14.3.741
A67: 35019717 | B67: CD46 Isoforms Influence the Mode of Entry by Human Herpesvirus 6A/B in T Cells | C67: Rossen LS, Schack VR, Thuesen KKH, Bundgaard B, Höllsberg P. | D67: J Virol. 2022 Mar 9;96(5):e0155721. doi: 10.1128/JVI.01557-21. Epub 2022 Jan 12. | E67: Rossen LS | F67: J Virol | G67: 2022 | H67: 44573 | I67: PMC8906420 | K67: 10.1128/JVI.01557-21
A68: 11427741 | B68: Human herpesviruses 6 and 7: effects on hematopoiesis and mode of transmission | C68: Yamada M. | D68: Jpn J Infect Dis. 2001 Apr;54(2):47-54. | E68: Yamada M | F68: Jpn J Infect Dis | G68: 2001 | H68: 37070
